Workbook

Sheet Template
A1: Count | B1: Transaction Number | C1: Detail # | D1: Date | E1: Establishment Id | F1: Establishment | G1: Branch | H1: Payment Type | I1: Amount | J1: Account | K1: Quantity | L1: Unit Price | M1: Amount | N1: Total | O1: Item ID | P1: Brand | Q1: Type | R1: Details | S1: Notes
A2: =IF(OR(D2<>D1,D2=""),1,IF(NOT(AND(E2=E1,F2=F1,G2=G1)),A1+1,IF(OR(H2="",AND(H2<>"",H2<>H1,H1<>"")),A1,A1+1))) -> 1 | B2: =IF(D2<>"",TEXT(D2,"YYYYMMDD")&CHAR(64+A2),"") | C2: =IF(OR(B2="",B2<>B10),1,C10+1) -> 1 | F2: =INDEX(Establishment!B$2:B$1005,MATCH($E2,Establishment!$A$2:$A$1005,0)) -> #N/A | G2: =INDEX(Establishment!C$2:C$1005,MATCH($E2,Establishment!$A$2:$A$1005,0)) -> #N/A | M2: =K2*L2 -> 0 | N2: =IF(B2=B1,N1+M2,M2) -> 0 | P2: =INDEX(Items!B$2:B$1032,MATCH($O2,Items!$A$2:$A$1032,0)) -> #N/A | Q2: =INDEX(Items!C$2:C$1032,MATCH($O2,Items!$A$2:$A$1032,0)) -> #N/A | R2: =INDEX(Items!D$2:D$1032,MATCH($O2,Items!$A$2:$A$1032,0)) -> #N/A
A3: =IF(OR(D3<>D2,D3=""),1,IF(NOT(AND(E3=E2,F3=F2,G3=G2)),A2+1,IF(OR(H3="",AND(H3<>"",H3<>H2,H2<>"")),A2,A2+1))) -> 1 | B3: =IF(D3<>"",TEXT(D3,"YYYYMMDD")&CHAR(64+A3),"") | C3: =IF(OR(B3="",B3<>B11),1,C11+1) -> 1 | F3: =INDEX(Establishment!B$2:B$1005,MATCH($E3,Establishment!$A$2:$A$1005,0)) -> #N/A | G3: =INDEX(Establishment!C$2:C$1005,MATCH($E3,Establishment!$A$2:$A$1005,0)) -> #N/A | M3: =K3*L3 -> 0 | N3: =IF(B3=B2,N2+M3,M3) -> 0 | P3: =INDEX(Items!B$2:B$1032,MATCH($O3,Items!$A$2:$A$1032,0)) -> #N/A | Q3: =INDEX(Items!C$2:C$1032,MATCH($O3,Items!$A$2:$A$1032,0)) -> #N/A | R3: =INDEX(Items!D$2:D$1032,MATCH($O3,Items!$A$2:$A$1032,0)) -> #N/A
A4: =IF(OR(D4<>D3,D4=""),1,IF(NOT(AND(E4=E3,F4=F3,G4=G3)),A3+1,IF(OR(H4="",AND(H4<>"",H4<>H3,H3<>"")),A3,A3+1))) -> 1 | B4: =IF(D4<>"",TEXT(D4,"YYYYMMDD")&CHAR(64+A4),"") | C4: =IF(OR(B4="",B4<>B12),1,C12+1) -> 1 | F4: =INDEX(Establishment!B$2:B$1005,MATCH($E4,Establishment!$A$2:$A$1005,0)) -> #N/A | G4: =INDEX(Establishment!C$2:C$1005,MATCH($E4,Establishment!$A$2:$A$1005,0)) -> #N/A | M4: =K4*L4 -> 0 | N4: =IF(B4=B3,N3+M4,M4) -> 0 | P4: =INDEX(Items!B$2:B$1032,MATCH($O4,Items!$A$2:$A$1032,0)) -> #N/A | Q4: =INDEX(Items!C$2:C$1032,MATCH($O4,Items!$A$2:$A$1032,0)) -> #N/A | R4: =INDEX(Items!D$2:D$1032,MATCH($O4,Items!$A$2:$A$1032,0)) -> #N/A
A5: =IF(OR(D5<>D4,D5=""),1,IF(NOT(AND(E5=E4,F5=F4,G5=G4)),A4+1,IF(OR(H5="",AND(H5<>"",H5<>H4,H4<>"")),A4,A4+1))) -> 1 | B5: =IF(D5<>"",TEXT(D5,"YYYYMMDD")&CHAR(64+A5),"") | C5: =IF(OR(B5="",B5<>B13),1,C13+1) -> 1 | F5: =INDEX(Establishment!B$2:B$1005,MATCH($E5,Establishment!$A$2:$A$1005,0)) -> #N/A | G5: =INDEX(Establishment!C$2:C$1005,MATCH($E5,Establishment!$A$2:$A$1005,0)) -> #N/A | M5: =K5*L5 -> 0 | N5: =IF(B5=B4,N4+M5,M5) -> 0 | P5: =INDEX(Items!B$2:B$1032,MATCH($O5,Items!$A$2:$A$1032,0)) -> #N/A | Q5: =INDEX(Items!C$2:C$1032,MATCH($O5,Items!$A$2:$A$1032,0)) -> #N/A | R5: =INDEX(Items!D$2:D$1032,MATCH($O5,Items!$A$2:$A$1032,0)) -> #N/A
A6: =IF(OR(D6<>D5,D6=""),1,IF(NOT(AND(E6=E5,F6=F5,G6=G5)),A5+1,IF(OR(H6="",AND(H6<>"",H6<>H5,H5<>"")),A5,A5+1))) -> 1 | B6: =IF(D6<>"",TEXT(D6,"YYYYMMDD")&CHAR(64+A6),"") | C6: =IF(OR(B6="",B6<>B14),1,C14+1) -> 1 | F6: =INDEX(Establishment!B$2:B$1005,MATCH($E6,Establishment!$A$2:$A$1005,0)) -> #N/A | G6: =INDEX(Establishment!C$2:C$1005,MATCH($E6,Establishment!$A$2:$A$1005,0)) -> #N/A | M6: =K6*L6 -> 0 | N6: =IF(B6=B5,N5+M6,M6) -> 0 | P6: =INDEX(Items!B$2:B$1032,MATCH($O6,Items!$A$2:$A$1032,0)) -> #N/A | Q6: =INDEX(Items!C$2:C$1032,MATCH($O6,Items!$A$2:$A$1032,0)) -> #N/A | R6: =INDEX(Items!D$2:D$1032,MATCH($O6,Items!$A$2:$A$1032,0)) -> #N/A
A7: =IF(OR(D7<>D6,D7=""),1,IF(NOT(AND(E7=E6,F7=F6,G7=G6)),A6+1,IF(OR(H7="",AND(H7<>"",H7<>H6,H6<>"")),A6,A6+1))) -> 1 | B7: =IF(D7<>"",TEXT(D7,"YYYYMMDD")&CHAR(64+A7),"") | C7: =IF(OR(B7="",B7<>B15),1,C15+1) -> 1 | F7: =INDEX(Establishment!B$2:B$1005,MATCH($E7,Establishment!$A$2:$A$1005,0)) -> #N/A | G7: =INDEX(Establishment!C$2:C$1005,MATCH($E7,Establishment!$A$2:$A$1005,0)) -> #N/A | M7: =K7*L7 -> 0 | N7: =IF(B7=B6,N6+M7,M7) -> 0 | P7: =INDEX(Items!B$2:B$1032,MATCH($O7,Items!$A$2:$A$1032,0)) -> #N/A | Q7: =INDEX(Items!C$2:C$1032,MATCH($O7,Items!$A$2:$A$1032,0)) -> #N/A | R7: =INDEX(Items!D$2:D$1032,MATCH($O7,Items!$A$2:$A$1032,0)) -> #N/A
A8: =IF(OR(D8<>D7,D8=""),1,IF(NOT(AND(E8=E7,F8=F7,G8=G7)),A7+1,IF(OR(H8="",AND(H8<>"",H8<>H7,H7<>"")),A7,A7+1))) -> 1 | B8: =IF(D8<>"",TEXT(D8,"YYYYMMDD")&CHAR(64+A8),"") | C8: =IF(OR(B8="",B8<>B7),1,C7+1) -> 1 | F8: =INDEX(Establishment!B$2:B$1005,MATCH($E8,Establishment!$A$2:$A$1005,0)) -> #N/A | G8: =INDEX(Establishment!C$2:C$1005,MATCH($E8,Establishment!$A$2:$A$1005,0)) -> #N/A | M8: =K8*L8 -> 0 | N8: =IF(B8=B7,N7+M8,M8) -> 0 | P8: =INDEX(Items!B$2:B$1032,MATCH($O8,Items!$A$2:$A$1032,0)) -> #N/A | Q8: =INDEX(Items!C$2:C$1032,MATCH($O8,Items!$A$2:$A$1032,0)) -> #N/A | R8: =INDEX(Items!D$2:D$1032,MATCH($O8,Items!$A$2:$A$1032,0)) -> #N/A
A9: =IF(OR(D9<>D8,D9=""),1,IF(NOT(AND(E9=E8,F9=F8,G9=G8)),A8+1,IF(OR(H9="",AND(H9<>"",H9<>H8,H8<>"")),A8,A8+1))) -> 1 | B9: =IF(D9<>"",TEXT(D9,"YYYYMMDD")&CHAR(64+A9),"") | C9: =IF(OR(B9="",B9<>B8),1,C8+1) -> 1 | F9: =INDEX(Establishment!B$2:B$1005,MATCH($E9,Establishment!$A$2:$A$1005,0)) -> #N/A | G9: =INDEX(Establishment!C$2:C$1005,MATCH($E9,Establishment!$A$2:$A$1005,0)) -> #N/A | M9: =K9*L9 -> 0 | N9: =IF(B9=B8,N8+M9,M9) -> 0 | P9: =INDEX(Items!B$2:B$1032,MATCH($O9,Items!$A$2:$A$1032,0)) -> #N/A | Q9: =INDEX(Items!C$2:C$1032,MATCH($O9,Items!$A$2:$A$1032,0)) -> #N/A | R9: =INDEX(Items!D$2:D$1032,MATCH($O9,Items!$A$2:$A$1032,0)) -> #N/A
A10: =IF(OR(D10<>D9,D10=""),1,IF(NOT(AND(E10=E9,F10=F9,G10=G9)),A9+1,IF(OR(H10="",AND(H10<>"",H10<>H9,H9<>"")),A9,A9+1))) -> 1 | B10: =IF(D10<>"",TEXT(D10,"YYYYMMDD")&CHAR(64+A10),"") | C10: =IF(OR(B10="",B10<>B9),1,C9+1) -> 1 | F10: =INDEX(Establishment!B$2:B$1005,MATCH($E10,Establishment!$A$2:$A$1005,0)) -> #N/A | G10: =INDEX(Establishment!C$2:C$1005,MATCH($E10,Establishment!$A$2:$A$1005,0)) -> #N/A | M10: =K10*L10 -> 0 | N10: =IF(B10=B9,N9+M10,M10) -> 0 | P10: =INDEX(Items!B$2:B$1032,MATCH($O10,Items!$A$2:$A$1032,0)) -> #N/A | Q10: =INDEX(Items!C$2:C$1032,MATCH($O10,Items!$A$2:$A$1032,0)) -> #N/A | R10: =INDEX(Items!D$2:D$1032,MATCH($O10,Items!$A$2:$A$1032,0)) -> #N/A
A11: =IF(OR(D11<>D10,D11=""),1,IF(NOT(AND(E11=E10,F11=F10,G11=G10)),A10+1,IF(OR(H11="",AND(H11<>"",H11<>H10,H10<>"")),A10,A10+1))) -> 1 | B11: =IF(D11<>"",TEXT(D11,"YYYYMMDD")&CHAR(64+A11),"") | C11: =IF(OR(B11="",B11<>B10),1,C10+1) -> 1 | F11: =INDEX(Establishment!B$2:B$1005,MATCH($E11,Establishment!$A$2:$A$1005,0)) -> #N/A | G11: =INDEX(Establishment!C$2:C$1005,MATCH($E11,Establishment!$A$2:$A$1005,0)) -> #N/A | M11: =K11*L11 -> 0 | N11: =IF(B11=B10,N10+M11,M11) -> 0 | P11: =INDEX(Items!B$2:B$1032,MATCH($O11,Items!$A$2:$A$1032,0)) -> #N/A | Q11: =INDEX(Items!C$2:C$1032,MATCH($O11,Items!$A$2:$A$1032,0)) -> #N/A | R11: =INDEX(Items!D$2:D$1032,MATCH($O11,Items!$A$2:$A$1032,0)) -> #N/A
A12: =IF(OR(D12<>D11,D12=""),1,IF(NOT(AND(E12=E11,F12=F11,G12=G11)),A11+1,IF(OR(H12="",AND(H12<>"",H12<>H11,H11<>"")),A11,A11+1))) -> 1 | B12: =IF(D12<>"",TEXT(D12,"YYYYMMDD")&CHAR(64+A12),"") | C12: =IF(OR(B12="",B12<>B11),1,C11+1) -> 1 | F12: =INDEX(Establishment!B$2:B$1005,MATCH($E12,Establishment!$A$2:$A$1005,0)) -> #N/A | G12: =INDEX(Establishment!C$2:C$1005,MATCH($E12,Establishment!$A$2:$A$1005,0)) -> #N/A | M12: =K12*L12 -> 0 | N12: =IF(B12=B11,N11+M12,M12) -> 0 | P12: =INDEX(Items!B$2:B$1032,MATCH($O12,Items!$A$2:$A$1032,0)) -> #N/A | Q12: =INDEX(Items!C$2:C$1032,MATCH($O12,Items!$A$2:$A$1032,0)) -> #N/A | R12: =INDEX(Items!D$2:D$1032,MATCH($O12,Items!$A$2:$A$1032,0)) -> #N/A
A13: =IF(OR(D13<>D12,D13=""),1,IF(NOT(AND(E13=E12,F13=F12,G13=G12)),A12+1,IF(OR(H13="",AND(H13<>"",H13<>H12,H12<>"")),A12,A12+1))) -> 1 | B13: =IF(D13<>"",TEXT(D13,"YYYYMMDD")&CHAR(64+A13),"") | C13: =IF(OR(B13="",B13<>B12),1,C12+1) -> 1 | F13: =INDEX(Establishment!B$2:B$1005,MATCH($E13,Establishment!$A$2:$A$1005,0)) -> #N/A | G13: =INDEX(Establishment!C$2:C$1005,MATCH($E13,Establishment!$A$2:$A$1005,0)) -> #N/A | M13: =K13*L13 -> 0 | N13: =IF(B13=B12,N12+M13,M13) -> 0 | P13: =INDEX(Items!B$2:B$1032,MATCH($O13,Items!$A$2:$A$1032,0)) -> #N/A | Q13: =INDEX(Items!C$2:C$1032,MATCH($O13,Items!$A$2:$A$1032,0)) -> #N/A | R13: =INDEX(Items!D$2:D$1032,MATCH($O13,Items!$A$2:$A$1032,0)) -> #N/A
A14: =IF(OR(D14<>D13,D14=""),1,IF(NOT(AND(E14=E13,F14=F13,G14=G13)),A13+1,IF(OR(H14="",AND(H14<>"",H14<>H13,H13<>"")),A13,A13+1))) -> 1 | B14: =IF(D14<>"",TEXT(D14,"YYYYMMDD")&CHAR(64+A14),"") | C14: =IF(OR(B14="",B14<>B13),1,C13+1) -> 1 | F14: =INDEX(Establishment!B$2:B$1005,MATCH($E14,Establishment!$A$2:$A$1005,0)) -> #N/A | G14: =INDEX(Establishment!C$2:C$1005,MATCH($E14,Establishment!$A$2:$A$1005,0)) -> #N/A | M14: =K14*L14 -> 0 | N14: =IF(B14=B13,N13+M14,M14) -> 0 | P14: =INDEX(Items!B$2:B$1032,MATCH($O14,Items!$A$2:$A$1032,0)) -> #N/A | Q14: =INDEX(Items!C$2:C$1032,MATCH($O14,Items!$A$2:$A$1032,0)) -> #N/A | R14: =INDEX(Items!D$2:D$1032,MATCH($O14,Items!$A$2:$A$1032,0)) -> #N/A
A15: =IF(OR(D15<>D14,D15=""),1,IF(NOT(AND(E15=E14,F15=F14,G15=G14)),A14+1,IF(OR(H15="",AND(H15<>"",H15<>H14,H14<>"")),A14,A14+1))) -> 1 | B15: =IF(D15<>"",TEXT(D15,"YYYYMMDD")&CHAR(64+A15),"") | C15: =IF(OR(B15="",B15<>B14),1,C14+1) -> 1 | F15: =INDEX(Establishment!B$2:B$1005,MATCH($E15,Establishment!$A$2:$A$1005,0)) -> #N/A | G15: =INDEX(Establishment!C$2:C$1005,MATCH($E15,Establishment!$A$2:$A$1005,0)) -> #N/A | M15: =K15*L15 -> 0 | N15: =IF(B15=B14,N14+M15,M15) -> 0 | P15: =INDEX(Items!B$2:B$1032,MATCH($O15,Items!$A$2:$A$1032,0)) -> #N/A | Q15: =INDEX(Items!C$2:C$1032,MATCH($O15,Items!$A$2:$A$1032,0)) -> #N/A | R15: =INDEX(Items!D$2:D$1032,MATCH($O15,Items!$A$2:$A$1032,0)) -> #N/A
A16: =IF(OR(D16<>D15,D16=""),1,IF(NOT(AND(E16=E15,F16=F15,G16=G15)),A15+1,IF(OR(H16="",AND(H16<>"",H16<>H15,H15<>"")),A15,A15+1))) -> 1 | B16: =IF(D16<>"",TEXT(D16,"YYYYMMDD")&CHAR(64+A16),"") | C16: =IF(OR(B16="",B16<>B15),1,C15+1) -> 1 | F16: =INDEX(Establishment!B$2:B$1005,MATCH($E16,Establishment!$A$2:$A$1005,0)) -> #N/A | G16: =INDEX(Establishment!C$2:C$1005,MATCH($E16,Establishment!$A$2:$A$1005,0)) -> #N/A | M16: =K16*L16 -> 0 | N16: =IF(B16=B15,N15+M16,M16) -> 0 | P16: =INDEX(Items!B$2:B$1032,MATCH($O16,Items!$A$2:$A$1032,0)) -> #N/A | Q16: =INDEX(Items!C$2:C$1032,MATCH($O16,Items!$A$2:$A$1032,0)) -> #N/A | R16: =INDEX(Items!D$2:D$1032,MATCH($O16,Items!$A$2:$A$1032,0)) -> #N/A
A17: =IF(OR(D17<>D16,D17=""),1,IF(NOT(AND(E17=E16,F17=F16,G17=G16)),A16+1,IF(OR(H17="",AND(H17<>"",H17<>H16,H16<>"")),A16,A16+1))) -> 1 | B17: =IF(D17<>"",TEXT(D17,"YYYYMMDD")&CHAR(64+A17),"") | C17: =IF(OR(B17="",B17<>B16),1,C16+1) -> 1 | F17: =INDEX(Establishment!B$2:B$1005,MATCH($E17,Establishment!$A$2:$A$1005,0)) -> #N/A | G17: =INDEX(Establishment!C$2:C$1005,MATCH($E17,Establishment!$A$2:$A$1005,0)) -> #N/A | M17: =K17*L17 -> 0 | N17: =IF(B17=B16,N16+M17,M17) -> 0 | P17: =INDEX(Items!B$2:B$1032,MATCH($O17,Items!$A$2:$A$1032,0)) -> #N/A | Q17: =INDEX(Items!C$2:C$1032,MATCH($O17,Items!$A$2:$A$1032,0)) -> #N/A | R17: =INDEX(Items!D$2:D$1032,MATCH($O17,Items!$A$2:$A$1032,0)) -> #N/A
A18: =IF(OR(D18<>D17,D18=""),1,IF(NOT(AND(E18=E17,F18=F17,G18=G17)),A17+1,IF(OR(H18="",AND(H18<>"",H18<>H17,H17<>"")),A17,A17+1))) -> 1 | B18: =IF(D18<>"",TEXT(D18,"YYYYMMDD")&CHAR(64+A18),"") | C18: =IF(OR(B18="",B18<>B17),1,C17+1) -> 1 | F18: =INDEX(Establishment!B$2:B$1005,MATCH($E18,Establishment!$A$2:$A$1005,0)) -> #N/A | G18: =INDEX(Establishment!C$2:C$1005,MATCH($E18,Establishment!$A$2:$A$1005,0)) -> #N/A | M18: =K18*L18 -> 0 | N18: =IF(B18=B17,N17+M18,M18) -> 0 | P18: =INDEX(Items!B$2:B$1032,MATCH($O18,Items!$A$2:$A$1032,0)) -> #N/A | Q18: =INDEX(Items!C$2:C$1032,MATCH($O18,Items!$A$2:$A$1032,0)) -> #N/A | R18: =INDEX(Items!D$2:D$1032,MATCH($O18,Items!$A$2:$A$1032,0)) -> #N/A
A19: =IF(OR(D19<>D18,D19=""),1,IF(NOT(AND(E19=E18,F19=F18,G19=G18)),A18+1,IF(OR(H19="",AND(H19<>"",H19<>H18,H18<>"")),A18,A18+1))) -> 1 | B19: =IF(D19<>"",TEXT(D19,"YYYYMMDD")&CHAR(64+A19),"") | C19: =IF(OR(B19="",B19<>B18),1,C18+1) -> 1 | F19: =INDEX(Establishment!B$2:B$1005,MATCH($E19,Establishment!$A$2:$A$1005,0)) -> #N/A | G19: =INDEX(Establishment!C$2:C$1005,MATCH($E19,Establishment!$A$2:$A$1005,0)) -> #N/A | M19: =K19*L19 -> 0 | N19: =IF(B19=B18,N18+M19,M19) -> 0 | P19: =INDEX(Items!B$2:B$1032,MATCH($O19,Items!$A$2:$A$1032,0)) -> #N/A | Q19: =INDEX(Items!C$2:C$1032,MATCH($O19,Items!$A$2:$A$1032,0)) -> #N/A | R19: =INDEX(Items!D$2:D$1032,MATCH($O19,Items!$A$2:$A$1032,0)) -> #N/A
... A25: =IF(OR(D25<>D24,D25=""),1,IF(NOT(AND(E25=E24,F25=F24,G25=G24)),A24+1,IF(OR(H25="",AND(H25<>"",H25<>H24,H24<>"")),A24,A24+1))) -> 1 | B25: =IF(D25<>"",TEXT(D25,"YYYYMMDD")&CHAR(64+A25),"") | C25: =IF(OR(B25="",B25<>B24),1,C24+1) -> 1 | F25: =INDEX(Establishment!B$2:B$1005,MATCH($E25,Establishment!$A$2:$A$1005,0)) -> #N/A | G25: =INDEX(Establishment!C$2:C$1005,MATCH($E25,Establishment!$A$2:$A$1005,0)) -> #N/A | M25: =K25*L25 -> 0 | N25: =IF(B25=B24,N24+M25,M25) -> 0 | P25: =INDEX(Items!B$2:B$1032,MATCH($O25,Items!$A$2:$A$1032,0)) -> #N/A | Q25: =INDEX(Items!C$2:C$1032,MATCH($O25,Items!$A$2:$A$1032,0)) -> #N/A | R25: =INDEX(Items!D$2:D$1032,MATCH($O25,Items!$A$2:$A$1032,0)) -> #N/A
A26: =IF(OR(D26<>D25,D26=""),1,IF(NOT(AND(E26=E25,F26=F25,G26=G25)),A25+1,IF(OR(H26="",AND(H26<>"",H26<>H25,H25<>"")),A25,A25+1))) -> 1 | B26: =IF(D26<>"",TEXT(D26,"YYYYMMDD")&CHAR(64+A26),"") | C26: =IF(OR(B26="",B26<>B25),1,C25+1) -> 1 | F26: Street Vendor | G26: Fried Chicken Seller | M26: =K26*L26 -> 0 | N26: =IF(B26=B25,N25+M26,M26) -> 0 | P26: =INDEX(Items!B$2:B$1032,MATCH($O26,Items!$A$2:$A$1032,0)) -> #N/A | Q26: =INDEX(Items!C$2:C$1032,MATCH($O26,Items!$A$2:$A$1032,0)) -> #N/A | R26: =INDEX(Items!D$2:D$1032,MATCH($O26,Items!$A$2:$A$1032,0)) -> #N/A
A27: =IF(OR(D27<>D26,D27=""),1,IF(NOT(AND(E27=E26,F27=F26,G27=G26)),A26+1,IF(OR(H27="",AND(H27<>"",H27<>H26,H26<>"")),A26,A26+1))) -> 1 | B27: =IF(D27<>"",TEXT(D27,"YYYYMMDD")&CHAR(64+A27),"") | C27: =IF(OR(B27="",B27<>B26),1,C26+1) -> 1 | F27: Street Vendor | G27: Fried Chicken Seller | M27: =K27*L27 -> 0 | N27: =IF(B27=B26,N26+M27,M27) -> 0 | P27: =INDEX(Items!B$2:B$1032,MATCH($O27,Items!$A$2:$A$1032,0)) -> #N/A | Q27: =INDEX(Items!C$2:C$1032,MATCH($O27,Items!$A$2:$A$1032,0)) -> #N/A | R27: =INDEX(Items!D$2:D$1032,MATCH($O27,Items!$A$2:$A$1032,0)) -> #N/A
A28: =IF(OR(D28<>D27,D28=""),1,IF(NOT(AND(E28=E27,F28=F27,G28=G27)),A27+1,IF(OR(H28="",AND(H28<>"",H28<>H27,H27<>"")),A27,A27+1))) -> 1 | B28: =IF(D28<>"",TEXT(D28,"YYYYMMDD")&CHAR(64+A28),"") | C28: =IF(OR(B28="",B28<>B27),1,C27+1) -> 1 | F28: Street Vendor | G28: Fried Chicken Seller | M28: =K28*L28 -> 0 | N28: =IF(B28=B27,N27+M28,M28) -> 0 | P28: =INDEX(Items!B$2:B$1032,MATCH($O28,Items!$A$2:$A$1032,0)) -> #N/A | Q28: =INDEX(Items!C$2:C$1032,MATCH($O28,Items!$A$2:$A$1032,0)) -> #N/A | R28: =INDEX(Items!D$2:D$1032,MATCH($O28,Items!$A$2:$A$1032,0)) -> #N/A
A29: =IF(OR(D29<>D28,D29=""),1,IF(NOT(AND(E29=E28,F29=F28,G29=G28)),A28+1,IF(OR(H29="",AND(H29<>"",H29<>H28,H28<>"")),A28,A28+1))) -> 1 | B29: =IF(D29<>"",TEXT(D29,"YYYYMMDD")&CHAR(64+A29),"") | C29: =IF(OR(B29="",B29<>B28),1,C28+1) -> 1 | F29: =INDEX(Establishment!B$2:B$1005,MATCH($E29,Establishment!$A$2:$A$1005,0)) -> #N/A | G29: =INDEX(Establishment!C$2:C$1005,MATCH($E29,Establishment!$A$2:$A$1005,0)) -> #N/A | M29: =K29*L29 -> 0 | N29: =IF(B29=B28,N28+M29,M29) -> 0 | P29: =INDEX(Items!B$2:B$1032,MATCH($O29,Items!$A$2:$A$1032,0)) -> #N/A | Q29: =INDEX(Items!C$2:C$1032,MATCH($O29,Items!$A$2:$A$1032,0)) -> #N/A | R29: =INDEX(Items!D$2:D$1032,MATCH($O29,Items!$A$2:$A$1032,0)) -> #N/A
A30: =IF(OR(D30<>D29,D30=""),1,IF(NOT(AND(E30=E29,F30=F29,G30=G29)),A29+1,IF(OR(H30="",AND(H30<>"",H30<>H29,H29<>"")),A29,A29+1))) -> 1 | B30: =IF(D30<>"",TEXT(D30,"YYYYMMDD")&CHAR(64+A30),"") | C30: =IF(OR(B30="",B30<>B29),1,C29+1) -> 1 | F30: =INDEX(Establishment!B$2:B$1005,MATCH($E30,Establishment!$A$2:$A$1005,0)) -> #N/A | G30: =INDEX(Establishment!C$2:C$1005,MATCH($E30,Establishment!$A$2:$A$1005,0)) -> #N/A | M30: =K30*L30 -> 0 | N30: =IF(B30=B29,N29+M30,M30) -> 0 | P30: =INDEX(Items!B$2:B$1032,MATCH($O30,Items!$A$2:$A$1032,0)) -> #N/A | Q30: =INDEX(Items!C$2:C$1032,MATCH($O30,Items!$A$2:$A$1032,0)) -> #N/A | R30: =INDEX(Items!D$2:D$1032,MATCH($O30,Items!$A$2:$A$1032,0)) -> #N/A
A31: =IF(OR(D31<>D30,D31=""),1,IF(NOT(AND(E31=E30,F31=F30,G31=G30)),A30+1,IF(OR(H31="",AND(H31<>"",H31<>H30,H30<>"")),A30,A30+1))) -> 1 | B31: =IF(D31<>"",TEXT(D31,"YYYYMMDD")&CHAR(64+A31),"") | C31: =IF(OR(B31="",B31<>B30),1,C30+1) -> 1 | F31: =INDEX(Establishment!B$2:B$1005,MATCH($E31,Establishment!$A$2:$A$1005,0)) -> #N/A | G31: =INDEX(Establishment!C$2:C$1005,MATCH($E31,Establishment!$A$2:$A$1005,0)) -> #N/A | M31: =K31*L31 -> 0 | N31: =IF(B31=B30,N30+M31,M31) -> 0 | P31: =INDEX(Items!B$2:B$1032,MATCH($O31,Items!$A$2:$A$1032,0)) -> #N/A | Q31: =INDEX(Items!C$2:C$1032,MATCH($O31,Items!$A$2:$A$1032,0)) -> #N/A | R31: =INDEX(Items!D$2:D$1032,MATCH($O31,Items!$A$2:$A$1032,0)) -> #N/A
A32: =IF(OR(D32<>D31,D32=""),1,IF(NOT(AND(E32=E31,F32=F31,G32=G31)),A31+1,IF(OR(H32="",AND(H32<>"",H32<>H31,H31<>"")),A31,A31+1))) -> 1 | B32: =IF(D32<>"",TEXT(D32,"YYYYMMDD")&CHAR(64+A32),"") | C32: =IF(OR(B32="",B32<>B31),1,C31+1) -> 1 | F32: Street Vendor | G32: B. Rodriguez | M32: =K32*L32 -> 0 | N32: =IF(B32=B31,N31+M32,M32) -> 0 | P32: =INDEX(Items!B$2:B$1032,MATCH($O32,Items!$A$2:$A$1032,0)) -> #N/A | Q32: =INDEX(Items!C$2:C$1032,MATCH($O32,Items!$A$2:$A$1032,0)) -> #N/A | R32: =INDEX(Items!D$2:D$1032,MATCH($O32,Items!$A$2:$A$1032,0)) -> #N/A
A33: =IF(OR(D33<>D32,D33=""),1,IF(NOT(AND(E33=E32,F33=F32,G33=G32)),A32+1,IF(OR(H33="",AND(H33<>"",H33<>H32,H32<>"")),A32,A32+1))) -> 1 | B33: =IF(D33<>"",TEXT(D33,"YYYYMMDD")&CHAR(64+A33),"") | C33: =IF(OR(B33="",B33<>B32),1,C32+1) -> 1 | F33: Street Vendor | G33: B. Rodriguez | M33: =K33*L33 -> 0 | N33: =IF(B33=B32,N32+M33,M33) -> 0 | P33: =INDEX(Items!B$2:B$1032,MATCH($O33,Items!$A$2:$A$1032,0)) -> #N/A | Q33: =INDEX(Items!C$2:C$1032,MATCH($O33,Items!$A$2:$A$1032,0)) -> #N/A | R33: =INDEX(Items!D$2:D$1032,MATCH($O33,Items!$A$2:$A$1032,0)) -> #N/A
A34: =IF(OR(D34<>D33,D34=""),1,IF(NOT(AND(E34=E33,F34=F33,G34=G33)),A33+1,IF(OR(H34="",AND(H34<>"",H34<>H33,H33<>"")),A33,A33+1))) -> 1 | B34: =IF(D34<>"",TEXT(D34,"YYYYMMDD")&CHAR(64+A34),"") | C34: =IF(OR(B34="",B34<>B33),1,C33+1) -> 1 | F34: Street Vendor | G34: B. Rodriguez | M34: =K34*L34 -> 0 | N34: =IF(B34=B33,N33+M34,M34) -> 0 | P34: =INDEX(Items!B$2:B$1032,MATCH($O34,Items!$A$2:$A$1032,0)) -> #N/A | Q34: =INDEX(Items!C$2:C$1032,MATCH($O34,Items!$A$2:$A$1032,0)) -> #N/A | R34: =INDEX(Items!D$2:D$1032,MATCH($O34,Items!$A$2:$A$1032,0)) -> #N/A
A35: =IF(OR(D35<>D34,D35=""),1,IF(NOT(AND(E35=E34,F35=F34,G35=G34)),A34+1,IF(OR(H35="",AND(H35<>"",H35<>H34,H34<>"")),A34,A34+1))) -> 1 | B35: =IF(D35<>"",TEXT(D35,"YYYYMMDD")&CHAR(64+A35),"") | C35: =IF(OR(B35="",B35<>B34),1,C34+1) -> 1 | F35: Street Vendor | G35: B. Rodriguez | M35: =K35*L35 -> 0 | N35: =IF(B35=B34,N34+M35,M35) -> 0 | P35: =INDEX(Items!B$2:B$1032,MATCH($O35,Items!$A$2:$A$1032,0)) -> #N/A | Q35: =INDEX(Items!C$2:C$1032,MATCH($O35,Items!$A$2:$A$1032,0)) -> #N/A | R35: =INDEX(Items!D$2:D$1032,MATCH($O35,Items!$A$2:$A$1032,0)) -> #N/A
A36: =IF(OR(D36<>D35,D36=""),1,IF(NOT(AND(E36=E35,F36=F35,G36=G35)),A35+1,IF(OR(H36="",AND(H36<>"",H36<>H35,H35<>"")),A35,A35+1))) -> 1 | B36: =IF(D36<>"",TEXT(D36,"YYYYMMDD")&CHAR(64+A36),"") | C36: =IF(OR(B36="",B36<>B35),1,C35+1) -> 1 | F36: Carenderia | G36: B. Rodriguez | M36: =K36*L36 -> 0 | N36: =IF(B36=B35,N35+M36,M36) -> 0 | P36: =INDEX(Items!B$2:B$1032,MATCH($O36,Items!$A$2:$A$1032,0)) -> #N/A | Q36: =INDEX(Items!C$2:C$1032,MATCH($O36,Items!$A$2:$A$1032,0)) -> #N/A | R36: =INDEX(Items!D$2:D$1032,MATCH($O36,Items!$A$2:$A$1032,0)) -> #N/A
A37: =IF(OR(D37<>D36,D37=""),1,IF(NOT(AND(E37=E36,F37=F36,G37=G36)),A36+1,IF(OR(H37="",AND(H37<>"",H37<>H36,H36<>"")),A36,A36+1))) -> 1 | B37: =IF(D37<>"",TEXT(D37,"YYYYMMDD")&CHAR(64+A37),"") | C37: =IF(OR(B37="",B37<>B36),1,C36+1) -> 1 | F37: Carenderia | G37: B. Rodriguez | M37: =K37*L37 -> 0 | N37: =IF(B37=B36,N36+M37,M37) -> 0 | P37: =INDEX(Items!B$2:B$1032,MATCH($O37,Items!$A$2:$A$1032,0)) -> #N/A | Q37: =INDEX(Items!C$2:C$1032,MATCH($O37,Items!$A$2:$A$1032,0)) -> #N/A | R37: =INDEX(Items!D$2:D$1032,MATCH($O37,Items!$A$2:$A$1032,0)) -> #N/A
A38: =IF(OR(D38<>D37,D38=""),1,IF(NOT(AND(E38=E37,F38=F37,G38=G37)),A37+1,IF(OR(H38="",AND(H38<>"",H38<>H37,H37<>"")),A37,A37+1))) -> 1 | B38: =IF(D38<>"",TEXT(D38,"YYYYMMDD")&CHAR(64+A38),"") | C38: =IF(OR(B38="",B38<>B37),1,C37+1) -> 1 | F38: Carenderia | G38: B. Rodriguez | M38: =K38*L38 -> 0 | N38: =IF(B38=B37,N37+M38,M38) -> 0 | P38: =INDEX(Items!B$2:B$1032,MATCH($O38,Items!$A$2:$A$1032,0)) -> #N/A | Q38: =INDEX(Items!C$2:C$1032,MATCH($O38,Items!$A$2:$A$1032,0)) -> #N/A | R38: =INDEX(Items!D$2:D$1032,MATCH($O38,Items!$A$2:$A$1032,0)) -> #N/A
A39: =IF(OR(D39<>D38,D39=""),1,IF(NOT(AND(E39=E38,F39=F38,G39=G38)),A38+1,IF(OR(H39="",AND(H39<>"",H39<>H38,H38<>"")),A38,A38+1))) -> 1 | B39: =IF(D39<>"",TEXT(D39,"YYYYMMDD")&CHAR(64+A39),"") | C39: =IF(OR(B39="",B39<>B38),1,C38+1) -> 1 | F39: Carenderia | G39: B. Rodriguez | M39: =K39*L39 -> 0 | N39: =IF(B39=B38,N38+M39,M39) -> 0 | P39: =INDEX(Items!B$2:B$1032,MATCH($O39,Items!$A$2:$A$1032,0)) -> #N/A | Q39: =INDEX(Items!C$2:C$1032,MATCH($O39,Items!$A$2:$A$1032,0)) -> #N/A | R39: =INDEX(Items!D$2:D$1032,MATCH($O39,Items!$A$2:$A$1032,0)) -> #N/A
A40: =IF(OR(D40<>D39,D40=""),1,IF(NOT(AND(E40=E39,F40=F39,G40=G39)),A39+1,IF(OR(H40="",AND(H40<>"",H40<>H39,H39<>"")),A39,A39+1))) -> 1 | B40: =IF(D40<>"",TEXT(D40,"YYYYMMDD")&CHAR(64+A40),"") | C40: =IF(OR(B40="",B40<>B39),1,C39+1) -> 1 | F40: Carenderia | G40: B. Rodriguez | M40: =K40*L40 -> 0 | N40: =IF(B40=B39,N39+M40,M40) -> 0 | P40: =INDEX(Items!B$2:B$1032,MATCH($O40,Items!$A$2:$A$1032,0)) -> #N/A | Q40: =INDEX(Items!C$2:C$1032,MATCH($O40,Items!$A$2:$A$1032,0)) -> #N/A | R40: =INDEX(Items!D$2:D$1032,MATCH($O40,Items!$A$2:$A$1032,0)) -> #N/A
A41: =IF(OR(D41<>D40,D41=""),1,IF(NOT(AND(E41=E40,F41=F40,G41=G40)),A40+1,IF(OR(H41="",AND(H41<>"",H41<>H40,H40<>"")),A40,A40+1))) -> 1 | B41: =IF(D41<>"",TEXT(D41,"YYYYMMDD")&CHAR(64+A41),"") | C41: =IF(OR(B41="",B41<>B40),1,C40+1) -> 1 | F41: Carenderia | G41: B. Rodriguez | M41: =K41*L41 -> 0 | N41: =IF(B41=B40,N40+M41,M41) -> 0 | P41: =INDEX(Items!B$2:B$1032,MATCH($O41,Items!$A$2:$A$1032,0)) -> #N/A | Q41: =INDEX(Items!C$2:C$1032,MATCH($O41,Items!$A$2:$A$1032,0)) -> #N/A | R41: =INDEX(Items!D$2:D$1032,MATCH($O41,Items!$A$2:$A$1032,0)) -> #N/A
A42: =IF(OR(D42<>D41,D42=""),1,IF(NOT(AND(E42=E41,F42=F41,G42=G41)),A41+1,IF(OR(H42="",AND(H42<>"",H42<>H41,H41<>"")),A41,A41+1))) -> 1 | B42: =IF(D42<>"",TEXT(D42,"YYYYMMDD")&CHAR(64+A42),"") | C42: =IF(OR(B42="",B42<>B41),1,C41+1) -> 1 | F42: Carenderia | G42: B. Rodriguez | M42: =K42*L42 -> 0 | N42: =IF(B42=B41,N41+M42,M42) -> 0 | P42: =INDEX(Items!B$2:B$1032,MATCH($O42,Items!$A$2:$A$1032,0)) -> #N/A | Q42: =INDEX(Items!C$2:C$1032,MATCH($O42,Items!$A$2:$A$1032,0)) -> #N/A | R42: =INDEX(Items!D$2:D$1032,MATCH($O42,Items!$A$2:$A$1032,0)) -> #N/A
A43: =IF(OR(D43<>D42,D43=""),1,IF(NOT(AND(E43=E42,F43=F42,G43=G42)),A42+1,IF(OR(H43="",AND(H43<>"",H43<>H42,H42<>"")),A42,A42+1))) -> 1 | B43: =IF(D43<>"",TEXT(D43,"YYYYMMDD")&CHAR(64+A43),"") | C43: =IF(OR(B43="",B43<>B42),1,C42+1) -> 1 | F43: Carenderia | G43: B. Rodriguez | M43: =K43*L43 -> 0 | N43: =IF(B43=B42,N42+M43,M43) -> 0 | P43: =INDEX(Items!B$2:B$1032,MATCH($O43,Items!$A$2:$A$1032,0)) -> #N/A | Q43: =INDEX(Items!C$2:C$1032,MATCH($O43,Items!$A$2:$A$1032,0)) -> #N/A | R43: =INDEX(Items!D$2:D$1032,MATCH($O43,Items!$A$2:$A$1032,0)) -> #N/A
... A45: =IF(OR(D45<>D44,D45=""),1,IF(NOT(AND(E45=E44,F45=F44,G45=G44)),A44+1,IF(OR(H45="",AND(H45<>"",H45<>H44,H44<>"")),A44,A44+1))) -> 1 | B45: =IF(D45<>"",TEXT(D45,"YYYYMMDD")&CHAR(64+A45),"") | C45: =IF(OR(B45="",B45<>B44),1,C44+1) -> 1 | F45: Street Vendor | G45: Don Gil Garcia st. | M45: =K45*L45 -> 0 | N45: =IF(B45=B44,N44+M45,M45) -> 0 | P45: =INDEX(Items!B$2:B$1032,MATCH($O45,Items!$A$2:$A$1032,0)) -> #N/A | Q45: =INDEX(Items!C$2:C$1032,MATCH($O45,Items!$A$2:$A$1032,0)) -> #N/A | R45: =INDEX(Items!D$2:D$1032,MATCH($O45,Items!$A$2:$A$1032,0)) -> #N/A
A46: =IF(OR(D46<>D45,D46=""),1,IF(NOT(AND(E46=E45,F46=F45,G46=G45)),A45+1,IF(OR(H46="",AND(H46<>"",H46<>H45,H45<>"")),A45,A45+1))) -> 1 | B46: =IF(D46<>"",TEXT(D46,"YYYYMMDD")&CHAR(64+A46),"") | C46: =IF(OR(B46="",B46<>B45),1,C45+1) -> 1 | F46: =INDEX(Establishment!B$2:B$1005,MATCH($E46,Establishment!$A$2:$A$1005,0)) -> #N/A | G46: =INDEX(Establishment!C$2:C$1005,MATCH($E46,Establishment!$A$2:$A$1005,0)) -> #N/A | M46: =K46*L46 -> 0 | N46: =IF(B46=B45,N45+M46,M46) -> 0 | P46: =INDEX(Items!B$2:B$1032,MATCH($O46,Items!$A$2:$A$1032,0)) -> #N/A | Q46: =INDEX(Items!C$2:C$1032,MATCH($O46,Items!$A$2:$A$1032,0)) -> #N/A | R46: =INDEX(Items!D$2:D$1032,MATCH($O46,Items!$A$2:$A$1032,0)) -> #N/A
A47: =IF(OR(D47<>D46,D47=""),1,IF(NOT(AND(E47=E46,F47=F46,G47=G46)),A46+1,IF(OR(H47="",AND(H47<>"",H47<>H46,H46<>"")),A46,A46+1))) -> 1 | B47: =IF(D47<>"",TEXT(D47,"YYYYMMDD")&CHAR(64+A47),"") | C47: =IF(OR(B47="",B47<>B46),1,C46+1) -> 1 | F47: =INDEX(Establishment!B$2:B$1005,MATCH($E47,Establishment!$A$2:$A$1005,0)) -> #N/A | G47: =INDEX(Establishment!C$2:C$1005,MATCH($E47,Establishment!$A$2:$A$1005,0)) -> #N/A | M47: =K47*L47 -> 0 | N47: =IF(B47=B46,N46+M47,M47) -> 0 | P47: =INDEX(Items!B$2:B$1032,MATCH($O47,Items!$A$2:$A$1032,0)) -> #N/A | Q47: =INDEX(Items!C$2:C$1032,MATCH($O47,Items!$A$2:$A$1032,0)) -> #N/A | R47: =INDEX(Items!D$2:D$1032,MATCH($O47,Items!$A$2:$A$1032,0)) -> #N/A
A48: =IF(OR(D48<>D47,D48=""),1,IF(NOT(AND(E48=E47,F48=F47,G48=G47)),A47+1,IF(OR(H48="",AND(H48<>"",H48<>H47,H47<>"")),A47,A47+1))) -> 1 | B48: =IF(D48<>"",TEXT(D48,"YYYYMMDD")&CHAR(64+A48),"") | C48: =IF(OR(B48="",B48<>B47),1,C47+1) -> 1 | F48: =INDEX(Establishment!B$2:B$1005,MATCH($E48,Establishment!$A$2:$A$1005,0)) -> #N/A | G48: =INDEX(Establishment!C$2:C$1005,MATCH($E48,Establishment!$A$2:$A$1005,0)) -> #N/A | M48: =K48*L48 -> 0 | N48: =IF(B48=B47,N47+M48,M48) -> 0 | P48: =INDEX(Items!B$2:B$1032,MATCH($O48,Items!$A$2:$A$1032,0)) -> #N/A | Q48: =INDEX(Items!C$2:C$1032,MATCH($O48,Items!$A$2:$A$1032,0)) -> #N/A | R48: =INDEX(Items!D$2:D$1032,MATCH($O48,Items!$A$2:$A$1032,0)) -> #N/A
A49: =IF(OR(D49<>D48,D49=""),1,IF(NOT(AND(E49=E48,F49=F48,G49=G48)),A48+1,IF(OR(H49="",AND(H49<>"",H49<>H48,H48<>"")),A48,A48+1))) -> 1 | B49: =IF(D49<>"",TEXT(D49,"YYYYMMDD")&CHAR(64+A49),"") | C49: =IF(OR(B49="",B49<>B48),1,C48+1) -> 1 | F49: =INDEX(Establishment!B$2:B$1005,MATCH($E49,Establishment!$A$2:$A$1005,0)) -> #N/A | G49: =INDEX(Establishment!C$2:C$1005,MATCH($E49,Establishment!$A$2:$A$1005,0)) -> #N/A | M49: =K49*L49 -> 0 | N49: =IF(B49=B48,N48+M49,M49) -> 0 | P49: =INDEX(Items!B$2:B$1032,MATCH($O49,Items!$A$2:$A$1032,0)) -> #N/A | Q49: =INDEX(Items!C$2:C$1032,MATCH($O49,Items!$A$2:$A$1032,0)) -> #N/A | R49: =INDEX(Items!D$2:D$1032,MATCH($O49,Items!$A$2:$A$1032,0)) -> #N/A
A50: =IF(OR(D50<>D49,D50=""),1,IF(NOT(AND(E50=E49,F50=F49,G50=G49)),A49+1,IF(OR(H50="",AND(H50<>"",H50<>H49,H49<>"")),A49,A49+1))) -> 1 | B50: =IF(D50<>"",TEXT(D50,"YYYYMMDD")&CHAR(64+A50),"") | C50: =IF(OR(B50="",B50<>B49),1,C49+1) -> 1 | F50: =INDEX(Establishment!B$2:B$1005,MATCH($E50,Establishment!$A$2:$A$1005,0)) -> #N/A | G50: =INDEX(Establishment!C$2:C$1005,MATCH($E50,Establishment!$A$2:$A$1005,0)) -> #N/A | M50: =K50*L50 -> 0 | N50: =IF(B50=B49,N49+M50,M50) -> 0 | P50: =INDEX(Items!B$2:B$1032,MATCH($O50,Items!$A$2:$A$1032,0)) -> #N/A | Q50: =INDEX(Items!C$2:C$1032,MATCH($O50,Items!$A$2:$A$1032,0)) -> #N/A | R50: =INDEX(Items!D$2:D$1032,MATCH($O50,Items!$A$2:$A$1032,0)) -> #N/A
A51: =IF(OR(D51<>D50,D51=""),1,IF(NOT(AND(E51=E50,F51=F50,G51=G50)),A50+1,IF(OR(H51="",AND(H51<>"",H51<>H50,H50<>"")),A50,A50+1))) -> 1 | B51: =IF(D51<>"",TEXT(D51,"YYYYMMDD")&CHAR(64+A51),"") | C51: =IF(OR(B51="",B51<>B50),1,C50+1) -> 1 | F51: =INDEX(Establishment!B$2:B$1005,MATCH($E51,Establishment!$A$2:$A$1005,0)) -> #N/A | G51: =INDEX(Establishment!C$2:C$1005,MATCH($E51,Establishment!$A$2:$A$1005,0)) -> #N/A | M51: =K51*L51 -> 0 | N51: =IF(B51=B50,N50+M51,M51) -> 0 | P51: =INDEX(Items!B$2:B$1032,MATCH($O51,Items!$A$2:$A$1032,0)) -> #N/A | Q51: =INDEX(Items!C$2:C$1032,MATCH($O51,Items!$A$2:$A$1032,0)) -> #N/A | R51: =INDEX(Items!D$2:D$1032,MATCH($O51,Items!$A$2:$A$1032,0)) -> #N/A
A52: =IF(OR(D52<>D51,D52=""),1,IF(NOT(AND(E52=E51,F52=F51,G52=G51)),A51+1,IF(OR(H52="",AND(H52<>"",H52<>H51,H51<>"")),A51,A51+1))) -> 1 | B52: =IF(D52<>"",TEXT(D52,"YYYYMMDD")&CHAR(64+A52),"") | C52: =IF(OR(B52="",B52<>B51),1,C51+1) -> 1 | F52: =INDEX(Establishment!B$2:B$1005,MATCH($E52,Establishment!$A$2:$A$1005,0)) -> #N/A | G52: =INDEX(Establishment!C$2:C$1005,MATCH($E52,Establishment!$A$2:$A$1005,0)) -> #N/A | M52: =K52*L52 -> 0 | N52: =IF(B52=B51,N51+M52,M52) -> 0 | P52: =INDEX(Items!B$2:B$1032,MATCH($O52,Items!$A$2:$A$1032,0)) -> #N/A | Q52: =INDEX(Items!C$2:C$1032,MATCH($O52,Items!$A$2:$A$1032,0)) -> #N/A | R52: =INDEX(Items!D$2:D$1032,MATCH($O52,Items!$A$2:$A$1032,0)) -> #N/A
A53: =IF(OR(D53<>D52,D53=""),1,IF(NOT(AND(E53=E52,F53=F52,G53=G52)),A52+1,IF(OR(H53="",AND(H53<>"",H53<>H52,H52<>"")),A52,A52+1))) -> 1 | B53: =IF(D53<>"",TEXT(D53,"YYYYMMDD")&CHAR(64+A53),"") | C53: =IF(OR(B53="",B53<>B52),1,C52+1) -> 1 | F53: =INDEX(Establishment!B$2:B$1005,MATCH($E53,Establishment!$A$2:$A$1005,0)) -> #N/A | G53: =INDEX(Establishment!C$2:C$1005,MATCH($E53,Establishment!$A$2:$A$1005,0)) -> #N/A | M53: =K53*L53 -> 0 | N53: =IF(B53=B52,N52+M53,M53) -> 0 | P53: =INDEX(Items!B$2:B$1032,MATCH($O53,Items!$A$2:$A$1032,0)) -> #N/A | Q53: =INDEX(Items!C$2:C$1032,MATCH($O53,Items!$A$2:$A$1032,0)) -> #N/A | R53: =INDEX(Items!D$2:D$1032,MATCH($O53,Items!$A$2:$A$1032,0)) -> #N/A
A54: =IF(OR(D54<>D53,D54=""),1,IF(NOT(AND(E54=E53,F54=F53,G54=G53)),A53+1,IF(OR(H54="",AND(H54<>"",H54<>H53,H53<>"")),A53,A53+1))) -> 1 | B54: =IF(D54<>"",TEXT(D54,"YYYYMMDD")&CHAR(64+A54),"") | C54: =IF(OR(B54="",B54<>B53),1,C53+1) -> 1 | F54: =INDEX(Establishment!B$2:B$1005,MATCH($E54,Establishment!$A$2:$A$1005,0)) -> #N/A | G54: =INDEX(Establishment!C$2:C$1005,MATCH($E54,Establishment!$A$2:$A$1005,0)) -> #N/A | M54: =K54*L54 -> 0 | N54: =IF(B54=B53,N53+M54,M54) -> 0 | P54: =INDEX(Items!B$2:B$1032,MATCH($O54,Items!$A$2:$A$1032,0)) -> #N/A | Q54: =INDEX(Items!C$2:C$1032,MATCH($O54,Items!$A$2:$A$1032,0)) -> #N/A | R54: =INDEX(Items!D$2:D$1032,MATCH($O54,Items!$A$2:$A$1032,0)) -> #N/A
A55: =IF(OR(D55<>D54,D55=""),1,IF(NOT(AND(E55=E54,F55=F54,G55=G54)),A54+1,IF(OR(H55="",AND(H55<>"",H55<>H54,H54<>"")),A54,A54+1))) -> 1 | B55: =IF(D55<>"",TEXT(D55,"YYYYMMDD")&CHAR(64+A55),"") | C55: =IF(OR(B55="",B55<>B54),1,C54+1) -> 1 | F55: =INDEX(Establishment!B$2:B$1005,MATCH($E55,Establishment!$A$2:$A$1005,0)) -> #N/A | G55: =INDEX(Establishment!C$2:C$1005,MATCH($E55,Establishment!$A$2:$A$1005,0)) -> #N/A | M55: =K55*L55 -> 0 | N55: =IF(B55=B54,N54+M55,M55) -> 0 | P55: =INDEX(Items!B$2:B$1032,MATCH($O55,Items!$A$2:$A$1032,0)) -> #N/A | Q55: =INDEX(Items!C$2:C$1032,MATCH($O55,Items!$A$2:$A$1032,0)) -> #N/A | R55: =INDEX(Items!D$2:D$1032,MATCH($O55,Items!$A$2:$A$1032,0)) -> #N/A
A56: =IF(OR(D56<>D55,D56=""),1,IF(NOT(AND(E56=E55,F56=F55,G56=G55)),A55+1,IF(OR(H56="",AND(H56<>"",H56<>H55,H55<>"")),A55,A55+1))) -> 1 | B56: =IF(D56<>"",TEXT(D56,"YYYYMMDD")&CHAR(64+A56),"") | C56: =IF(OR(B56="",B56<>B55),1,C55+1) -> 1 | F56: =INDEX(Establishment!B$2:B$1005,MATCH($E56,Establishment!$A$2:$A$1005,0)) -> #N/A | G56: =INDEX(Establishment!C$2:C$1005,MATCH($E56,Establishment!$A$2:$A$1005,0)) -> #N/A | M56: =K56*L56 -> 0 | N56: =IF(B56=B55,N55+M56,M56) -> 0 | P56: =INDEX(Items!B$2:B$1032,MATCH($O56,Items!$A$2:$A$1032,0)) -> #N/A | Q56: =INDEX(Items!C$2:C$1032,MATCH($O56,Items!$A$2:$A$1032,0)) -> #N/A | R56: =INDEX(Items!D$2:D$1032,MATCH($O56,Items!$A$2:$A$1032,0)) -> #N/A
A57: =IF(OR(D57<>D56,D57=""),1,IF(NOT(AND(E57=E56,F57=F56,G57=G56)),A56+1,IF(OR(H57="",AND(H57<>"",H57<>H56,H56<>"")),A56,A56+1))) -> 1 | B57: =IF(D57<>"",TEXT(D57,"YYYYMMDD")&CHAR(64+A57),"") | C57: =IF(OR(B57="",B57<>B56),1,C56+1) -> 1 | F57: =INDEX(Establishment!B$2:B$1005,MATCH($E57,Establishment!$A$2:$A$1005,0)) -> #N/A | G57: =INDEX(Establishment!C$2:C$1005,MATCH($E57,Establishment!$A$2:$A$1005,0)) -> #N/A | M57: =K57*L57 -> 0 | N57: =IF(B57=B56,N56+M57,M57) -> 0 | P57: =INDEX(Items!B$2:B$1032,MATCH($O57,Items!$A$2:$A$1032,0)) -> #N/A | Q57: =INDEX(Items!C$2:C$1032,MATCH($O57,Items!$A$2:$A$1032,0)) -> #N/A | R57: =INDEX(Items!D$2:D$1032,MATCH($O57,Items!$A$2:$A$1032,0)) -> #N/A
... A66: =IF(OR(D66<>D65,D66=""),1,IF(NOT(AND(E66=E65,F66=F65,G66=G65)),A65+1,IF(OR(H66="",AND(H66<>"",H66<>H65,H65<>"")),A65,A65+1))) -> 1 | B66: =IF(D66<>"",TEXT(D66,"YYYYMMDD")&CHAR(64+A66),"") | C66: =IF(OR(B66="",B66<>B65),1,C65+1) -> 1 | F66: =INDEX(Establishment!B$2:B$1005,MATCH($E66,Establishment!$A$2:$A$1005,0)) -> #N/A | G66: =INDEX(Establishment!C$2:C$1005,MATCH($E66,Establishment!$A$2:$A$1005,0)) -> #N/A | M66: =K66*L66 -> 0 | N66: =IF(B66=B65,N65+M66,M66) -> 0 | P66: =INDEX(Items!B$2:B$1032,MATCH($O66,Items!$A$2:$A$1032,0)) -> #N/A | Q66: =INDEX(Items!C$2:C$1032,MATCH($O66,Items!$A$2:$A$1032,0)) -> #N/A | R66: =INDEX(Items!D$2:D$1032,MATCH($O66,Items!$A$2:$A$1032,0)) -> #N/A
A67: =IF(OR(D67<>D66,D67=""),1,IF(NOT(AND(E67=E66,F67=F66,G67=G66)),A66+1,IF(OR(H67="",AND(H67<>"",H67<>H66,H66<>"")),A66,A66+1))) -> 1 | B67: =IF(D67<>"",TEXT(D67,"YYYYMMDD")&CHAR(64+A67),"") | C67: =IF(OR(B67="",B67<>B66),1,C66+1) -> 1 | F67: Street Vendor | G67: B. Rodriguez | M67: =K67*L67 -> 0 | N67: =IF(B67=B66,N66+M67,M67) -> 0 | P67: =INDEX(Items!B$2:B$1032,MATCH($O67,Items!$A$2:$A$1032,0)) -> #N/A | Q67: =INDEX(Items!C$2:C$1032,MATCH($O67,Items!$A$2:$A$1032,0)) -> #N/A | R67: =INDEX(Items!D$2:D$1032,MATCH($O67,Items!$A$2:$A$1032,0)) -> #N/A
A68: =IF(OR(D68<>D67,D68=""),1,IF(NOT(AND(E68=E67,F68=F67,G68=G67)),A67+1,IF(OR(H68="",AND(H68<>"",H68<>H67,H67<>"")),A67,A67+1))) -> 1 | B68: =IF(D68<>"",TEXT(D68,"YYYYMMDD")&CHAR(64+A68),"") | C68: =IF(OR(B68="",B68<>B67),1,C67+1) -> 1 | F68: Street Vendor | G68: B. Rodriguez | M68: =K68*L68 -> 0 | N68: =IF(B68=B67,N67+M68,M68) -> 0 | P68: =INDEX(Items!B$2:B$1032,MATCH($O68,Items!$A$2:$A$1032,0)) -> #N/A | Q68: =INDEX(Items!C$2:C$1032,MATCH($O68,Items!$A$2:$A$1032,0)) -> #N/A | R68: =INDEX(Items!D$2:D$1032,MATCH($O68,Items!$A$2:$A$1032,0)) -> #N/A
A69: =IF(OR(D69<>D68,D69=""),1,IF(NOT(AND(E69=E68,F69=F68,G69=G68)),A68+1,IF(OR(H69="",AND(H69<>"",H69<>H68,H68<>"")),A68,A68+1))) -> 1 | B69: =IF(D69<>"",TEXT(D69,"YYYYMMDD")&CHAR(64+A69),"") | C69: =IF(OR(B69="",B69<>B68),1,C68+1) -> 1 | F69: Street Vendor | G69: B. Rodriguez | M69: =K69*L69 -> 0 | N69: =IF(B69=B68,N68+M69,M69) -> 0 | P69: =INDEX(Items!B$2:B$1032,MATCH($O69,Items!$A$2:$A$1032,0)) -> #N/A | Q69: =INDEX(Items!C$2:C$1032,MATCH($O69,Items!$A$2:$A$1032,0)) -> #N/A | R69: =INDEX(Items!D$2:D$1032,MATCH($O69,Items!$A$2:$A$1032,0)) -> #N/A
A70: =IF(OR(D70<>D69,D70=""),1,IF(NOT(AND(E70=E69,F70=F69,G70=G69)),A69+1,IF(OR(H70="",AND(H70<>"",H70<>H69,H69<>"")),A69,A69+1))) -> 1 | B70: =IF(D70<>"",TEXT(D70,"YYYYMMDD")&CHAR(64+A70),"") | C70: =IF(OR(B70="",B70<>B69),1,C69+1) -> 1 | F70: Street Vendor | G70: B. Rodriguez | M70: =K70*L70 -> 0 | N70: =IF(B70=B69,N69+M70,M70) -> 0 | P70: =INDEX(Items!B$2:B$1032,MATCH($O70,Items!$A$2:$A$1032,0)) -> #N/A | Q70: =INDEX(Items!C$2:C$1032,MATCH($O70,Items!$A$2:$A$1032,0)) -> #N/A | R70: =INDEX(Items!D$2:D$1032,MATCH($O70,Items!$A$2:$A$1032,0)) -> #N/A
A71: =IF(OR(D71<>D70,D71=""),1,IF(NOT(AND(E71=E70,F71=F70,G71=G70)),A70+1,IF(OR(H71="",AND(H71<>"",H71<>H70,H70<>"")),A70,A70+1))) -> 1 | B71: =IF(D71<>"",TEXT(D71,"YYYYMMDD")&CHAR(64+A71),"") | C71: =IF(OR(B71="",B71<>B70),1,C70+1) -> 1 | F71: Street Vendor | G71: B. Rodriguez | M71: =K71*L71 -> 0 | N71: =IF(B71=B70,N70+M71,M71) -> 0 | P71: =INDEX(Items!B$2:B$1032,MATCH($O71,Items!$A$2:$A$1032,0)) -> #N/A | Q71: =INDEX(Items!C$2:C$1032,MATCH($O71,Items!$A$2:$A$1032,0)) -> #N/A | R71: =INDEX(Items!D$2:D$1032,MATCH($O71,Items!$A$2:$A$1032,0)) -> #N/A
A72: =IF(OR(D72<>D71,D72=""),1,IF(NOT(AND(E72=E71,F72=F71,G72=G71)),A71+1,IF(OR(H72="",AND(H72<>"",H72<>H71,H71<>"")),A71,A71+1))) -> 1 | B72: =IF(D72<>"",TEXT(D72,"YYYYMMDD")&CHAR(64+A72),"") | C72: =IF(OR(B72="",B72<>B71),1,C71+1) -> 1 | F72: Massage | G72: Don Gil Garcia st. | M72: =K72*L72 -> 0 | N72: =IF(B72=B71,N71+M72,M72) -> 0 | P72: =INDEX(Items!B$2:B$1032,MATCH($O72,Items!$A$2:$A$1032,0)) -> #N/A | Q72: =INDEX(Items!C$2:C$1032,MATCH($O72,Items!$A$2:$A$1032,0)) -> #N/A | R72: =INDEX(Items!D$2:D$1032,MATCH($O72,Items!$A$2:$A$1032,0)) -> #N/A
A73: =IF(OR(D73<>D72,D73=""),1,IF(NOT(AND(E73=E72,F73=F72,G73=G72)),A72+1,IF(OR(H73="",AND(H73<>"",H73<>H72,H72<>"")),A72,A72+1))) -> 1 | B73: =IF(D73<>"",TEXT(D73,"YYYYMMDD")&CHAR(64+A73),"") | C73: =IF(OR(B73="",B73<>B72),1,C72+1) -> 1 | F73: Massage | G73: Don Gil Garcia st. | M73: =K73*L73 -> 0 | N73: =IF(B73=B72,N72+M73,M73) -> 0 | P73: =INDEX(Items!B$2:B$1032,MATCH($O73,Items!$A$2:$A$1032,0)) -> #N/A | Q73: =INDEX(Items!C$2:C$1032,MATCH($O73,Items!$A$2:$A$1032,0)) -> #N/A | R73: =INDEX(Items!D$2:D$1032,MATCH($O73,Items!$A$2:$A$1032,0)) -> #N/A
A74: =IF(OR(D74<>D73,D74=""),1,IF(NOT(AND(E74=E73,F74=F73,G74=G73)),A73+1,IF(OR(H74="",AND(H74<>"",H74<>H73,H73<>"")),A73,A73+1))) -> 1 | B74: =IF(D74<>"",TEXT(D74,"YYYYMMDD")&CHAR(64+A74),"") | C74: =IF(OR(B74="",B74<>B73),1,C73+1) -> 1 | F74: Street Vendor | G74: Don Gil Garcia st. | M74: =K74*L74 -> 0 | N74: =IF(B74=B73,N73+M74,M74) -> 0 | P74: =INDEX(Items!B$2:B$1032,MATCH($O74,Items!$A$2:$A$1032,0)) -> #N/A | Q74: =INDEX(Items!C$2:C$1032,MATCH($O74,Items!$A$2:$A$1032,0)) -> #N/A | R74: =INDEX(Items!D$2:D$1032,MATCH($O74,Items!$A$2:$A$1032,0)) -> #N/A
A75: =IF(OR(D75<>D74,D75=""),1,IF(NOT(AND(E75=E74,F75=F74,G75=G74)),A74+1,IF(OR(H75="",AND(H75<>"",H75<>H74,H74<>"")),A74,A74+1))) -> 1 | B75: =IF(D75<>"",TEXT(D75,"YYYYMMDD")&CHAR(64+A75),"") | C75: =IF(OR(B75="",B75<>B74),1,C74+1) -> 1 | F75: Street Vendor | G75: Don Gil Garcia st. | M75: =K75*L75 -> 0 | N75: =IF(B75=B74,N74+M75,M75) -> 0 | P75: =INDEX(Items!B$2:B$1032,MATCH($O75,Items!$A$2:$A$1032,0)) -> #N/A | Q75: =INDEX(Items!C$2:C$1032,MATCH($O75,Items!$A$2:$A$1032,0)) -> #N/A | R75: =INDEX(Items!D$2:D$1032,MATCH($O75,Items!$A$2:$A$1032,0)) -> #N/A
A76: =IF(OR(D76<>D75,D76=""),1,IF(NOT(AND(E76=E75,F76=F75,G76=G75)),A75+1,IF(OR(H76="",AND(H76<>"",H76<>H75,H75<>"")),A75,A75+1))) -> 1 | B76: =IF(D76<>"",TEXT(D76,"YYYYMMDD")&CHAR(64+A76),"") | C76: =IF(OR(B76="",B76<>B75),1,C75+1) -> 1 | F76: Street Vendor | G76: Don Gil Garcia st. | M76: =K76*L76 -> 0 | N76: =IF(B76=B75,N75+M76,M76) -> 0 | P76: =INDEX(Items!B$2:B$1032,MATCH($O76,Items!$A$2:$A$1032,0)) -> #N/A | Q76: =INDEX(Items!C$2:C$1032,MATCH($O76,Items!$A$2:$A$1032,0)) -> #N/A | R76: =INDEX(Items!D$2:D$1032,MATCH($O76,Items!$A$2:$A$1032,0)) -> #N/A
A77: =IF(OR(D77<>D76,D77=""),1,IF(NOT(AND(E77=E76,F77=F76,G77=G76)),A76+1,IF(OR(H77="",AND(H77<>"",H77<>H76,H76<>"")),A76,A76+1))) -> 1 | B77: =IF(D77<>"",TEXT(D77,"YYYYMMDD")&CHAR(64+A77),"") | C77: =IF(OR(B77="",B77<>B76),1,C76+1) -> 1 | F77: Street Vendor | G77: Don Gil Garcia st. | M77: =K77*L77 -> 0 | N77: =IF(B77=B76,N76+M77,M77) -> 0 | P77: =INDEX(Items!B$2:B$1032,MATCH($O77,Items!$A$2:$A$1032,0)) -> #N/A | Q77: =INDEX(Items!C$2:C$1032,MATCH($O77,Items!$A$2:$A$1032,0)) -> #N/A | R77: =INDEX(Items!D$2:D$1032,MATCH($O77,Items!$A$2:$A$1032,0)) -> #N/A
A78: =IF(OR(D78<>D77,D78=""),1,IF(NOT(AND(E78=E77,F78=F77,G78=G77)),A77+1,IF(OR(H78="",AND(H78<>"",H78<>H77,H77<>"")),A77,A77+1))) -> 1 | B78: =IF(D78<>"",TEXT(D78,"YYYYMMDD")&CHAR(64+A78),"") | C78: =IF(OR(B78="",B78<>B77),1,C77+1) -> 1 | F78: Street Vendor | G78: Don Gil Garcia st. | M78: =K78*L78 -> 0 | N78: =IF(B78=B77,N77+M78,M78) -> 0 | P78: =INDEX(Items!B$2:B$1032,MATCH($O78,Items!$A$2:$A$1032,0)) -> #N/A | Q78: =INDEX(Items!C$2:C$1032,MATCH($O78,Items!$A$2:$A$1032,0)) -> #N/A | R78: =INDEX(Items!D$2:D$1032,MATCH($O78,Items!$A$2:$A$1032,0)) -> #N/A
... A82: =IF(OR(D82<>D81,D82=""),1,IF(NOT(AND(E82=E81,F82=F81,G82=G81)),A81+1,IF(OR(H82="",AND(H82<>"",H82<>H81,H81<>"")),A81,A81+1))) -> 1 | B82: =IF(D82<>"",TEXT(D82,"YYYYMMDD")&CHAR(64+A82),"") | C82: =IF(OR(B82="",B82<>B81),1,C81+1) -> 1 | F82: Street Vendor | G82: B. Rodriguez | M82: =K82*L82 -> 0 | N82: =IF(B82=B81,N81+M82,M82) -> 0 | P82: =INDEX(Items!B$2:B$1032,MATCH($O82,Items!$A$2:$A$1032,0)) -> #N/A | Q82: =INDEX(Items!C$2:C$1032,MATCH($O82,Items!$A$2:$A$1032,0)) -> #N/A | R82: =INDEX(Items!D$2:D$1032,MATCH($O82,Items!$A$2:$A$1032,0)) -> #N/A
A83: =IF(OR(D83<>D82,D83=""),1,IF(NOT(AND(E83=E82,F83=F82,G83=G82)),A82+1,IF(OR(H83="",AND(H83<>"",H83<>H82,H82<>"")),A82,A82+1))) -> 1 | B83: =IF(D83<>"",TEXT(D83,"YYYYMMDD")&CHAR(64+A83),"") | C83: =IF(OR(B83="",B83<>B82),1,C82+1) -> 1 | F83: =INDEX(Establishment!B$2:B$1005,MATCH($E83,Establishment!$A$2:$A$1005,0)) -> #N/A | G83: =INDEX(Establishment!C$2:C$1005,MATCH($E83,Establishment!$A$2:$A$1005,0)) -> #N/A | M83: =K83*L83 -> 0 | N83: =IF(B83=B82,N82+M83,M83) -> 0 | P83: =INDEX(Items!B$2:B$1032,MATCH($O83,Items!$A$2:$A$1032,0)) -> #N/A | Q83: =INDEX(Items!C$2:C$1032,MATCH($O83,Items!$A$2:$A$1032,0)) -> #N/A | R83: =INDEX(Items!D$2:D$1032,MATCH($O83,Items!$A$2:$A$1032,0)) -> #N/A
A84: =IF(OR(D84<>D83,D84=""),1,IF(NOT(AND(E84=E83,F84=F83,G84=G83)),A83+1,IF(OR(H84="",AND(H84<>"",H84<>H83,H83<>"")),A83,A83+1))) -> 1 | B84: =IF(D84<>"",TEXT(D84,"YYYYMMDD")&CHAR(64+A84),"") | C84: =IF(OR(B84="",B84<>B83),1,C83+1) -> 1 | F84: =INDEX(Establishment!B$2:B$1005,MATCH($E84,Establishment!$A$2:$A$1005,0)) -> #N/A | G84: =INDEX(Establishment!C$2:C$1005,MATCH($E84,Establishment!$A$2:$A$1005,0)) -> #N/A | M84: =K84*L84 -> 0 | N84: =IF(B84=B83,N83+M84,M84) -> 0 | P84: =INDEX(Items!B$2:B$1032,MATCH($O84,Items!$A$2:$A$1032,0)) -> #N/A | Q84: =INDEX(Items!C$2:C$1032,MATCH($O84,Items!$A$2:$A$1032,0)) -> #N/A | R84: =INDEX(Items!D$2:D$1032,MATCH($O84,Items!$A$2:$A$1032,0)) -> #N/A
A85: =IF(OR(D85<>D84,D85=""),1,IF(NOT(AND(E85=E84,F85=F84,G85=G84)),A84+1,IF(OR(H85="",AND(H85<>"",H85<>H84,H84<>"")),A84,A84+1))) -> 1 | B85: =IF(D85<>"",TEXT(D85,"YYYYMMDD")&CHAR(64+A85),"") | C85: =IF(OR(B85="",B85<>B84),1,C84+1) -> 1 | F85: =INDEX(Establishment!B$2:B$1005,MATCH($E85,Establishment!$A$2:$A$1005,0)) -> #N/A | G85: =INDEX(Establishment!C$2:C$1005,MATCH($E85,Establishment!$A$2:$A$1005,0)) -> #N/A | M85: =K85*L85 -> 0 | N85: =IF(B85=B84,N84+M85,M85) -> 0 | P85: =INDEX(Items!B$2:B$1032,MATCH($O85,Items!$A$2:$A$1032,0)) -> #N/A | Q85: =INDEX(Items!C$2:C$1032,MATCH($O85,Items!$A$2:$A$1032,0)) -> #N/A | R85: =INDEX(Items!D$2:D$1032,MATCH($O85,Items!$A$2:$A$1032,0)) -> #N/A
A86: =IF(OR(D86<>D85,D86=""),1,IF(NOT(AND(E86=E85,F86=F85,G86=G85)),A85+1,IF(OR(H86="",AND(H86<>"",H86<>H85,H85<>"")),A85,A85+1))) -> 1 | B86: =IF(D86<>"",TEXT(D86,"YYYYMMDD")&CHAR(64+A86),"") | C86: =IF(OR(B86="",B86<>B85),1,C85+1) -> 1 | F86: =INDEX(Establishment!B$2:B$1005,MATCH($E86,Establishment!$A$2:$A$1005,0)) -> #N/A | G86: =INDEX(Establishment!C$2:C$1005,MATCH($E86,Establishment!$A$2:$A$1005,0)) -> #N/A | M86: =K86*L86 -> 0 | N86: =IF(B86=B85,N85+M86,M86) -> 0 | P86: =INDEX(Items!B$2:B$1032,MATCH($O86,Items!$A$2:$A$1032,0)) -> #N/A | Q86: =INDEX(Items!C$2:C$1032,MATCH($O86,Items!$A$2:$A$1032,0)) -> #N/A | R86: =INDEX(Items!D$2:D$1032,MATCH($O86,Items!$A$2:$A$1032,0)) -> #N/A
A87: =IF(OR(D87<>D86,D87=""),1,IF(NOT(AND(E87=E86,F87=F86,G87=G86)),A86+1,IF(OR(H87="",AND(H87<>"",H87<>H86,H86<>"")),A86,A86+1))) -> 1 | B87: =IF(D87<>"",TEXT(D87,"YYYYMMDD")&CHAR(64+A87),"") | C87: =IF(OR(B87="",B87<>B86),1,C86+1) -> 1 | F87: =INDEX(Establishment!B$2:B$1005,MATCH($E87,Establishment!$A$2:$A$1005,0)) -> #N/A | G87: =INDEX(Establishment!C$2:C$1005,MATCH($E87,Establishment!$A$2:$A$1005,0)) -> #N/A | M87: =K87*L87 -> 0 | N87: =IF(B87=B86,N86+M87,M87) -> 0 | P87: =INDEX(Items!B$2:B$1032,MATCH($O87,Items!$A$2:$A$1032,0)) -> #N/A | Q87: =INDEX(Items!C$2:C$1032,MATCH($O87,Items!$A$2:$A$1032,0)) -> #N/A | R87: =INDEX(Items!D$2:D$1032,MATCH($O87,Items!$A$2:$A$1032,0)) -> #N/A
A88: =IF(OR(D88<>D87,D88=""),1,IF(NOT(AND(E88=E87,F88=F87,G88=G87)),A87+1,IF(OR(H88="",AND(H88<>"",H88<>H87,H87<>"")),A87,A87+1))) -> 1 | B88: =IF(D88<>"",TEXT(D88,"YYYYMMDD")&CHAR(64+A88),"") | C88: =IF(OR(B88="",B88<>B87),1,C87+1) -> 1 | F88: =INDEX(Establishment!B$2:B$1005,MATCH($E88,Establishment!$A$2:$A$1005,0)) -> #N/A | G88: =INDEX(Establishment!C$2:C$1005,MATCH($E88,Establishment!$A$2:$A$1005,0)) -> #N/A | M88: =K88*L88 -> 0 | N88: =IF(B88=B87,N87+M88,M88) -> 0 | P88: =INDEX(Items!B$2:B$1032,MATCH($O88,Items!$A$2:$A$1032,0)) -> #N/A | Q88: =INDEX(Items!C$2:C$1032,MATCH($O88,Items!$A$2:$A$1032,0)) -> #N/A | R88: =INDEX(Items!D$2:D$1032,MATCH($O88,Items!$A$2:$A$1032,0)) -> #N/A
A89: =IF(OR(D89<>D88,D89=""),1,IF(NOT(AND(E89=E88,F89=F88,G89=G88)),A88+1,IF(OR(H89="",AND(H89<>"",H89<>H88,H88<>"")),A88,A88+1))) -> 1 | B89: =IF(D89<>"",TEXT(D89,"YYYYMMDD")&CHAR(64+A89),"") | C89: =IF(OR(B89="",B89<>B88),1,C88+1) -> 1 | F89: =INDEX(Establishment!B$2:B$1005,MATCH($E89,Establishment!$A$2:$A$1005,0)) -> #N/A | G89: =INDEX(Establishment!C$2:C$1005,MATCH($E89,Establishment!$A$2:$A$1005,0)) -> #N/A | M89: =K89*L89 -> 0 | N89: =IF(B89=B88,N88+M89,M89) -> 0 | P89: =INDEX(Items!B$2:B$1032,MATCH($O89,Items!$A$2:$A$1032,0)) -> #N/A | Q89: =INDEX(Items!C$2:C$1032,MATCH($O89,Items!$A$2:$A$1032,0)) -> #N/A | R89: =INDEX(Items!D$2:D$1032,MATCH($O89,Items!$A$2:$A$1032,0)) -> #N/A
A90: =IF(OR(D90<>D89,D90=""),1,IF(NOT(AND(E90=E89,F90=F89,G90=G89)),A89+1,IF(OR(H90="",AND(H90<>"",H90<>H89,H89<>"")),A89,A89+1))) -> 1 | B90: =IF(D90<>"",TEXT(D90,"YYYYMMDD")&CHAR(64+A90),"") | C90: =IF(OR(B90="",B90<>B89),1,C89+1) -> 1 | F90: =INDEX(Establishment!B$2:B$1005,MATCH($E90,Establishment!$A$2:$A$1005,0)) -> #N/A | G90: =INDEX(Establishment!C$2:C$1005,MATCH($E90,Establishment!$A$2:$A$1005,0)) -> #N/A | M90: =K90*L90 -> 0 | N90: =IF(B90=B89,N89+M90,M90) -> 0 | P90: =INDEX(Items!B$2:B$1032,MATCH($O90,Items!$A$2:$A$1032,0)) -> #N/A | Q90: =INDEX(Items!C$2:C$1032,MATCH($O90,Items!$A$2:$A$1032,0)) -> #N/A | R90: =INDEX(Items!D$2:D$1032,MATCH($O90,Items!$A$2:$A$1032,0)) -> #N/A
A91: =IF(OR(D91<>D90,D91=""),1,IF(NOT(AND(E91=E90,F91=F90,G91=G90)),A90+1,IF(OR(H91="",AND(H91<>"",H91<>H90,H90<>"")),A90,A90+1))) -> 1 | B91: =IF(D91<>"",TEXT(D91,"YYYYMMDD")&CHAR(64+A91),"") | C91: =IF(OR(B91="",B91<>B90),1,C90+1) -> 1 | F91: =INDEX(Establishment!B$2:B$1005,MATCH($E91,Establishment!$A$2:$A$1005,0)) -> #N/A | G91: =INDEX(Establishment!C$2:C$1005,MATCH($E91,Establishment!$A$2:$A$1005,0)) -> #N/A | M91: =K91*L91 -> 0 | N91: =IF(B91=B90,N90+M91,M91) -> 0 | P91: =INDEX(Items!B$2:B$1032,MATCH($O91,Items!$A$2:$A$1032,0)) -> #N/A | Q91: =INDEX(Items!C$2:C$1032,MATCH($O91,Items!$A$2:$A$1032,0)) -> #N/A | R91: =INDEX(Items!D$2:D$1032,MATCH($O91,Items!$A$2:$A$1032,0)) -> #N/A
A92: =IF(OR(D92<>D91,D92=""),1,IF(NOT(AND(E92=E91,F92=F91,G92=G91)),A91+1,IF(OR(H92="",AND(H92<>"",H92<>H91,H91<>"")),A91,A91+1))) -> 1 | B92: =IF(D92<>"",TEXT(D92,"YYYYMMDD")&CHAR(64+A92),"") | C92: =IF(OR(B92="",B92<>B91),1,C91+1) -> 1 | F92: =INDEX(Establishment!B$2:B$1005,MATCH($E92,Establishment!$A$2:$A$1005,0)) -> #N/A | G92: =INDEX(Establishment!C$2:C$1005,MATCH($E92,Establishment!$A$2:$A$1005,0)) -> #N/A | M92: =K92*L92 -> 0 | N92: =IF(B92=B91,N91+M92,M92) -> 0 | P92: =INDEX(Items!B$2:B$1032,MATCH($O92,Items!$A$2:$A$1032,0)) -> #N/A | Q92: =INDEX(Items!C$2:C$1032,MATCH($O92,Items!$A$2:$A$1032,0)) -> #N/A | R92: =INDEX(Items!D$2:D$1032,MATCH($O92,Items!$A$2:$A$1032,0)) -> #N/A
A93: =IF(OR(D93<>D92,D93=""),1,IF(NOT(AND(E93=E92,F93=F92,G93=G92)),A92+1,IF(OR(H93="",AND(H93<>"",H93<>H92,H92<>"")),A92,A92+1))) -> 1 | B93: =IF(D93<>"",TEXT(D93,"YYYYMMDD")&CHAR(64+A93),"") | C93: =IF(OR(B93="",B93<>B92),1,C92+1) -> 1 | F93: =INDEX(Establishment!B$2:B$1005,MATCH($E93,Establishment!$A$2:$A$1005,0)) | G93: =INDEX(Establishment!C$2:C$1005,MATCH($E93,Establishment!$A$2:$A$1005,0)) | M93: =K93*L93 -> 0 | N93: =IF(B93=B92,N92+M93,M93) -> 0 | P93: =INDEX(Items!B$2:B$1032,MATCH($O93,Items!$A$2:$A$1032,0)) -> #N/A | Q93: =INDEX(Items!C$2:C$1032,MATCH($O93,Items!$A$2:$A$1032,0)) -> #N/A | R93: =INDEX(Items!D$2:D$1032,MATCH($O93,Items!$A$2:$A$1032,0)) -> #N/A
A94: =IF(OR(D94<>D93,D94=""),1,IF(NOT(AND(E94=E93,F94=F93,G94=G93)),A93+1,IF(OR(H94="",AND(H94<>"",H94<>H93,H93<>"")),A93,A93+1))) -> 1 | B94: =IF(D94<>"",TEXT(D94,"YYYYMMDD")&CHAR(64+A94),"") | C94: =IF(OR(B94="",B94<>B93),1,C93+1) -> 1 | F94: =INDEX(Establishment!B$2:B$1005,MATCH($E94,Establishment!$A$2:$A$1005,0)) | G94: =INDEX(Establishment!C$2:C$1005,MATCH($E94,Establishment!$A$2:$A$1005,0)) | M94: =K94*L94 -> 0 | N94: =IF(B94=B93,N93+M94,M94) -> 0 | P94: =INDEX(Items!B$2:B$1032,MATCH($O94,Items!$A$2:$A$1032,0)) -> #N/A | Q94: =INDEX(Items!C$2:C$1032,MATCH($O94,Items!$A$2:$A$1032,0)) -> #N/A | R94: =INDEX(Items!D$2:D$1032,MATCH($O94,Items!$A$2:$A$1032,0)) -> #N/A
... A98: =IF(OR(D98<>D97,D98=""),1,IF(NOT(AND(E98=E97,F98=F97,G98=G97)),A97+1,IF(OR(H98="",AND(H98<>"",H98<>H97,H97<>"")),A97,A97+1))) -> 1 | B98: =IF(D98<>"",TEXT(D98,"YYYYMMDD")&CHAR(64+A98),"") | C98: =IF(OR(B98="",B98<>B97),1,C97+1) -> 1 | F98: =INDEX(Establishment!B$2:B$1005,MATCH($E98,Establishment!$A$2:$A$1005,0)) | G98: =INDEX(Establishment!C$2:C$1005,MATCH($E98,Establishment!$A$2:$A$1005,0)) | M98: =K98*L98 -> 0 | N98: =IF(B98=B97,N97+M98,M98) -> 0 | P98: =INDEX(Items!B$2:B$1032,MATCH($O98,Items!$A$2:$A$1032,0)) -> #N/A | Q98: =INDEX(Items!C$2:C$1032,MATCH($O98,Items!$A$2:$A$1032,0)) -> #N/A | R98: =INDEX(Items!D$2:D$1032,MATCH($O98,Items!$A$2:$A$1032,0)) -> #N/A
A99: =IF(OR(D99<>D98,D99=""),1,IF(NOT(AND(E99=E98,F99=F98,G99=G98)),A98+1,IF(OR(H99="",AND(H99<>"",H99<>H98,H98<>"")),A98,A98+1))) -> 1 | B99: =IF(D99<>"",TEXT(D99,"YYYYMMDD")&CHAR(64+A99),"") -> 20230621A | C99: =IF(OR(B99="",B99<>B98),1,C98+1) -> 1 | D99: 45098 | E99: Carenderia 14th Floor-ACC Tower Cebu Business Park | F99: =INDEX(Establishment!B$2:B$1005,MATCH($E99,Establishment!$A$2:$A$1005,0)) -> Carenderia 14th Floor | G99: =INDEX(Establishment!C$2:C$1005,MATCH($E99,Establishment!$A$2:$A$1005,0)) -> ACC Tower Cebu Business Park | M99: =K99*L99 -> 0 | N99: =IF(B99=B98,N98+M99,M99) -> 0 | P99: =INDEX(Items!B$2:B$1032,MATCH($O99,Items!$A$2:$A$1032,0)) -> #N/A | Q99: =INDEX(Items!C$2:C$1032,MATCH($O99,Items!$A$2:$A$1032,0)) -> #N/A | R99: =INDEX(Items!D$2:D$1032,MATCH($O99,Items!$A$2:$A$1032,0)) -> #N/A
A100: =IF(OR(D100<>D99,D100=""),1,IF(NOT(AND(E100=E99,F100=F99,G100=G99)),A99+1,IF(OR(H100="",AND(H100<>"",H100<>H99,H99<>"")),A99,A99+1))) -> 1 | B100: =IF(D100<>"",TEXT(D100,"YYYYMMDD")&CHAR(64+A100),"") | C100: =IF(OR(B100="",B100<>B99),1,C99+1) -> 1 | F100: =INDEX(Establishment!B$2:B$1005,MATCH($E100,Establishment!$A$2:$A$1005,0)) -> #N/A | G100: =INDEX(Establishment!C$2:C$1005,MATCH($E100,Establishment!$A$2:$A$1005,0)) -> #N/A | M100: =K100*L100 -> 0 | N100: =IF(B100=B99,N99+M100,M100) -> 0 | P100: =INDEX(Items!B$2:B$1032,MATCH($O100,Items!$A$2:$A$1032,0)) -> #N/A | Q100: =INDEX(Items!C$2:C$1032,MATCH($O100,Items!$A$2:$A$1032,0)) -> #N/A | R100: =INDEX(Items!D$2:D$1032,MATCH($O100,Items!$A$2:$A$1032,0)) -> #N/A
A101: =IF(OR(D101<>D100,D101=""),1,IF(NOT(AND(E101=E100,F101=F100,G101=G100)),A100+1,IF(OR(H101="",AND(H101<>"",H101<>H100,H100<>"")),A100,A100+1))) -> 1 | B101: =IF(D101<>"",TEXT(D101,"YYYYMMDD")&CHAR(64+A101),"") | C101: =IF(OR(B101="",B101<>B100),1,C100+1) -> 1 | F101: =INDEX(Establishment!B$2:B$1005,MATCH($E101,Establishment!$A$2:$A$1005,0)) | G101: =INDEX(Establishment!C$2:C$1005,MATCH($E101,Establishment!$A$2:$A$1005,0)) | M101: =K101*L101 -> 0 | N101: =IF(B101=B100,N100+M101,M101) -> 0 | P101: =INDEX(Items!B$2:B$1032,MATCH($O101,Items!$A$2:$A$1032,0)) -> #N/A | Q101: =INDEX(Items!C$2:C$1032,MATCH($O101,Items!$A$2:$A$1032,0)) -> #N/A | R101: =INDEX(Items!D$2:D$1032,MATCH($O101,Items!$A$2:$A$1032,0)) -> #N/A
A102: =IF(OR(D102<>D101,D102=""),1,IF(NOT(AND(E102=E101,F102=F101,G102=G101)),A101+1,IF(OR(H102="",AND(H102<>"",H102<>H101,H101<>"")),A101,A101+1))) -> 1 | B102: =IF(D102<>"",TEXT(D102,"YYYYMMDD")&CHAR(64+A102),"") | C102: =IF(OR(B102="",B102<>B101),1,C101+1) -> 1 | F102: =INDEX(Establishment!B$2:B$1005,MATCH($E102,Establishment!$A$2:$A$1005,0)) | G102: =INDEX(Establishment!C$2:C$1005,MATCH($E102,Establishment!$A$2:$A$1005,0)) | M102: =K102*L102 -> 0 | N102: =IF(B102=B101,N101+M102,M102) -> 0 | P102: =INDEX(Items!B$2:B$1032,MATCH($O102,Items!$A$2:$A$1032,0)) -> #N/A | Q102: =INDEX(Items!C$2:C$1032,MATCH($O102,Items!$A$2:$A$1032,0)) -> #N/A | R102: =INDEX(Items!D$2:D$1032,MATCH($O102,Items!$A$2:$A$1032,0)) -> #N/A
A103: =IF(OR(D103<>D102,D103=""),1,IF(NOT(AND(E103=E102,F103=F102,G103=G102)),A102+1,IF(OR(H103="",AND(H103<>"",H103<>H102,H102<>"")),A102,A102+1))) -> 1 | B103: =IF(D103<>"",TEXT(D103,"YYYYMMDD")&CHAR(64+A103),"") | C103: =IF(OR(B103="",B103<>B102),1,C102+1) -> 1 | F103: =INDEX(Establishment!B$2:B$1005,MATCH($E103,Establishment!$A$2:$A$1005,0)) | G103: =INDEX(Establishment!C$2:C$1005,MATCH($E103,Establishment!$A$2:$A$1005,0)) | M103: =K103*L103 -> 0 | N103: =IF(B103=B102,N102+M103,M103) -> 0 | P103: =INDEX(Items!B$2:B$1032,MATCH($O103,Items!$A$2:$A$1032,0)) -> #N/A | Q103: =INDEX(Items!C$2:C$1032,MATCH($O103,Items!$A$2:$A$1032,0)) -> #N/A | R103: =INDEX(Items!D$2:D$1032,MATCH($O103,Items!$A$2:$A$1032,0)) -> #N/A
A104: =IF(OR(D104<>D103,D104=""),1,IF(NOT(AND(E104=E103,F104=F103,G104=G103)),A103+1,IF(OR(H104="",AND(H104<>"",H104<>H103,H103<>"")),A103,A103+1))) -> 1 | B104: =IF(D104<>"",TEXT(D104,"YYYYMMDD")&CHAR(64+A104),"") | C104: =IF(OR(B104="",B104<>B103),1,C103+1) -> 1 | F104: =INDEX(Establishment!B$2:B$1005,MATCH($E104,Establishment!$A$2:$A$1005,0)) | G104: =INDEX(Establishment!C$2:C$1005,MATCH($E104,Establishment!$A$2:$A$1005,0)) | M104: =K104*L104 -> 0 | N104: =IF(B104=B103,N103+M104,M104) -> 0 | P104: =INDEX(Items!B$2:B$1032,MATCH($O104,Items!$A$2:$A$1032,0)) -> #N/A | Q104: =INDEX(Items!C$2:C$1032,MATCH($O104,Items!$A$2:$A$1032,0)) -> #N/A | R104: =INDEX(Items!D$2:D$1032,MATCH($O104,Items!$A$2:$A$1032,0)) -> #N/A
A105: =IF(OR(D105<>D104,D105=""),1,IF(NOT(AND(E105=E104,F105=F104,G105=G104)),A104+1,IF(OR(H105="",AND(H105<>"",H105<>H104,H104<>"")),A104,A104+1))) -> 1 | B105: =IF(D105<>"",TEXT(D105,"YYYYMMDD")&CHAR(64+A105),"") | C105: =IF(OR(B105="",B105<>B104),1,C104+1) -> 1 | F105: =INDEX(Establishment!B$2:B$1005,MATCH($E105,Establishment!$A$2:$A$1005,0)) | G105: =INDEX(Establishment!C$2:C$1005,MATCH($E105,Establishment!$A$2:$A$1005,0)) | M105: =K105*L105 -> 0 | N105: =IF(B105=B104,N104+M105,M105) -> 0 | P105: =INDEX(Items!B$2:B$1032,MATCH($O105,Items!$A$2:$A$1032,0)) -> #N/A | Q105: =INDEX(Items!C$2:C$1032,MATCH($O105,Items!$A$2:$A$1032,0)) -> #N/A | R105: =INDEX(Items!D$2:D$1032,MATCH($O105,Items!$A$2:$A$1032,0)) -> #N/A
A106: =IF(OR(D106<>D105,D106=""),1,IF(NOT(AND(E106=E105,F106=F105,G106=G105)),A105+1,IF(OR(H106="",AND(H106<>"",H106<>H105,H105<>"")),A105,A105+1))) -> 1 | B106: =IF(D106<>"",TEXT(D106,"YYYYMMDD")&CHAR(64+A106),"") | C106: =IF(OR(B106="",B106<>B105),1,C105+1) -> 1 | F106: =INDEX(Establishment!B$2:B$1005,MATCH($E106,Establishment!$A$2:$A$1005,0)) | G106: =INDEX(Establishment!C$2:C$1005,MATCH($E106,Establishment!$A$2:$A$1005,0)) | M106: =K106*L106 -> 0 | N106: =IF(B106=B105,N105+M106,M106) -> 0 | P106: =INDEX(Items!B$2:B$1032,MATCH($O106,Items!$A$2:$A$1032,0)) -> #N/A | Q106: =INDEX(Items!C$2:C$1032,MATCH($O106,Items!$A$2:$A$1032,0)) -> #N/A | R106: =INDEX(Items!D$2:D$1032,MATCH($O106,Items!$A$2:$A$1032,0)) -> #N/A
A107: =IF(OR(D107<>D106,D107=""),1,IF(NOT(AND(E107=E106,F107=F106,G107=G106)),A106+1,IF(OR(H107="",AND(H107<>"",H107<>H106,H106<>"")),A106,A106+1))) -> 1 | B107: =IF(D107<>"",TEXT(D107,"YYYYMMDD")&CHAR(64+A107),"") | C107: =IF(OR(B107="",B107<>B106),1,C106+1) -> 1 | F107: =INDEX(Establishment!B$2:B$1005,MATCH($E107,Establishment!$A$2:$A$1005,0)) | G107: =INDEX(Establishment!C$2:C$1005,MATCH($E107,Establishment!$A$2:$A$1005,0)) | M107: =K107*L107 -> 0 | N107: =IF(B107=B106,N106+M107,M107) -> 0 | P107: =INDEX(Items!B$2:B$1032,MATCH($O107,Items!$A$2:$A$1032,0)) -> #N/A | Q107: =INDEX(Items!C$2:C$1032,MATCH($O107,Items!$A$2:$A$1032,0)) -> #N/A | R107: =INDEX(Items!D$2:D$1032,MATCH($O107,Items!$A$2:$A$1032,0)) -> #N/A
A108: =IF(OR(D108<>D107,D108=""),1,IF(NOT(AND(E108=E107,F108=F107,G108=G107)),A107+1,IF(OR(H108="",AND(H108<>"",H108<>H107,H107<>"")),A107,A107+1))) -> 1 | B108: =IF(D108<>"",TEXT(D108,"YYYYMMDD")&CHAR(64+A108),"") | C108: =IF(OR(B108="",B108<>B107),1,C107+1) -> 1 | F108: =INDEX(Establishment!B$2:B$1005,MATCH($E108,Establishment!$A$2:$A$1005,0)) | G108: =INDEX(Establishment!C$2:C$1005,MATCH($E108,Establishment!$A$2:$A$1005,0)) | M108: =K108*L108 -> 0 | N108: =IF(B108=B107,N107+M108,M108) -> 0 | P108: =INDEX(Items!B$2:B$1032,MATCH($O108,Items!$A$2:$A$1032,0)) -> #N/A | Q108: =INDEX(Items!C$2:C$1032,MATCH($O108,Items!$A$2:$A$1032,0)) -> #N/A | R108: =INDEX(Items!D$2:D$1032,MATCH($O108,Items!$A$2:$A$1032,0)) -> #N/A
A109: =IF(OR(D109<>D108,D109=""),1,IF(NOT(AND(E109=E108,F109=F108,G109=G108)),A108+1,IF(OR(H109="",AND(H109<>"",H109<>H108,H108<>"")),A108,A108+1))) -> 1 | B109: =IF(D109<>"",TEXT(D109,"YYYYMMDD")&CHAR(64+A109),"") | C109: =IF(OR(B109="",B109<>B108),1,C108+1) -> 1 | F109: =INDEX(Establishment!B$2:B$1005,MATCH($E109,Establishment!$A$2:$A$1005,0)) | G109: =INDEX(Establishment!C$2:C$1005,MATCH($E109,Establishment!$A$2:$A$1005,0)) | M109: =K109*L109 -> 0 | N109: =IF(B109=B108,N108+M109,M109) -> 0 | P109: =INDEX(Items!B$2:B$1032,MATCH($O109,Items!$A$2:$A$1032,0)) -> #N/A | Q109: =INDEX(Items!C$2:C$1032,MATCH($O109,Items!$A$2:$A$1032,0)) -> #N/A | R109: =INDEX(Items!D$2:D$1032,MATCH($O109,Items!$A$2:$A$1032,0)) -> #N/A
A110: =IF(OR(D110<>D109,D110=""),1,IF(NOT(AND(E110=E109,F110=F109,G110=G109)),A109+1,IF(OR(H110="",AND(H110<>"",H110<>H109,H109<>"")),A109,A109+1))) -> 1 | B110: =IF(D110<>"",TEXT(D110,"YYYYMMDD")&CHAR(64+A110),"") | C110: =IF(OR(B110="",B110<>B109),1,C109+1) -> 1 | F110: =INDEX(Establishment!B$2:B$1005,MATCH($E110,Establishment!$A$2:$A$1005,0)) | G110: =INDEX(Establishment!C$2:C$1005,MATCH($E110,Establishment!$A$2:$A$1005,0)) | M110: =K110*L110 -> 0 | N110: =IF(B110=B109,N109+M110,M110) -> 0 | P110: =INDEX(Items!B$2:B$1032,MATCH($O110,Items!$A$2:$A$1032,0)) -> #N/A | Q110: =INDEX(Items!C$2:C$1032,MATCH($O110,Items!$A$2:$A$1032,0)) -> #N/A | R110: =INDEX(Items!D$2:D$1032,MATCH($O110,Items!$A$2:$A$1032,0)) -> #N/A
A111: =IF(OR(D111<>D110,D111=""),1,IF(NOT(AND(E111=E110,F111=F110,G111=G110)),A110+1,IF(OR(H111="",AND(H111<>"",H111<>H110,H110<>"")),A110,A110+1))) -> 1 | B111: =IF(D111<>"",TEXT(D111,"YYYYMMDD")&CHAR(64+A111),"") | C111: =IF(OR(B111="",B111<>B110),1,C110+1) -> 1 | F111: =INDEX(Establishment!B$2:B$1005,MATCH($E111,Establishment!$A$2:$A$1005,0)) | G111: =INDEX(Establishment!C$2:C$1005,MATCH($E111,Establishment!$A$2:$A$1005,0)) | M111: =K111*L111 -> 0 | N111: =IF(B111=B110,N110+M111,M111) -> 0 | P111: =INDEX(Items!B$2:B$1032,MATCH($O111,Items!$A$2:$A$1032,0)) -> #N/A | Q111: =INDEX(Items!C$2:C$1032,MATCH($O111,Items!$A$2:$A$1032,0)) -> #N/A | R111: =INDEX(Items!D$2:D$1032,MATCH($O111,Items!$A$2:$A$1032,0)) -> #N/A
... A499: =IF(OR(D499<>D498,D499=""),1,IF(NOT(AND(E499=E498,F499=F498,G499=G498)),A498+1,IF(OR(H499="",AND(H499<>"",H499<>H498,H498<>"")),A498,A498+1))) -> 1 | B499: =IF(D499<>"",TEXT(D499,"YYYYMMDD")&CHAR(64+A499),"") | C499: =IF(OR(B499="",B499<>B498),1,C498+1) -> 1 | F499: =INDEX(Establishment!B$2:B$1005,MATCH($E499,Establishment!$A$2:$A$1005,0)) | G499: =INDEX(Establishment!C$2:C$1005,MATCH($E499,Establishment!$A$2:$A$1005,0)) | M499: =K499*L499 -> 0 | N499: =IF(B499=B498,N498+M499,M499) -> 0 | P499: =INDEX(Items!B$2:B$1032,MATCH($O499,Items!$A$2:$A$1032,0)) -> #N/A | Q499: =INDEX(Items!C$2:C$1032,MATCH($O499,Items!$A$2:$A$1032,0)) -> #N/A | R499: =INDEX(Items!D$2:D$1032,MATCH($O499,Items!$A$2:$A$1032,0)) -> #N/A

Sheet Misc
A1: Payment Type
A2: Cash
A3: MetroBank
A4: HSBC
A5: BPI Debit
A6: GC

Sheet Establishment
A1: ID | B1: Establishment | C1: Branch
A3: =B3&"-"&C3 -> One Time- | B3: One Time
A4: =B4&"-"&C4 -> 1st AutoGas-Panagdait | B4: 1st AutoGas | C4: Panagdait
A5: =B5&"-"&C5 -> A.N.G Cellshoppe-Colon Street | B5: A.N.G Cellshoppe | C5: Colon Street
A6: =B6&"-"&C6 -> Ace Hardware-SM City, Cebu | B6: Ace Hardware | C6: SM City, Cebu
A7: =B7&"-"&C7 -> Ace Hardware-SM Seaside, Cebu | B7: Ace Hardware | C7: SM Seaside, Cebu
A8: =B8&"-"&C8 -> Achi Ichiban-SM City, Cebu | B8: Achi Ichiban | C8: SM City, Cebu
A9: =B9&"-"&C9 -> Aircon Master-R. Landon street | B9: Aircon Master | C9: R. Landon street
A10: =B10&"-"&C10 -> Alberto's Pizza-Basak, Pardo | B10: Alberto's Pizza | C10: Basak, Pardo
A11: =B11&"-"&C11 -> Asian Homes Appliance-Osmenia Blvd. | B11: Asian Homes Appliance | C11: Osmenia Blvd.
A12: =B12&"-"&C12 -> Azian Thai Massage and SPA-Sancianko Street | B12: Azian Thai Massage and SPA | C12: Sancianko Street
A13: =B13&"-"&C13 -> Banana Stall-F. Llamas | B13: Banana Stall | C13: F. Llamas
A14: =B14&"-"&C14 -> Burger King-Panagdait | B14: Burger King | C14: Panagdait
A15: =B15&"-"&C15 -> Carenderia 14th Floor-ACC Tower Cebu Business Park | B15: Carenderia 14th Floor | C15: ACC Tower Cebu Business Park
... A34: =B34&"-"&C34 -> Colonnade-Colon Street | B34: Colonnade | C34: Colon Street
A35: =B35&"-"&C35 -> Crown Hardware- | B35: Crown Hardware
A36: =B36&"-"&C36 -> Delux Bakery-Magallanes | B36: Delux Bakery | C36: Magallanes
A37: =B37&"-"&C37 -> Department of Health-Vivente Sotto Memorial Medical Center | B37: Department of Health | C37: Vivente Sotto Memorial Medical Center
A38: =B38&"-"&C38 -> Diatoms-Katipunan | B38: Diatoms | C38: Katipunan
A39: =B39&"-"&C39 -> Dimsum Break-SM City, Cebu | B39: Dimsum Break | C39: SM City, Cebu
A40: =B40&"-"&C40 -> Domings-Guadalupe | B40: Domings | C40: Guadalupe
A41: =B41&"-"&C41 -> Dr. Edward Chua-Perpetuaql Hospital | B41: Dr. Edward Chua | C41: Perpetuaql Hospital
A42: =B42&"-"&C42 -> Dunkin Donuts-Ayala Center Cebu | B42: Dunkin Donuts | C42: Ayala Center Cebu
A43: =B43&"-"&C43 -> Dunkin Donuts-SM City, Cebu | B43: Dunkin Donuts | C43: SM City, Cebu
A44: =B44&"-"&C44 -> Dunkin Donuts-Super Metro (Basak San Nicolas) | B44: Dunkin Donuts | C44: Super Metro (Basak San Nicolas)
A45: =B45&"-"&C45 -> Echo Appliance Center-Magallanes | B45: Echo Appliance Center | C45: Magallanes
A46: =B46&"-"&C46 -> Egg Seller-C. Padilla (Mambaling) | B46: Egg Seller | C46: C. Padilla (Mambaling)
A47: =B47&"-"&C47 -> Eggcelsior-7Tsi - Guadalupe | B47: Eggcelsior | C47: 7Tsi - Guadalupe
... A73: =B73&"-"&C73 -> JOYOJoyo Marketing-SM Seaside, Cebu | B73: JOYOJoyo Marketing | C73: SM Seaside, Cebu
A74: =B74&"-"&C74 -> JPV-V. Rama Ave. | B74: JPV | C74: V. Rama Ave. | D74: at the back of Phoenix Gasoline Station
A75: =B75&"-"&C75 -> Julies Bakeshope-Basak San Nicolas | B75: Julies Bakeshope | C75: Basak San Nicolas
A76: =B76&"-"&C76 -> Julies Bakeshope-F. Llamas | B76: Julies Bakeshope | C76: F. Llamas
A77: =B77&"-"&C77 -> Julies Bakeshope-Junquera Ext | B77: Julies Bakeshope | C77: Junquera Ext
A78: =B78&"-"&C78 -> Julies Bakeshope-Tisa | B78: Julies Bakeshope | C78: Tisa
A79: =B79&"-"&C79 -> Julies Bakeshope-Urgello | B79: Julies Bakeshope | C79: Urgello
A80: =B80&"-"&C80 -> Kakeng-Parkmall | B80: Kakeng | C80: Parkmall
A81: =B81&"-"&C81 -> Kakeng-Plaridel | B81: Kakeng | C81: Plaridel
A82: =B82&"-"&C82 -> Kapitan AutoParts-Boromeo st. | B82: Kapitan AutoParts | C82: Boromeo st.
A83: =B83&"-"&C83 -> KFC-Panagdait | B83: KFC | C83: Panagdait
A84: =B84&"-"&C84 -> KFC-SM Seaside, Cebu | B84: KFC | C84: SM Seaside, Cebu
A85: =B85&"-"&C85 -> La Fortuna Bakery-Borromeo | B85: La Fortuna Bakery | C85: Borromeo
A86: =B86&"-"&C86 -> Lazada-Online | B86: Lazada | C86: Online
... A164: =B164&"-"&C164 -> Wired Systems Corporation-St. Patricks Square | B164: Wired Systems Corporation | C164: St. Patricks Square
A165: =B165&"-"&C165 -> -
A166: =B166&"-"&C166 -> -
A167: =B167&"-"&C167 -> -
A168: =B168&"-"&C168 -> -
A169: =B169&"-"&C169 -> -
A170: =B170&"-"&C170 -> -
A171: =B171&"-"&C171 -> -
A172: =B172&"-"&C172 -> -
A173: =B173&"-"&C173 -> -
A174: =B174&"-"&C174 -> -
A175: =B175&"-"&C175 -> -
A176: =B176&"-"&C176 -> -
... A236: =B236&"-"&C236 -> -

Sheet Accounts
A1: ID | B1: Type | C1: Account | D1: Detail
A2: =B2&"-"&C2&"-"&D2 -> Accessories-Zach-00000 | B2: Accessories | C2: Zach | D2: 00000
A3: =B3&"-"&C3&"-"&D3 -> Baking-00000-00000 | B3: Baking | C3: 00000 | D3: 00000
A4: =B4&"-"&C4&"-"&D4 -> Bonding-00000-Family | B4: Bonding | C4: 00000 | D4: Family
A5: =B5&"-"&C5&"-"&D5 -> Bonding-00001-Bedian | B5: Bonding | C5: 00001 | D5: Bedian
A6: =B6&"-"&C6&"-"&D6 -> Bonding-00002-Kids | B6: Bonding | C6: 00002 | D6: Kids
A7: =B7&"-"&C7&"-"&D7 -> Bonding-00003-Brayton | B7: Bonding | C7: 00003 | D7: Brayton
A8: =B8&"-"&C8&"-"&D8 -> Bonding-00004-Kaleb | B8: Bonding | C8: 00004 | D8: Kaleb
A9: =B9&"-"&C9&"-"&D9 -> Car-00000-Maintenance | B9: Car | C9: 00000 | D9: Maintenance
A10: =B10&"-"&C10&"-"&D10 -> Car-Avanza-Fuel | B10: Car | C10: Avanza | D10: Fuel
A11: =B11&"-"&C11&"-"&D11 -> Car-Avanza-Laundry | B11: Car | C11: Avanza | D11: Laundry
A12: =B12&"-"&C12&"-"&D12 -> Car-Avanza-Maintenance | B12: Car | C12: Avanza | D12: Maintenance
A13: =B13&"-"&C13&"-"&D13 -> Car-Avanza-Expense | B13: Car | C13: Avanza | D13: Expense
... A16: =B16&"-"&C16&"-"&D16 -> Car-Carens-Expense | B16: Car | C16: Carens | D16: Expense
A17: =B17&"-"&C17&"-"&D17 -> Car-Parking- | B17: Car | C17: Parking
A18: =B18&"-"&C18&"-"&D18 -> Celebration-Zach-00000 | B18: Celebration | C18: Zach | D18: 00000
A19: =B19&"-"&C19&"-"&D19 -> Cellphone-Kaleb-00000 | B19: Cellphone | C19: Kaleb | D19: 00000
A20: =B20&"-"&C20&"-"&D20 -> Cellphone-Bedian-00000 | B20: Cellphone | C20: Bedian | D20: 00000
A21: =B21&"-"&C21&"-"&D21 -> Cellphone-Brayton-00000 | B21: Cellphone | C21: Brayton | D21: 00000
A22: =B22&"-"&C22&"-"&D22 -> Cellphone-Zach-00000 | B22: Cellphone | C22: Zach | D22: 00000
A23: =B23&"-"&C23&"-"&D23 -> Clothing-Brayton-00000 | B23: Clothing | C23: Brayton | D23: 00000
A24: =B24&"-"&C24&"-"&D24 -> Clothing-Kaleb-00000 | B24: Clothing | C24: Kaleb | D24: 00000
A25: =B25&"-"&C25&"-"&D25 -> Computer-Twins-00000 | B25: Computer | C25: Twins | D25: 00000
A26: =B26&"-"&C26&"-"&D26 -> Computer-Bedian-00000 | B26: Computer | C26: Bedian | D26: 00000
A27: =B27&"-"&C27&"-"&D27 -> Computer-Brayton-00000 | B27: Computer | C27: Brayton | D27: 00000
A28: =B28&"-"&C28&"-"&D28 -> Computer-Kaleb-00000 | B28: Computer | C28: Kaleb | D28: 00000
A29: =B29&"-"&C29&"-"&D29 -> Computer-Oldhouse-00000 | B29: Computer | C29: Oldhouse | D29: 00000
... A45: =B45&"-"&C45&"-"&D45 -> Expense-Shirley-00000 | B45: Expense | C45: Shirley | D45: 00000
A46: =B46&"-"&C46&"-"&D46 -> Expense-Keng Offering- | B46: Expense | C46: Keng Offering
A47: Expense-Mama's Offering | B47: Expense | C47: Mama's Offering
A48: =B48&"-"&C48&"-"&D48 -> Expense-Parent's Offering- | B48: Expense | C48: Parent's Offering
A49: =B49&"-"&C49&"-"&D49 -> Expense-Bedian-0000 | B49: Expense | C49: Bedian | D49: 0000
A50: =B50&"-"&C50&"-"&D50 -> Expense-Zach-0000 | B50: Expense | C50: Zach | D50: 0000
A51: =B51&"-"&C51&"-"&D51 -> Expense-Shipping and Delivery-0000 | B51: Expense | C51: Shipping and Delivery | D51: 0000
A52: =B52&"-"&C52&"-"&D52 -> Gift-Twins-00000 | B52: Gift | C52: Twins | D52: 00000
A53: =B53&"-"&C53&"-"&D53 -> Gift-Bedian-00000 | B53: Gift | C53: Bedian | D53: 00000
A54: =B54&"-"&C54&"-"&D54 -> Gift-Brayton-00000 | B54: Gift | C54: Brayton | D54: 00000
A55: =B55&"-"&C55&"-"&D55 -> Gift-Others-00000 | B55: Gift | C55: Others | D55: 00000
A56: =B56&"-"&C56&"-"&D56 -> Gift-Kaleb-00000 | B56: Gift | C56: Kaleb | D56: 00000
A57: =B57&"-"&C57&"-"&D57 -> Grocery-00000-00000 | B57: Grocery | C57: 00000 | D57: 00000
A58: =B58&"-"&C58&"-"&D58 -> Grocery-2nd Floor-00000 | B58: Grocery | C58: 2nd Floor | D58: 00000
A59: =B59&"-"&C59&"-"&D59 -> Grocery-3rd Floor-00000 | B59: Grocery | C59: 3rd Floor | D59: 00000
A60: =B60&"-"&C60&"-"&D60 -> Grocery-Oldhouse-00000 | B60: Grocery | C60: Oldhouse | D60: 00000
... A113: =B113&"-"&C113&"-"&D113 -> Work-Bedian-00000 | B113: Work | C113: Bedian | D113: 00000
A114: =B114&"-"&C114&"-"&D114 -> --
A115: =B115&"-"&C115&"-"&D115 -> --
A116: =B116&"-"&C116&"-"&D116 -> --
A117: =B117&"-"&C117&"-"&D117 -> --
A118: =B118&"-"&C118&"-"&D118 -> --
A119: =B119&"-"&C119&"-"&D119 -> --
A120: =B120&"-"&C120&"-"&D120 -> --
A121: =B121&"-"&C121&"-"&D121 -> --
A122: =B122&"-"&C122&"-"&D122 -> --
A123: =B123&"-"&C123&"-"&D123 -> --

Sheet Items
A1: ID | B1: Brand | C1: Type | D1: Details | E1: Category
E2: Category | G2: 0. One Time only
E3: Category | G3: 1. Medicine
E4: Category | G4: 2. Food and Drinks
E5: Category | G5: 4. Snacks
E6: Category | G6: 5. Automotive
E7: Category | G7: 6. Service
E8: Category | G8: 7. Household
E9: Category | G9: 8. Religious
E10: Category | G10: 9. Discount and Tips
E11: Category | G11: 10. Appliance
E12: Category
A13: =C13&IF(B13<>"","("&B13&") "," ")&D13 -> Unliquidated(Items) | B13: Items | C13: Unliquidated
A14: One Time | C14: One Time | E14: 0. One Time only
A15: =C15&IF(B15<>"","("&B15&") "," ")&D15 -> (Omega) 120ml | B15: Omega | D15: 120ml | E15: 1. Medicine
A16: =C16&IF(B16<>"","("&B16&") "," ")&D16 -> (Omega) 60ml | B16: Omega | D16: 60ml | E16: 1. Medicine
A17: =C17&IF(B17<>"","("&B17&") "," ")&D17 -> (Rosuvastatin) 5mg | B17: Rosuvastatin | D17: 5mg | E17: 1. Medicine
A18: =C18&IF(B18<>"","("&B18&") "," ")&D18 -> Acetylcysteine (Fluimucil) 100mg | B18: Fluimucil | C18: Acetylcysteine | D18: 100mg | E18: 1. Medicine
A19: =C19&IF(B19<>"","("&B19&") "," ")&D19 -> Aldactone(Spironolactone) 25mg | B19: Spironolactone | C19: Aldactone | D19: 25mg | E19: 1. Medicine
A20: Aldactone(Spironolactone) 50mg | B20: Spironolactone | C20: Aldactone | D20: 50mg | E20: 1. Medicine
A21: Amlodipine(Rite-Med) 5mg | B21: Rite-Med | C21: Amlodipine | D21: 5mg | E21: 1. Medicine
A22: =C22&IF(B22<>"","("&B22&") "," ")&D22 -> Antasid(Maalox) | B22: Maalox | C22: Antasid | E22: 1. Medicine
A23: =C23&IF(B23<>"","("&B23&") "," ")&D23 -> Ascorbic Acid(Rhea ) 500mg | B23: Rhea | C23: Ascorbic Acid | D23: 500mg | E23: 1. Medicine
A24: =C24&IF(B24<>"","("&B24&") "," ")&D24 -> Aspirin(Aspilets) 80mg | B24: Aspilets | C24: Aspirin | D24: 80mg | E24: 1. Medicine
A25: =C25&IF(B25<>"","("&B25&") "," ")&D25 -> AZITHROMYCIN Dihydrate(Zithromax) 15ml | B25: Zithromax | C25: AZITHROMYCIN Dihydrate | D25: 15ml | E25: 1. Medicine
A26: =C26&IF(B26<>"","("&B26&") "," ")&D26 -> AZITHROMYCIN Dihydrate(Zithromax) 22.5ml | B26: Zithromax | C26: AZITHROMYCIN Dihydrate | D26: 22.5ml | E26: 1. Medicine
A27: =C27&IF(B27<>"","("&B27&") "," ")&D27 -> Bilaxten(Bilastine) 20mg | B27: Bilastine | C27: Bilaxten | D27: 20mg | E27: 1. Medicine
A28: =C28&IF(B28<>"","("&B28&") "," ")&D28 -> Butamirate Forte(Sinecod) 50mg | B28: Sinecod | C28: Butamirate Forte | D28: 50mg | E28: 1. Medicine
A29: Carvedilol(BetaCard) 25mg | B29: BetaCard | C29: Carvedilol | D29: 25mg | E29: 1. Medicine
A30: Carvedilol(Cardipres) 25mg | B30: Cardipres | C30: Carvedilol | D30: 25mg | E30: 1. Medicine
A31: Carvid(Carvedilol) 25mg | B31: Carvedilol | C31: Carvid | D31: 25mg | E31: 1. Medicine
A32: =C32&IF(B32<>"","("&B32&") "," ")&D32 -> Cetirizine HCL(Rose Pharmacy) 10mg | B32: Rose Pharmacy | C32: Cetirizine HCL | D32: 10mg | E32: 1. Medicine
A33: =C33&IF(B33<>"","("&B33&") "," ")&D33 -> Clonidine HC1(Clonipress) 75mcg | B33: Clonipress | C33: Clonidine HC1 | D33: 75mcg | E33: 1. Medicine
A34: Clopidogrel(PLAZ) 175mg | B34: PLAZ | C34: Clopidogrel | D34: 175mg | E34: 1. Medicine
A35: Clopidogrel(Rhea) 175mg | B35: Rhea | C35: Clopidogrel | D35: 175mg | E35: 1. Medicine
A36: dapagliflozin(ForXiga) 10mg | B36: ForXiga | C36: dapagliflozin | D36: 10mg | E36: 1. Medicine
A37: =C37&IF(B37<>"","("&B37&") "," ")&D37 -> dapagliflozin/Metformin HCl(xigduo) 10mg/1000mg Tablet | B37: xigduo | C37: dapagliflozin/Metformin HCl | D37: 10mg/1000mg Tablet | E37: 1. Medicine
A38: Diamicron(Gliclazide ) 60mg | B38: Gliclazide | C38: Diamicron | D38: 60mg | E38: 1. Medicine
A39: =C39&IF(B39<>"","("&B39&") "," ")&D39 -> Doxofylline(Ansimar) 100mg/5ml | B39: Ansimar | C39: Doxofylline | D39: 100mg/5ml | E39: 1. Medicine
A40: =C40&IF(B40<>"","("&B40&") "," ")&D40 -> Energen(Chocolate) 8x30x40g | B40: Chocolate | C40: Energen | D40: 8x30x40g | E40: 1. Medicine
A41: Entresto(Sacubitril, Valsartan) 100mg | B41: Sacubitril, Valsartan | C41: Entresto | D41: 100mg | E41: 1. Medicine
A42: Entresto(Sacubitril, Valsartan) 200mg | B42: Sacubitril, Valsartan | C42: Entresto | D42: 200mg | E42: 1. Medicine
A43: =C43&IF(B43<>"","("&B43&") "," ")&D43 -> Face Mask(Generic) KN95 | B43: Generic | C43: Face Mask | D43: KN95 | E43: 1. Medicine
A44: =C44&IF(B44<>"","("&B44&") "," ")&D44 -> Face Mask(Generic) Surgical | B44: Generic | C44: Face Mask | D44: Surgical | E44: 1. Medicine
A45: Glyxambi(Empagliflozin Linagliptin) 25mg/5mg | B45: Empagliflozin Linagliptin | C45: Glyxambi | D45: 25mg/5mg | E45: 1. Medicine
A46: Glyxambi(Empagliflozin Linagliptin) T10/5mg | B46: Empagliflozin Linagliptin | C46: Glyxambi | D46: T10/5mg | E46: 1. Medicine
A47: =C47&IF(B47<>"","("&B47&") "," ")&D47 -> Inhaler(Vicks) Keychain | B47: Vicks | C47: Inhaler | D47: Keychain | E47: 1. Medicine
A48: =C48&IF(B48<>"","("&B48&") "," ")&D48 -> IPRATROPIUM Bromide SABUTAMOL(Pulmodual) 500mcg / 2.5mg per 2.5mL | B48: Pulmodual | C48: IPRATROPIUM Bromide SABUTAMOL | D48: 500mcg / 2.5mg per 2.5mL | E48: 1. Medicine
A49: =C49&IF(B49<>"","("&B49&") "," ")&D49 -> Kefir(Wellnessland Wellness Center) | B49: Wellnessland Wellness Center | C49: Kefir | E49: 1. Medicine
A50: Loperamide(Diatabs) 2mg | B50: Diatabs | C50: Loperamide | D50: 2mg | E50: 1. Medicine
A51: Losartan(Neosartan) 100mg | B51: Neosartan | C51: Losartan | D51: 100mg | E51: 1. Medicine
A52: =C52&IF(B52<>"","("&B52&") "," ")&D52 -> Losartan(Rite-Med) 100mg | B52: Rite-Med | C52: Losartan | D52: 100mg | E52: 1. Medicine
A53: =C53&IF(B53<>"","("&B53&") "," ")&D53 -> Losartan(Rose Pharmacy) 100mg | B53: Rose Pharmacy | C53: Losartan | D53: 100mg | E53: 1. Medicine | F53: Losartan(Neosartan) 100mg | G53: Neosartan | H53: Losartan | I53: 100mg | J53: 1. Medicine | K53: Losartan(Neosartan) 100mg | L53: Neosartan | M53: Losartan | N53: 100mg | O53: 1. Medicine | P53: Losartan(Neosartan) 100mg | Q53: Neosartan | R53: Losartan | S53: 100mg | T53: 1. Medicine | U53: Losartan(Neosartan) 100mg | V53: Neosartan | W53: Losartan | X53: 100mg | Y53: 1. Medicine
A54: =C54&IF(B54<>"","("&B54&") "," ")&D54 -> Mefenamic(Rhea) 500mg | B54: Rhea | C54: Mefenamic | D54: 500mg | E54: 1. Medicine
A55: Mefenamic(Rite-Med) 500mg | B55: Rite-Med | C55: Mefenamic | D55: 500mg | E55: 1. Medicine
A56: =C56&IF(B56<>"","("&B56&") "," ")&D56 -> Melandy MR(Gliclazide ) 60mg | B56: Gliclazide | C56: Melandy MR | D56: 60mg | E56: 1. Medicine
A57: =C57&IF(B57<>"","("&B57&") "," ")&D57 -> Metformin(Neoform) 500mg | B57: Neoform | C57: Metformin | D57: 500mg | E57: 1. Medicine
A58: =C58&IF(B58<>"","("&B58&") "," ")&D58 -> Methformin Hydrochloride(Fornidd XR) 1g | B58: Fornidd XR | C58: Methformin Hydrochloride | D58: 1g | E58: 1. Medicine
A59: =C59&IF(B59<>"","("&B59&") "," ")&D59 -> Methformin Hydrochloride(Glumet-XR) 500mg | B59: Glumet-XR | C59: Methformin Hydrochloride | D59: 500mg | E59: 1. Medicine
A60: Methformin(Glumet) 1g | B60: Glumet | C60: Methformin | D60: 1g | E60: 1. Medicine
A61: Methformin(Glumet) 500mg | B61: Glumet | C61: Methformin | D61: 500mg | E61: 1. Medicine
A62: Methformin(NeoForm) 100g | B62: NeoForm | C62: Methformin | D62: 100g | E62: 1. Medicine
A63: Methformin(Rhea) 500mg | B63: Rhea | C63: Methformin | D63: 500mg | E63: 1. Medicine
A64: =C64&IF(B64<>"","("&B64&") "," ")&D64 -> Methol Camphor Eucalyptus Oil(Efficascent Relaxscent Oil) 500mg | B64: Efficascent Relaxscent Oil | C64: Methol Camphor Eucalyptus Oil | D64: 500mg | E64: 1. Medicine
A65: =C65&IF(B65<>"","("&B65&") "," ")&D65 -> Methol Camphor Eucalyptus Oil(Efficascent) 6ml [Roll-On] | B65: Efficascent | C65: Methol Camphor Eucalyptus Oil | D65: 6ml [Roll-On] | E65: 1. Medicine | F65: (Efficascent Oil) 6ml
A66: =C66&IF(B66<>"","("&B66&") "," ")&D66 -> MONTELUKAST Sodium/LEVOCETIRIZINE Dihydrochloride(Co-Altria Ped) 5mg/5mg Chewable | B66: Co-Altria Ped | C66: MONTELUKAST Sodium/LEVOCETIRIZINE Dihydrochloride | D66: 5mg/5mg Chewable | E66: 1. Medicine
A67: =C67&IF(B67<>"","("&B67&") "," ")&D67 -> Multivitamin(Cecon) Plus Zinc | B67: Cecon | C67: Multivitamin | D67: Plus Zinc | E67: 1. Medicine
A68: =C68&IF(B68<>"","("&B68&") "," ")&D68 -> Multivitamins with B Complex(Pharmaton Essential) 9 + 1 | B68: Pharmaton Essential | C68: Multivitamins with B Complex | D68: 9 + 1 | E68: 1. Medicine
A69: =C69&IF(B69<>"","("&B69&") "," ")&D69 -> Multivitamins(Enervon) | B69: Enervon | C69: Multivitamins | E69: 1. Medicine
A70: =C70&IF(B70<>"","("&B70&") "," ")&D70 -> Multivitamins(Enervon) 30 | B70: Enervon | C70: Multivitamins | D70: 30 | E70: 1. Medicine
A71: =C71&IF(B71<>"","("&B71&") "," ")&D71 -> Sodium Ascorbate Zinc(ImmunPro) 500mg | B71: ImmunPro | C71: Sodium Ascorbate Zinc | D71: 500mg | E71: 1. Medicine
A72: =C72&IF(B72<>"","("&B72&") "," ")&D72 -> Nebulizer Kit Mask (Sanjo ) Pedia | B72: Sanjo | C72: Nebulizer Kit Mask | D72: Pedia | E72: 1. Medicine
A73: Omacor(Elcosapentaenoic Acid, Docosahexaenoic Acid) 460mg/380mg | B73: Elcosapentaenoic Acid, Docosahexaenoic Acid | C73: Omacor | D73: 460mg/380mg | E73: 1. Medicine
A74: =C74&IF(B74<>"","("&B74&") "," ")&D74 -> Orlistat(Lesofat) 120mg | B74: Lesofat | C74: Orlistat | D74: 120mg | E74: 1. Medicine
A75: =C75&IF(B75<>"","("&B75&") "," ")&D75 -> Pantoprazole + Domperidone(Panto Plus) 40mg/30mg | B75: Panto Plus | C75: Pantoprazole + Domperidone | D75: 40mg/30mg | E75: 1. Medicine
A76: =C76&IF(B76<>"","("&B76&") "," ")&D76 -> Paracetamol(Decolgen) Forte | B76: Decolgen | C76: Paracetamol | D76: Forte | E76: 1. Medicine
A77: =C77&IF(B77<>"","("&B77&") "," ")&D77 -> Pastilles(Scotts) 30Mg30 | B77: Scotts | C77: Pastilles | D77: 30Mg30 | E77: 1. Medicine
A78: =C78&IF(B78<>"","("&B78&") "," ")&D78 -> Pastilles(Valda) Menthol | B78: Valda | C78: Pastilles | D78: Menthol | E78: 1. Medicine
A79: =C79&IF(B79<>"","("&B79&") "," ")&D79 -> Lemon Menthol Pastilles(Valda) 20g | B79: Valda | C79: Lemon Menthol Pastilles | D79: 20g | E79: 1. Medicine
A80: =C80&IF(B80<>"","("&B80&") "," ")&D80 -> Petroleum Jelly(Apollo) 200g | B80: Apollo | C80: Petroleum Jelly | D80: 200g | E80: 1. Medicine
A81: =C81&IF(B81<>"","("&B81&") "," ")&D81 -> Plaster(GDN) Plastic | B81: GDN | C81: Plaster | D81: Plastic | E81: 1. Medicine
A82: =C82&IF(B82<>"","("&B82&") "," ")&D82 -> Prednisolone(Pred 20) 20mg/5mL Syrup | B82: Pred 20 | C82: Prednisolone | D82: 20mg/5mL Syrup | E82: 1. Medicine
A83: =C83&IF(B83<>"","("&B83&") "," ")&D83 -> Psyllium Fiber Husk(C-Lium) Fibre | B83: C-Lium | C83: Psyllium Fiber Husk | D83: Fibre | E83: 1. Medicine
A84: =C84&IF(B84<>"","("&B84&") "," ")&D84 -> Racecadotril(Hidrasec) 100mg | B84: Hidrasec | C84: Racecadotril | D84: 100mg | E84: 1. Medicine
A85: =C85&IF(B85<>"","("&B85&") "," ")&D85 -> Refreshing Oil(Vaporin) 10ml | B85: Vaporin | C85: Refreshing Oil | D85: 10ml | E85: 1. Medicine
... A100: =C100&IF(B100<>"","("&B100&") "," ")&D100 -> Zeltine-MR(Gliclazide ) 60mg | B100: Gliclazide | C100: Zeltine-MR | D100: 60mg | E100: 1. Medicine
A101: =C101&IF(B101<>"","("&B101&") "," ")&D101 -> Pill Cutter | C101: Pill Cutter | E101: 1. Medicine
A102: =C102&IF(B102<>"","("&B102&") "," ")&D102 -> Electric Fan(Union) Industrial 18" | B102: Union | C102: Electric Fan | D102: Industrial 18" | E102: 10. Appliance
A103: =C103&IF(B103<>"","("&B103&") "," ")&D103 -> (Yakult) 80ml | B103: Yakult | D103: 80ml | E103: 2. Food and Drinks
A104: =C104&IF(B104<>"","("&B104&") "," ")&D104 -> 3in1 Mixes(Family Choice) 250g | B104: Family Choice | C104: 3in1 Mixes | D104: 250g | E104: 2. Food and Drinks
A105: =C105&IF(B105<>"","("&B105&") "," ")&D105 -> Biscuits(Nissin) Eggnog 130g | B105: Nissin | C105: Biscuits | D105: Eggnog 130g | E105: 4. Snacks
A106: =C106&IF(B106<>"","("&B106&") "," ")&D106 -> Biscuits(Malkist) Olezz Cheese Choco 100g | B106: Malkist | C106: Biscuits | D106: Olezz Cheese Choco 100g | E106: 4. Snacks
A107: =C107&IF(B107<>"","("&B107&") "," ")&D107 -> Biscuits(Marky's) Pacencia Biscuit 210g | B107: Marky's | C107: Biscuits | D107: Pacencia Biscuit 210g | E107: 4. Snacks
A108: =C108&IF(B108<>"","("&B108&") "," ")&D108 -> Biscuits(Skyflakes) 200g HPack | B108: Skyflakes | C108: Biscuits | D108: 200g HPack | E108: 4. Snacks
A109: =C109&IF(B109<>"","("&B109&") "," ")&D109 -> Biscuits(Skyflakes) 25g | B109: Skyflakes | C109: Biscuits | D109: 25g | E109: 4. Snacks
A110: =C110&IF(B110<>"","("&B110&") "," ")&D110 -> Chocholate Biscuits(Presto Cream) 30g | B110: Presto Cream | C110: Chocholate Biscuits | D110: 30g | E110: 4. Snacks | J110: =A110 -> Chocholate Biscuits(Presto Cream) 30g
A111: =C111&IF(B111<>"","("&B111&") "," ")&D111 -> Chocholate Peanut Biscuits(Presto Cream) 30g | B111: Presto Cream | C111: Chocholate Peanut Biscuits | D111: 30g | E111: 4. Snacks | J111: =A111 -> Chocholate Peanut Biscuits(Presto Cream) 30g
A112: =C112&IF(B112<>"","("&B112&") "," ")&D112 -> Choco Fudge Cream-Filled Chocolate Sandwich Biscuits(Cream-o) 30g | B112: Cream-o | C112: Choco Fudge Cream-Filled Chocolate Sandwich Biscuits | D112: 30g | E112: 4. Snacks | J112: =A112 -> Choco Fudge Cream-Filled Chocolate Sandwich Biscuits(Cream-o) 30g
A113: =C113&IF(B113<>"","("&B113&") "," ")&D113 -> Strawberry's Cream Biscuits(Jack 'n Jill Drewberry) 33g | B113: Jack 'n Jill Drewberry | C113: Strawberry's Cream Biscuits | D113: 33g | E113: 4. Snacks | J113: =A113 -> Strawberry's Cream Biscuits(Jack 'n Jill Drewberry) 33g
A114: =C114&IF(B114<>"","("&B114&") "," ")&D114 -> Drewberries'n Cream Biscuits(Jack 'n Jill Drewberry) 33g | B114: Jack 'n Jill Drewberry | C114: Drewberries'n Cream Biscuits | D114: 33g | E114: 4. Snacks | J114: =A114 -> Drewberries'n Cream Biscuits(Jack 'n Jill Drewberry) 33g
...

Sheet Sheet1
A1: 26.698 | B1: =A1 -> 26.698 | C1: =B1 -> 26.698 | D1: =B1 -> 26.698 | F1: 26.698
A2: 24.469 | B2: =A2 -> 24.469 | C2: =B2 -> 24.469 | E2: 24.469
A3: 23.583 | B3: =A3 -> 23.583 | C3: =B3 -> 23.583 | E3: 23.583
A4: 20 | B4: =A4 -> 20 | C4: =B4 -> 20
A5: 18.487 | B5: =A5 -> 18.487 | C5: 9 | D5: =B5 -> 18.487 | F5: 18.487
A6: 13.523 | B6: =A6 -> 13.523 | C6: =B6 -> 13.523 | D6: =B6 -> 13.523
A7: 2.727 | B7: =A7 -> 2.727 | C7: =B7 -> 2.727 | D7: =B7 -> 2.727 | F7: 2.727
A8: =SUM(A1:A7) -> 129.487 | B8: =SUM(B1:B7) -> 129.487 | C8: =SUM(C1:C7) -> 120 | D8: =SUM(D1:D7) -> 61.435 | E8: =SUM(E1:E7) -> 48.052 | F8: =SUM(F1:F7) -> 47.912
C9: =C8-120 -> 0 | D9: =D8-60 -> 1.435 | E9: =E8-60 -> -11.948 | F9: =F8-60 -> -12.088
C10: =57*C9 -> 0 | E10: =57*E9 -> -681.036 | F10: =57*F9 -> -689.016

Sheet 2023-01
A1: Count | B1: Transaction Number | C1: Detail # | D1: Date | E1: Establishment Id | F1: Establishment | G1: Branch | H1: Payment Type | I1: Amount | J1: Account | K1: Quantity | L1: Unit Price | M1: Amount | N1: Total | O1: Item ID | P1: Brand | Q1: Type | R1: Details | S1: Notes
A2: =IF(OR(D2<>D1,D2=""),1,IF(NOT(AND(E2=E1,F2=F1,G2=G1)),A1+1,IF(OR(H2="",AND(H2<>"",H2<>H1,H1<>"")),A1,A1+1))) -> 1 | B2: =IF(D2<>"",TEXT(D2,"YYYYMMDD")&CHAR(64+A2),"") | C2: =IF(OR(B2="",B2<>B10),1,C10+1) -> 1 | F2: =INDEX(Establishment!B$2:B$1005,MATCH($E2,Establishment!$A$2:$A$1005,0)) -> #N/A | G2: =INDEX(Establishment!C$2:C$1005,MATCH($E2,Establishment!$A$2:$A$1005,0)) -> #N/A | M2: =K2*L2 -> 0 | N2: =IF(B2=B1,N1+M2,M2) -> 0 | P2: =INDEX(Items!B$2:B$1032,MATCH($O2,Items!$A$2:$A$1032,0)) -> #N/A | Q2: =INDEX(Items!C$2:C$1032,MATCH($O2,Items!$A$2:$A$1032,0)) -> #N/A | R2: =INDEX(Items!D$2:D$1032,MATCH($O2,Items!$A$2:$A$1032,0)) -> #N/A
A3: =IF(OR(D3<>D2,D3=""),1,IF(NOT(AND(E3=E2,F3=F2,G3=G2)),A2+1,IF(OR(H3="",AND(H3<>"",H3<>H2,H2<>"")),A2,A2+1))) -> 1 | B3: =IF(D3<>"",TEXT(D3,"YYYYMMDD")&CHAR(64+A3),"") | C3: =IF(OR(B3="",B3<>B11),1,C11+1) -> 1 | F3: =INDEX(Establishment!B$2:B$1005,MATCH($E3,Establishment!$A$2:$A$1005,0)) -> #N/A | G3: =INDEX(Establishment!C$2:C$1005,MATCH($E3,Establishment!$A$2:$A$1005,0)) -> #N/A | M3: =K3*L3 -> 0 | N3: =IF(B3=B2,N2+M3,M3) -> 0 | P3: =INDEX(Items!B$2:B$1032,MATCH($O3,Items!$A$2:$A$1032,0)) -> #N/A | Q3: =INDEX(Items!C$2:C$1032,MATCH($O3,Items!$A$2:$A$1032,0)) -> #N/A | R3: =INDEX(Items!D$2:D$1032,MATCH($O3,Items!$A$2:$A$1032,0)) -> #N/A
A4: =IF(OR(D4<>D3,D4=""),1,IF(NOT(AND(E4=E3,F4=F3,G4=G3)),A3+1,IF(OR(H4="",AND(H4<>"",H4<>H3,H3<>"")),A3,A3+1))) -> 1 | B4: =IF(D4<>"",TEXT(D4,"YYYYMMDD")&CHAR(64+A4),"") | C4: =IF(OR(B4="",B4<>B12),1,C12+1) -> 1 | F4: =INDEX(Establishment!B$2:B$1005,MATCH($E4,Establishment!$A$2:$A$1005,0)) -> #N/A | G4: =INDEX(Establishment!C$2:C$1005,MATCH($E4,Establishment!$A$2:$A$1005,0)) -> #N/A | M4: =K4*L4 -> 0 | N4: =IF(B4=B3,N3+M4,M4) -> 0 | P4: =INDEX(Items!B$2:B$1032,MATCH($O4,Items!$A$2:$A$1032,0)) -> #N/A | Q4: =INDEX(Items!C$2:C$1032,MATCH($O4,Items!$A$2:$A$1032,0)) -> #N/A | R4: =INDEX(Items!D$2:D$1032,MATCH($O4,Items!$A$2:$A$1032,0)) -> #N/A
A5: =IF(OR(D5<>D4,D5=""),1,IF(NOT(AND(E5=E4,F5=F4,G5=G4)),A4+1,IF(OR(H5="",AND(H5<>"",H5<>H4,H4<>"")),A4,A4+1))) -> 1 | B5: =IF(D5<>"",TEXT(D5,"YYYYMMDD")&CHAR(64+A5),"") | C5: =IF(OR(B5="",B5<>B13),1,C13+1) -> 1 | F5: =INDEX(Establishment!B$2:B$1005,MATCH($E5,Establishment!$A$2:$A$1005,0)) -> #N/A | G5: =INDEX(Establishment!C$2:C$1005,MATCH($E5,Establishment!$A$2:$A$1005,0)) -> #N/A | M5: =K5*L5 -> 0 | N5: =IF(B5=B4,N4+M5,M5) -> 0 | P5: =INDEX(Items!B$2:B$1032,MATCH($O5,Items!$A$2:$A$1032,0)) -> #N/A | Q5: =INDEX(Items!C$2:C$1032,MATCH($O5,Items!$A$2:$A$1032,0)) -> #N/A | R5: =INDEX(Items!D$2:D$1032,MATCH($O5,Items!$A$2:$A$1032,0)) -> #N/A
A6: =IF(OR(D6<>D5,D6=""),1,IF(NOT(AND(E6=E5,F6=F5,G6=G5)),A5+1,IF(OR(H6="",AND(H6<>"",H6<>H5,H5<>"")),A5,A5+1))) -> 1 | B6: =IF(D6<>"",TEXT(D6,"YYYYMMDD")&CHAR(64+A6),"") | C6: =IF(OR(B6="",B6<>B14),1,C14+1) -> 1 | F6: =INDEX(Establishment!B$2:B$1005,MATCH($E6,Establishment!$A$2:$A$1005,0)) -> #N/A | G6: =INDEX(Establishment!C$2:C$1005,MATCH($E6,Establishment!$A$2:$A$1005,0)) -> #N/A | M6: =K6*L6 -> 0 | N6: =IF(B6=B5,N5+M6,M6) -> 0 | P6: =INDEX(Items!B$2:B$1032,MATCH($O6,Items!$A$2:$A$1032,0)) -> #N/A | Q6: =INDEX(Items!C$2:C$1032,MATCH($O6,Items!$A$2:$A$1032,0)) -> #N/A | R6: =INDEX(Items!D$2:D$1032,MATCH($O6,Items!$A$2:$A$1032,0)) -> #N/A
A7: =IF(OR(D7<>D6,D7=""),1,IF(NOT(AND(E7=E6,F7=F6,G7=G6)),A6+1,IF(OR(H7="",AND(H7<>"",H7<>H6,H6<>"")),A6,A6+1))) -> 1 | B7: =IF(D7<>"",TEXT(D7,"YYYYMMDD")&CHAR(64+A7),"") | C7: =IF(OR(B7="",B7<>B15),1,C15+1) -> 1 | F7: =INDEX(Establishment!B$2:B$1005,MATCH($E7,Establishment!$A$2:$A$1005,0)) -> #N/A | G7: =INDEX(Establishment!C$2:C$1005,MATCH($E7,Establishment!$A$2:$A$1005,0)) -> #N/A | M7: =K7*L7 -> 0 | N7: =IF(B7=B6,N6+M7,M7) -> 0 | P7: =INDEX(Items!B$2:B$1032,MATCH($O7,Items!$A$2:$A$1032,0)) -> #N/A | Q7: =INDEX(Items!C$2:C$1032,MATCH($O7,Items!$A$2:$A$1032,0)) -> #N/A | R7: =INDEX(Items!D$2:D$1032,MATCH($O7,Items!$A$2:$A$1032,0)) -> #N/A
A8: =IF(OR(D8<>D7,D8=""),1,IF(NOT(AND(E8=E7,F8=F7,G8=G7)),A7+1,IF(OR(H8="",AND(H8<>"",H8<>H7,H7<>"")),A7,A7+1))) -> 1 | B8: =IF(D8<>"",TEXT(D8,"YYYYMMDD")&CHAR(64+A8),"") | C8: =IF(OR(B8="",B8<>B7),1,C7+1) -> 1 | F8: =INDEX(Establishment!B$2:B$1005,MATCH($E8,Establishment!$A$2:$A$1005,0)) -> #N/A | G8: =INDEX(Establishment!C$2:C$1005,MATCH($E8,Establishment!$A$2:$A$1005,0)) -> #N/A | M8: =K8*L8 -> 0 | N8: =IF(B8=B7,N7+M8,M8) -> 0 | P8: =INDEX(Items!B$2:B$1032,MATCH($O8,Items!$A$2:$A$1032,0)) -> #N/A | Q8: =INDEX(Items!C$2:C$1032,MATCH($O8,Items!$A$2:$A$1032,0)) -> #N/A | R8: =INDEX(Items!D$2:D$1032,MATCH($O8,Items!$A$2:$A$1032,0)) -> #N/A
A9: =IF(OR(D9<>D8,D9=""),1,IF(NOT(AND(E9=E8,F9=F8,G9=G8)),A8+1,IF(OR(H9="",AND(H9<>"",H9<>H8,H8<>"")),A8,A8+1))) -> 1 | B9: =IF(D9<>"",TEXT(D9,"YYYYMMDD")&CHAR(64+A9),"") | C9: =IF(OR(B9="",B9<>B8),1,C8+1) -> 1 | F9: =INDEX(Establishment!B$2:B$1005,MATCH($E9,Establishment!$A$2:$A$1005,0)) -> #N/A | G9: =INDEX(Establishment!C$2:C$1005,MATCH($E9,Establishment!$A$2:$A$1005,0)) -> #N/A | M9: =K9*L9 -> 0 | N9: =IF(B9=B8,N8+M9,M9) -> 0 | P9: =INDEX(Items!B$2:B$1032,MATCH($O9,Items!$A$2:$A$1032,0)) -> #N/A | Q9: =INDEX(Items!C$2:C$1032,MATCH($O9,Items!$A$2:$A$1032,0)) -> #N/A | R9: =INDEX(Items!D$2:D$1032,MATCH($O9,Items!$A$2:$A$1032,0)) -> #N/A
A10: =IF(OR(D10<>D9,D10=""),1,IF(NOT(AND(E10=E9,F10=F9,G10=G9)),A9+1,IF(OR(H10="",AND(H10<>"",H10<>H9,H9<>"")),A9,A9+1))) -> 1 | B10: =IF(D10<>"",TEXT(D10,"YYYYMMDD")&CHAR(64+A10),"") | C10: =IF(OR(B10="",B10<>B9),1,C9+1) -> 1 | F10: =INDEX(Establishment!B$2:B$1005,MATCH($E10,Establishment!$A$2:$A$1005,0)) -> #N/A | G10: =INDEX(Establishment!C$2:C$1005,MATCH($E10,Establishment!$A$2:$A$1005,0)) -> #N/A | M10: =K10*L10 -> 0 | N10: =IF(B10=B9,N9+M10,M10) -> 0 | P10: =INDEX(Items!B$2:B$1032,MATCH($O10,Items!$A$2:$A$1032,0)) -> #N/A | Q10: =INDEX(Items!C$2:C$1032,MATCH($O10,Items!$A$2:$A$1032,0)) -> #N/A | R10: =INDEX(Items!D$2:D$1032,MATCH($O10,Items!$A$2:$A$1032,0)) -> #N/A
A11: =IF(OR(D11<>D10,D11=""),1,IF(NOT(AND(E11=E10,F11=F10,G11=G10)),A10+1,IF(OR(H11="",AND(H11<>"",H11<>H10,H10<>"")),A10,A10+1))) -> 1 | B11: =IF(D11<>"",TEXT(D11,"YYYYMMDD")&CHAR(64+A11),"") | C11: =IF(OR(B11="",B11<>B10),1,C10+1) -> 1 | F11: =INDEX(Establishment!B$2:B$1005,MATCH($E11,Establishment!$A$2:$A$1005,0)) -> #N/A | G11: =INDEX(Establishment!C$2:C$1005,MATCH($E11,Establishment!$A$2:$A$1005,0)) -> #N/A | M11: =K11*L11 -> 0 | N11: =IF(B11=B10,N10+M11,M11) -> 0 | P11: =INDEX(Items!B$2:B$1032,MATCH($O11,Items!$A$2:$A$1032,0)) -> #N/A | Q11: =INDEX(Items!C$2:C$1032,MATCH($O11,Items!$A$2:$A$1032,0)) -> #N/A | R11: =INDEX(Items!D$2:D$1032,MATCH($O11,Items!$A$2:$A$1032,0)) -> #N/A
A12: =IF(OR(D12<>D11,D12=""),1,IF(NOT(AND(E12=E11,F12=F11,G12=G11)),A11+1,IF(OR(H12="",AND(H12<>"",H12<>H11,H11<>"")),A11,A11+1))) -> 1 | B12: =IF(D12<>"",TEXT(D12,"YYYYMMDD")&CHAR(64+A12),"") | C12: =IF(OR(B12="",B12<>B11),1,C11+1) -> 1 | F12: =INDEX(Establishment!B$2:B$1005,MATCH($E12,Establishment!$A$2:$A$1005,0)) -> #N/A | G12: =INDEX(Establishment!C$2:C$1005,MATCH($E12,Establishment!$A$2:$A$1005,0)) -> #N/A | M12: =K12*L12 -> 0 | N12: =IF(B12=B11,N11+M12,M12) -> 0 | P12: =INDEX(Items!B$2:B$1032,MATCH($O12,Items!$A$2:$A$1032,0)) -> #N/A | Q12: =INDEX(Items!C$2:C$1032,MATCH($O12,Items!$A$2:$A$1032,0)) -> #N/A | R12: =INDEX(Items!D$2:D$1032,MATCH($O12,Items!$A$2:$A$1032,0)) -> #N/A
A13: =IF(OR(D13<>D12,D13=""),1,IF(NOT(AND(E13=E12,F13=F12,G13=G12)),A12+1,IF(OR(H13="",AND(H13<>"",H13<>H12,H12<>"")),A12,A12+1))) -> 1 | B13: =IF(D13<>"",TEXT(D13,"YYYYMMDD")&CHAR(64+A13),"") | C13: =IF(OR(B13="",B13<>B12),1,C12+1) -> 1 | F13: =INDEX(Establishment!B$2:B$1005,MATCH($E13,Establishment!$A$2:$A$1005,0)) -> #N/A | G13: =INDEX(Establishment!C$2:C$1005,MATCH($E13,Establishment!$A$2:$A$1005,0)) -> #N/A | M13: =K13*L13 -> 0 | N13: =IF(B13=B12,N12+M13,M13) -> 0 | P13: =INDEX(Items!B$2:B$1032,MATCH($O13,Items!$A$2:$A$1032,0)) -> #N/A | Q13: =INDEX(Items!C$2:C$1032,MATCH($O13,Items!$A$2:$A$1032,0)) -> #N/A | R13: =INDEX(Items!D$2:D$1032,MATCH($O13,Items!$A$2:$A$1032,0)) -> #N/A
A14: =IF(OR(D14<>D13,D14=""),1,IF(NOT(AND(E14=E13,F14=F13,G14=G13)),A13+1,IF(OR(H14="",AND(H14<>"",H14<>H13,H13<>"")),A13,A13+1))) -> 1 | B14: =IF(D14<>"",TEXT(D14,"YYYYMMDD")&CHAR(64+A14),"") | C14: =IF(OR(B14="",B14<>B13),1,C13+1) -> 1 | F14: =INDEX(Establishment!B$2:B$1005,MATCH($E14,Establishment!$A$2:$A$1005,0)) -> #N/A | G14: =INDEX(Establishment!C$2:C$1005,MATCH($E14,Establishment!$A$2:$A$1005,0)) -> #N/A | M14: =K14*L14 -> 0 | N14: =IF(B14=B13,N13+M14,M14) -> 0 | P14: =INDEX(Items!B$2:B$1032,MATCH($O14,Items!$A$2:$A$1032,0)) -> #N/A | Q14: =INDEX(Items!C$2:C$1032,MATCH($O14,Items!$A$2:$A$1032,0)) -> #N/A | R14: =INDEX(Items!D$2:D$1032,MATCH($O14,Items!$A$2:$A$1032,0)) -> #N/A
A15: =IF(OR(D15<>D14,D15=""),1,IF(NOT(AND(E15=E14,F15=F14,G15=G14)),A14+1,IF(OR(H15="",AND(H15<>"",H15<>H14,H14<>"")),A14,A14+1))) -> 1 | B15: =IF(D15<>"",TEXT(D15,"YYYYMMDD")&CHAR(64+A15),"") | C15: =IF(OR(B15="",B15<>B14),1,C14+1) -> 1 | F15: =INDEX(Establishment!B$2:B$1005,MATCH($E15,Establishment!$A$2:$A$1005,0)) -> #N/A | G15: =INDEX(Establishment!C$2:C$1005,MATCH($E15,Establishment!$A$2:$A$1005,0)) -> #N/A | M15: =K15*L15 -> 0 | N15: =IF(B15=B14,N14+M15,M15) -> 0 | P15: =INDEX(Items!B$2:B$1032,MATCH($O15,Items!$A$2:$A$1032,0)) -> #N/A | Q15: =INDEX(Items!C$2:C$1032,MATCH($O15,Items!$A$2:$A$1032,0)) -> #N/A | R15: =INDEX(Items!D$2:D$1032,MATCH($O15,Items!$A$2:$A$1032,0)) -> #N/A
A16: =IF(OR(D16<>D15,D16=""),1,IF(NOT(AND(E16=E15,F16=F15,G16=G15)),A15+1,IF(OR(H16="",AND(H16<>"",H16<>H15,H15<>"")),A15,A15+1))) -> 1 | B16: =IF(D16<>"",TEXT(D16,"YYYYMMDD")&CHAR(64+A16),"") | C16: =IF(OR(B16="",B16<>B15),1,C15+1) -> 1 | F16: =INDEX(Establishment!B$2:B$1005,MATCH($E16,Establishment!$A$2:$A$1005,0)) -> #N/A | G16: =INDEX(Establishment!C$2:C$1005,MATCH($E16,Establishment!$A$2:$A$1005,0)) -> #N/A | M16: =K16*L16 -> 0 | N16: =IF(B16=B15,N15+M16,M16) -> 0 | P16: =INDEX(Items!B$2:B$1032,MATCH($O16,Items!$A$2:$A$1032,0)) -> #N/A | Q16: =INDEX(Items!C$2:C$1032,MATCH($O16,Items!$A$2:$A$1032,0)) -> #N/A | R16: =INDEX(Items!D$2:D$1032,MATCH($O16,Items!$A$2:$A$1032,0)) -> #N/A
A17: =IF(OR(D17<>D16,D17=""),1,IF(NOT(AND(E17=E16,F17=F16,G17=G16)),A16+1,IF(OR(H17="",AND(H17<>"",H17<>H16,H16<>"")),A16,A16+1))) -> 1 | B17: =IF(D17<>"",TEXT(D17,"YYYYMMDD")&CHAR(64+A17),"") | C17: =IF(OR(B17="",B17<>B16),1,C16+1) -> 1 | F17: =INDEX(Establishment!B$2:B$1005,MATCH($E17,Establishment!$A$2:$A$1005,0)) -> #N/A | G17: =INDEX(Establishment!C$2:C$1005,MATCH($E17,Establishment!$A$2:$A$1005,0)) -> #N/A | M17: =K17*L17 -> 0 | N17: =IF(B17=B16,N16+M17,M17) -> 0 | P17: =INDEX(Items!B$2:B$1032,MATCH($O17,Items!$A$2:$A$1032,0)) -> #N/A | Q17: =INDEX(Items!C$2:C$1032,MATCH($O17,Items!$A$2:$A$1032,0)) -> #N/A | R17: =INDEX(Items!D$2:D$1032,MATCH($O17,Items!$A$2:$A$1032,0)) -> #N/A
A18: =IF(OR(D18<>D17,D18=""),1,IF(NOT(AND(E18=E17,F18=F17,G18=G17)),A17+1,IF(OR(H18="",AND(H18<>"",H18<>H17,H17<>"")),A17,A17+1))) -> 1 | B18: =IF(D18<>"",TEXT(D18,"YYYYMMDD")&CHAR(64+A18),"") | C18: =IF(OR(B18="",B18<>B17),1,C17+1) -> 1 | F18: =INDEX(Establishment!B$2:B$1005,MATCH($E18,Establishment!$A$2:$A$1005,0)) -> #N/A | G18: =INDEX(Establishment!C$2:C$1005,MATCH($E18,Establishment!$A$2:$A$1005,0)) -> #N/A | M18: =K18*L18 -> 0 | N18: =IF(B18=B17,N17+M18,M18) -> 0 | P18: =INDEX(Items!B$2:B$1032,MATCH($O18,Items!$A$2:$A$1032,0)) -> #N/A | Q18: =INDEX(Items!C$2:C$1032,MATCH($O18,Items!$A$2:$A$1032,0)) -> #N/A | R18: =INDEX(Items!D$2:D$1032,MATCH($O18,Items!$A$2:$A$1032,0)) -> #N/A
A19: =IF(OR(D19<>D18,D19=""),1,IF(NOT(AND(E19=E18,F19=F18,G19=G18)),A18+1,IF(OR(H19="",AND(H19<>"",H19<>H18,H18<>"")),A18,A18+1))) -> 1 | B19: =IF(D19<>"",TEXT(D19,"YYYYMMDD")&CHAR(64+A19),"") | C19: =IF(OR(B19="",B19<>B18),1,C18+1) -> 1 | F19: =INDEX(Establishment!B$2:B$1005,MATCH($E19,Establishment!$A$2:$A$1005,0)) -> #N/A | G19: =INDEX(Establishment!C$2:C$1005,MATCH($E19,Establishment!$A$2:$A$1005,0)) -> #N/A | M19: =K19*L19 -> 0 | N19: =IF(B19=B18,N18+M19,M19) -> 0 | P19: =INDEX(Items!B$2:B$1032,MATCH($O19,Items!$A$2:$A$1032,0)) -> #N/A | Q19: =INDEX(Items!C$2:C$1032,MATCH($O19,Items!$A$2:$A$1032,0)) -> #N/A | R19: =INDEX(Items!D$2:D$1032,MATCH($O19,Items!$A$2:$A$1032,0)) -> #N/A
... A25: =IF(OR(D25<>D24,D25=""),1,IF(NOT(AND(E25=E24,F25=F24,G25=G24)),A24+1,IF(OR(H25="",AND(H25<>"",H25<>H24,H24<>"")),A24,A24+1))) -> 1 | B25: =IF(D25<>"",TEXT(D25,"YYYYMMDD")&CHAR(64+A25),"") | C25: =IF(OR(B25="",B25<>B24),1,C24+1) -> 1 | F25: =INDEX(Establishment!B$2:B$1005,MATCH($E25,Establishment!$A$2:$A$1005,0)) -> #N/A | G25: =INDEX(Establishment!C$2:C$1005,MATCH($E25,Establishment!$A$2:$A$1005,0)) -> #N/A | M25: =K25*L25 -> 0 | N25: =IF(B25=B24,N24+M25,M25) -> 0 | P25: =INDEX(Items!B$2:B$1032,MATCH($O25,Items!$A$2:$A$1032,0)) -> #N/A | Q25: =INDEX(Items!C$2:C$1032,MATCH($O25,Items!$A$2:$A$1032,0)) -> #N/A | R25: =INDEX(Items!D$2:D$1032,MATCH($O25,Items!$A$2:$A$1032,0)) -> #N/A
A26: =IF(OR(D26<>D25,D26=""),1,IF(NOT(AND(E26=E25,F26=F25,G26=G25)),A25+1,IF(OR(H26="",AND(H26<>"",H26<>H25,H25<>"")),A25,A25+1))) -> 1 | B26: =IF(D26<>"",TEXT(D26,"YYYYMMDD")&CHAR(64+A26),"") | C26: =IF(OR(B26="",B26<>B25),1,C25+1) -> 1 | F26: Street Vendor | G26: Fried Chicken Seller | M26: =K26*L26 -> 0 | N26: =IF(B26=B25,N25+M26,M26) -> 0 | P26: =INDEX(Items!B$2:B$1032,MATCH($O26,Items!$A$2:$A$1032,0)) -> #N/A | Q26: =INDEX(Items!C$2:C$1032,MATCH($O26,Items!$A$2:$A$1032,0)) -> #N/A | R26: =INDEX(Items!D$2:D$1032,MATCH($O26,Items!$A$2:$A$1032,0)) -> #N/A
A27: =IF(OR(D27<>D26,D27=""),1,IF(NOT(AND(E27=E26,F27=F26,G27=G26)),A26+1,IF(OR(H27="",AND(H27<>"",H27<>H26,H26<>"")),A26,A26+1))) -> 1 | B27: =IF(D27<>"",TEXT(D27,"YYYYMMDD")&CHAR(64+A27),"") | C27: =IF(OR(B27="",B27<>B26),1,C26+1) -> 1 | F27: Street Vendor | G27: Fried Chicken Seller | M27: =K27*L27 -> 0 | N27: =IF(B27=B26,N26+M27,M27) -> 0 | P27: =INDEX(Items!B$2:B$1032,MATCH($O27,Items!$A$2:$A$1032,0)) -> #N/A | Q27: =INDEX(Items!C$2:C$1032,MATCH($O27,Items!$A$2:$A$1032,0)) -> #N/A | R27: =INDEX(Items!D$2:D$1032,MATCH($O27,Items!$A$2:$A$1032,0)) -> #N/A
A28: =IF(OR(D28<>D27,D28=""),1,IF(NOT(AND(E28=E27,F28=F27,G28=G27)),A27+1,IF(OR(H28="",AND(H28<>"",H28<>H27,H27<>"")),A27,A27+1))) -> 1 | B28: =IF(D28<>"",TEXT(D28,"YYYYMMDD")&CHAR(64+A28),"") | C28: =IF(OR(B28="",B28<>B27),1,C27+1) -> 1 | F28: Street Vendor | G28: Fried Chicken Seller | M28: =K28*L28 -> 0 | N28: =IF(B28=B27,N27+M28,M28) -> 0 | P28: =INDEX(Items!B$2:B$1032,MATCH($O28,Items!$A$2:$A$1032,0)) -> #N/A | Q28: =INDEX(Items!C$2:C$1032,MATCH($O28,Items!$A$2:$A$1032,0)) -> #N/A | R28: =INDEX(Items!D$2:D$1032,MATCH($O28,Items!$A$2:$A$1032,0)) -> #N/A
A29: =IF(OR(D29<>D28,D29=""),1,IF(NOT(AND(E29=E28,F29=F28,G29=G28)),A28+1,IF(OR(H29="",AND(H29<>"",H29<>H28,H28<>"")),A28,A28+1))) -> 1 | B29: =IF(D29<>"",TEXT(D29,"YYYYMMDD")&CHAR(64+A29),"") | C29: =IF(OR(B29="",B29<>B28),1,C28+1) -> 1 | F29: =INDEX(Establishment!B$2:B$1005,MATCH($E29,Establishment!$A$2:$A$1005,0)) -> #N/A | G29: =INDEX(Establishment!C$2:C$1005,MATCH($E29,Establishment!$A$2:$A$1005,0)) -> #N/A | M29: =K29*L29 -> 0 | N29: =IF(B29=B28,N28+M29,M29) -> 0 | P29: =INDEX(Items!B$2:B$1032,MATCH($O29,Items!$A$2:$A$1032,0)) -> #N/A | Q29: =INDEX(Items!C$2:C$1032,MATCH($O29,Items!$A$2:$A$1032,0)) -> #N/A | R29: =INDEX(Items!D$2:D$1032,MATCH($O29,Items!$A$2:$A$1032,0)) -> #N/A
A30: =IF(OR(D30<>D29,D30=""),1,IF(NOT(AND(E30=E29,F30=F29,G30=G29)),A29+1,IF(OR(H30="",AND(H30<>"",H30<>H29,H29<>"")),A29,A29+1))) -> 1 | B30: =IF(D30<>"",TEXT(D30,"YYYYMMDD")&CHAR(64+A30),"") | C30: =IF(OR(B30="",B30<>B29),1,C29+1) -> 1 | F30: =INDEX(Establishment!B$2:B$1005,MATCH($E30,Establishment!$A$2:$A$1005,0)) -> #N/A | G30: =INDEX(Establishment!C$2:C$1005,MATCH($E30,Establishment!$A$2:$A$1005,0)) -> #N/A | M30: =K30*L30 -> 0 | N30: =IF(B30=B29,N29+M30,M30) -> 0 | P30: =INDEX(Items!B$2:B$1032,MATCH($O30,Items!$A$2:$A$1032,0)) -> #N/A | Q30: =INDEX(Items!C$2:C$1032,MATCH($O30,Items!$A$2:$A$1032,0)) -> #N/A | R30: =INDEX(Items!D$2:D$1032,MATCH($O30,Items!$A$2:$A$1032,0)) -> #N/A
A31: =IF(OR(D31<>D30,D31=""),1,IF(NOT(AND(E31=E30,F31=F30,G31=G30)),A30+1,IF(OR(H31="",AND(H31<>"",H31<>H30,H30<>"")),A30,A30+1))) -> 1 | B31: =IF(D31<>"",TEXT(D31,"YYYYMMDD")&CHAR(64+A31),"") | C31: =IF(OR(B31="",B31<>B30),1,C30+1) -> 1 | F31: =INDEX(Establishment!B$2:B$1005,MATCH($E31,Establishment!$A$2:$A$1005,0)) -> #N/A | G31: =INDEX(Establishment!C$2:C$1005,MATCH($E31,Establishment!$A$2:$A$1005,0)) -> #N/A | M31: =K31*L31 -> 0 | N31: =IF(B31=B30,N30+M31,M31) -> 0 | P31: =INDEX(Items!B$2:B$1032,MATCH($O31,Items!$A$2:$A$1032,0)) -> #N/A | Q31: =INDEX(Items!C$2:C$1032,MATCH($O31,Items!$A$2:$A$1032,0)) -> #N/A | R31: =INDEX(Items!D$2:D$1032,MATCH($O31,Items!$A$2:$A$1032,0)) -> #N/A
A32: =IF(OR(D32<>D31,D32=""),1,IF(NOT(AND(E32=E31,F32=F31,G32=G31)),A31+1,IF(OR(H32="",AND(H32<>"",H32<>H31,H31<>"")),A31,A31+1))) -> 1 | B32: =IF(D32<>"",TEXT(D32,"YYYYMMDD")&CHAR(64+A32),"") | C32: =IF(OR(B32="",B32<>B31),1,C31+1) -> 1 | F32: Street Vendor | G32: B. Rodriguez | M32: =K32*L32 -> 0 | N32: =IF(B32=B31,N31+M32,M32) -> 0 | P32: =INDEX(Items!B$2:B$1032,MATCH($O32,Items!$A$2:$A$1032,0)) -> #N/A | Q32: =INDEX(Items!C$2:C$1032,MATCH($O32,Items!$A$2:$A$1032,0)) -> #N/A | R32: =INDEX(Items!D$2:D$1032,MATCH($O32,Items!$A$2:$A$1032,0)) -> #N/A
A33: =IF(OR(D33<>D32,D33=""),1,IF(NOT(AND(E33=E32,F33=F32,G33=G32)),A32+1,IF(OR(H33="",AND(H33<>"",H33<>H32,H32<>"")),A32,A32+1))) -> 1 | B33: =IF(D33<>"",TEXT(D33,"YYYYMMDD")&CHAR(64+A33),"") | C33: =IF(OR(B33="",B33<>B32),1,C32+1) -> 1 | F33: Street Vendor | G33: B. Rodriguez | M33: =K33*L33 -> 0 | N33: =IF(B33=B32,N32+M33,M33) -> 0 | P33: =INDEX(Items!B$2:B$1032,MATCH($O33,Items!$A$2:$A$1032,0)) -> #N/A | Q33: =INDEX(Items!C$2:C$1032,MATCH($O33,Items!$A$2:$A$1032,0)) -> #N/A | R33: =INDEX(Items!D$2:D$1032,MATCH($O33,Items!$A$2:$A$1032,0)) -> #N/A
A34: =IF(OR(D34<>D33,D34=""),1,IF(NOT(AND(E34=E33,F34=F33,G34=G33)),A33+1,IF(OR(H34="",AND(H34<>"",H34<>H33,H33<>"")),A33,A33+1))) -> 1 | B34: =IF(D34<>"",TEXT(D34,"YYYYMMDD")&CHAR(64+A34),"") | C34: =IF(OR(B34="",B34<>B33),1,C33+1) -> 1 | F34: Street Vendor | G34: B. Rodriguez | M34: =K34*L34 -> 0 | N34: =IF(B34=B33,N33+M34,M34) -> 0 | P34: =INDEX(Items!B$2:B$1032,MATCH($O34,Items!$A$2:$A$1032,0)) -> #N/A | Q34: =INDEX(Items!C$2:C$1032,MATCH($O34,Items!$A$2:$A$1032,0)) -> #N/A | R34: =INDEX(Items!D$2:D$1032,MATCH($O34,Items!$A$2:$A$1032,0)) -> #N/A
A35: =IF(OR(D35<>D34,D35=""),1,IF(NOT(AND(E35=E34,F35=F34,G35=G34)),A34+1,IF(OR(H35="",AND(H35<>"",H35<>H34,H34<>"")),A34,A34+1))) -> 1 | B35: =IF(D35<>"",TEXT(D35,"YYYYMMDD")&CHAR(64+A35),"") | C35: =IF(OR(B35="",B35<>B34),1,C34+1) -> 1 | F35: Street Vendor | G35: B. Rodriguez | M35: =K35*L35 -> 0 | N35: =IF(B35=B34,N34+M35,M35) -> 0 | P35: =INDEX(Items!B$2:B$1032,MATCH($O35,Items!$A$2:$A$1032,0)) -> #N/A | Q35: =INDEX(Items!C$2:C$1032,MATCH($O35,Items!$A$2:$A$1032,0)) -> #N/A | R35: =INDEX(Items!D$2:D$1032,MATCH($O35,Items!$A$2:$A$1032,0)) -> #N/A
A36: =IF(OR(D36<>D35,D36=""),1,IF(NOT(AND(E36=E35,F36=F35,G36=G35)),A35+1,IF(OR(H36="",AND(H36<>"",H36<>H35,H35<>"")),A35,A35+1))) -> 1 | B36: =IF(D36<>"",TEXT(D36,"YYYYMMDD")&CHAR(64+A36),"") | C36: =IF(OR(B36="",B36<>B35),1,C35+1) -> 1 | F36: Carenderia | G36: B. Rodriguez | M36: =K36*L36 -> 0 | N36: =IF(B36=B35,N35+M36,M36) -> 0 | P36: =INDEX(Items!B$2:B$1032,MATCH($O36,Items!$A$2:$A$1032,0)) -> #N/A | Q36: =INDEX(Items!C$2:C$1032,MATCH($O36,Items!$A$2:$A$1032,0)) -> #N/A | R36: =INDEX(Items!D$2:D$1032,MATCH($O36,Items!$A$2:$A$1032,0)) -> #N/A
A37: =IF(OR(D37<>D36,D37=""),1,IF(NOT(AND(E37=E36,F37=F36,G37=G36)),A36+1,IF(OR(H37="",AND(H37<>"",H37<>H36,H36<>"")),A36,A36+1))) -> 1 | B37: =IF(D37<>"",TEXT(D37,"YYYYMMDD")&CHAR(64+A37),"") | C37: =IF(OR(B37="",B37<>B36),1,C36+1) -> 1 | F37: Carenderia | G37: B. Rodriguez | M37: =K37*L37 -> 0 | N37: =IF(B37=B36,N36+M37,M37) -> 0 | P37: =INDEX(Items!B$2:B$1032,MATCH($O37,Items!$A$2:$A$1032,0)) -> #N/A | Q37: =INDEX(Items!C$2:C$1032,MATCH($O37,Items!$A$2:$A$1032,0)) -> #N/A | R37: =INDEX(Items!D$2:D$1032,MATCH($O37,Items!$A$2:$A$1032,0)) -> #N/A
A38: =IF(OR(D38<>D37,D38=""),1,IF(NOT(AND(E38=E37,F38=F37,G38=G37)),A37+1,IF(OR(H38="",AND(H38<>"",H38<>H37,H37<>"")),A37,A37+1))) -> 1 | B38: =IF(D38<>"",TEXT(D38,"YYYYMMDD")&CHAR(64+A38),"") | C38: =IF(OR(B38="",B38<>B37),1,C37+1) -> 1 | F38: Carenderia | G38: B. Rodriguez | M38: =K38*L38 -> 0 | N38: =IF(B38=B37,N37+M38,M38) -> 0 | P38: =INDEX(Items!B$2:B$1032,MATCH($O38,Items!$A$2:$A$1032,0)) -> #N/A | Q38: =INDEX(Items!C$2:C$1032,MATCH($O38,Items!$A$2:$A$1032,0)) -> #N/A | R38: =INDEX(Items!D$2:D$1032,MATCH($O38,Items!$A$2:$A$1032,0)) -> #N/A
A39: =IF(OR(D39<>D38,D39=""),1,IF(NOT(AND(E39=E38,F39=F38,G39=G38)),A38+1,IF(OR(H39="",AND(H39<>"",H39<>H38,H38<>"")),A38,A38+1))) -> 1 | B39: =IF(D39<>"",TEXT(D39,"YYYYMMDD")&CHAR(64+A39),"") | C39: =IF(OR(B39="",B39<>B38),1,C38+1) -> 1 | F39: Carenderia | G39: B. Rodriguez | M39: =K39*L39 -> 0 | N39: =IF(B39=B38,N38+M39,M39) -> 0 | P39: =INDEX(Items!B$2:B$1032,MATCH($O39,Items!$A$2:$A$1032,0)) -> #N/A | Q39: =INDEX(Items!C$2:C$1032,MATCH($O39,Items!$A$2:$A$1032,0)) -> #N/A | R39: =INDEX(Items!D$2:D$1032,MATCH($O39,Items!$A$2:$A$1032,0)) -> #N/A
A40: =IF(OR(D40<>D39,D40=""),1,IF(NOT(AND(E40=E39,F40=F39,G40=G39)),A39+1,IF(OR(H40="",AND(H40<>"",H40<>H39,H39<>"")),A39,A39+1))) -> 1 | B40: =IF(D40<>"",TEXT(D40,"YYYYMMDD")&CHAR(64+A40),"") | C40: =IF(OR(B40="",B40<>B39),1,C39+1) -> 1 | F40: Carenderia | G40: B. Rodriguez | M40: =K40*L40 -> 0 | N40: =IF(B40=B39,N39+M40,M40) -> 0 | P40: =INDEX(Items!B$2:B$1032,MATCH($O40,Items!$A$2:$A$1032,0)) -> #N/A | Q40: =INDEX(Items!C$2:C$1032,MATCH($O40,Items!$A$2:$A$1032,0)) -> #N/A | R40: =INDEX(Items!D$2:D$1032,MATCH($O40,Items!$A$2:$A$1032,0)) -> #N/A
A41: =IF(OR(D41<>D40,D41=""),1,IF(NOT(AND(E41=E40,F41=F40,G41=G40)),A40+1,IF(OR(H41="",AND(H41<>"",H41<>H40,H40<>"")),A40,A40+1))) -> 1 | B41: =IF(D41<>"",TEXT(D41,"YYYYMMDD")&CHAR(64+A41),"") | C41: =IF(OR(B41="",B41<>B40),1,C40+1) -> 1 | F41: Carenderia | G41: B. Rodriguez | M41: =K41*L41 -> 0 | N41: =IF(B41=B40,N40+M41,M41) -> 0 | P41: =INDEX(Items!B$2:B$1032,MATCH($O41,Items!$A$2:$A$1032,0)) -> #N/A | Q41: =INDEX(Items!C$2:C$1032,MATCH($O41,Items!$A$2:$A$1032,0)) -> #N/A | R41: =INDEX(Items!D$2:D$1032,MATCH($O41,Items!$A$2:$A$1032,0)) -> #N/A
A42: =IF(OR(D42<>D41,D42=""),1,IF(NOT(AND(E42=E41,F42=F41,G42=G41)),A41+1,IF(OR(H42="",AND(H42<>"",H42<>H41,H41<>"")),A41,A41+1))) -> 1 | B42: =IF(D42<>"",TEXT(D42,"YYYYMMDD")&CHAR(64+A42),"") | C42: =IF(OR(B42="",B42<>B41),1,C41+1) -> 1 | F42: Carenderia | G42: B. Rodriguez | M42: =K42*L42 -> 0 | N42: =IF(B42=B41,N41+M42,M42) -> 0 | P42: =INDEX(Items!B$2:B$1032,MATCH($O42,Items!$A$2:$A$1032,0)) -> #N/A | Q42: =INDEX(Items!C$2:C$1032,MATCH($O42,Items!$A$2:$A$1032,0)) -> #N/A | R42: =INDEX(Items!D$2:D$1032,MATCH($O42,Items!$A$2:$A$1032,0)) -> #N/A
A43: =IF(OR(D43<>D42,D43=""),1,IF(NOT(AND(E43=E42,F43=F42,G43=G42)),A42+1,IF(OR(H43="",AND(H43<>"",H43<>H42,H42<>"")),A42,A42+1))) -> 1 | B43: =IF(D43<>"",TEXT(D43,"YYYYMMDD")&CHAR(64+A43),"") | C43: =IF(OR(B43="",B43<>B42),1,C42+1) -> 1 | F43: Carenderia | G43: B. Rodriguez | M43: =K43*L43 -> 0 | N43: =IF(B43=B42,N42+M43,M43) -> 0 | P43: =INDEX(Items!B$2:B$1032,MATCH($O43,Items!$A$2:$A$1032,0)) -> #N/A | Q43: =INDEX(Items!C$2:C$1032,MATCH($O43,Items!$A$2:$A$1032,0)) -> #N/A | R43: =INDEX(Items!D$2:D$1032,MATCH($O43,Items!$A$2:$A$1032,0)) -> #N/A
... A45: =IF(OR(D45<>D44,D45=""),1,IF(NOT(AND(E45=E44,F45=F44,G45=G44)),A44+1,IF(OR(H45="",AND(H45<>"",H45<>H44,H44<>"")),A44,A44+1))) -> 1 | B45: =IF(D45<>"",TEXT(D45,"YYYYMMDD")&CHAR(64+A45),"") | C45: =IF(OR(B45="",B45<>B44),1,C44+1) -> 1 | F45: Street Vendor | G45: Don Gil Garcia st. | M45: =K45*L45 -> 0 | N45: =IF(B45=B44,N44+M45,M45) -> 0 | P45: =INDEX(Items!B$2:B$1032,MATCH($O45,Items!$A$2:$A$1032,0)) -> #N/A | Q45: =INDEX(Items!C$2:C$1032,MATCH($O45,Items!$A$2:$A$1032,0)) -> #N/A | R45: =INDEX(Items!D$2:D$1032,MATCH($O45,Items!$A$2:$A$1032,0)) -> #N/A
A46: =IF(OR(D46<>D45,D46=""),1,IF(NOT(AND(E46=E45,F46=F45,G46=G45)),A45+1,IF(OR(H46="",AND(H46<>"",H46<>H45,H45<>"")),A45,A45+1))) -> 1 | B46: =IF(D46<>"",TEXT(D46,"YYYYMMDD")&CHAR(64+A46),"") | C46: =IF(OR(B46="",B46<>B45),1,C45+1) -> 1 | F46: =INDEX(Establishment!B$2:B$1005,MATCH($E46,Establishment!$A$2:$A$1005,0)) -> #N/A | G46: =INDEX(Establishment!C$2:C$1005,MATCH($E46,Establishment!$A$2:$A$1005,0)) -> #N/A | M46: =K46*L46 -> 0 | N46: =IF(B46=B45,N45+M46,M46) -> 0 | P46: =INDEX(Items!B$2:B$1032,MATCH($O46,Items!$A$2:$A$1032,0)) -> #N/A | Q46: =INDEX(Items!C$2:C$1032,MATCH($O46,Items!$A$2:$A$1032,0)) -> #N/A | R46: =INDEX(Items!D$2:D$1032,MATCH($O46,Items!$A$2:$A$1032,0)) -> #N/A
A47: =IF(OR(D47<>D46,D47=""),1,IF(NOT(AND(E47=E46,F47=F46,G47=G46)),A46+1,IF(OR(H47="",AND(H47<>"",H47<>H46,H46<>"")),A46,A46+1))) -> 1 | B47: =IF(D47<>"",TEXT(D47,"YYYYMMDD")&CHAR(64+A47),"") | C47: =IF(OR(B47="",B47<>B46),1,C46+1) -> 1 | F47: =INDEX(Establishment!B$2:B$1005,MATCH($E47,Establishment!$A$2:$A$1005,0)) -> #N/A | G47: =INDEX(Establishment!C$2:C$1005,MATCH($E47,Establishment!$A$2:$A$1005,0)) -> #N/A | M47: =K47*L47 -> 0 | N47: =IF(B47=B46,N46+M47,M47) -> 0 | P47: =INDEX(Items!B$2:B$1032,MATCH($O47,Items!$A$2:$A$1032,0)) -> #N/A | Q47: =INDEX(Items!C$2:C$1032,MATCH($O47,Items!$A$2:$A$1032,0)) -> #N/A | R47: =INDEX(Items!D$2:D$1032,MATCH($O47,Items!$A$2:$A$1032,0)) -> #N/A
A48: =IF(OR(D48<>D47,D48=""),1,IF(NOT(AND(E48=E47,F48=F47,G48=G47)),A47+1,IF(OR(H48="",AND(H48<>"",H48<>H47,H47<>"")),A47,A47+1))) -> 1 | B48: =IF(D48<>"",TEXT(D48,"YYYYMMDD")&CHAR(64+A48),"") | C48: =IF(OR(B48="",B48<>B47),1,C47+1) -> 1 | F48: =INDEX(Establishment!B$2:B$1005,MATCH($E48,Establishment!$A$2:$A$1005,0)) -> #N/A | G48: =INDEX(Establishment!C$2:C$1005,MATCH($E48,Establishment!$A$2:$A$1005,0)) -> #N/A | M48: =K48*L48 -> 0 | N48: =IF(B48=B47,N47+M48,M48) -> 0 | P48: =INDEX(Items!B$2:B$1032,MATCH($O48,Items!$A$2:$A$1032,0)) -> #N/A | Q48: =INDEX(Items!C$2:C$1032,MATCH($O48,Items!$A$2:$A$1032,0)) -> #N/A | R48: =INDEX(Items!D$2:D$1032,MATCH($O48,Items!$A$2:$A$1032,0)) -> #N/A
A49: =IF(OR(D49<>D48,D49=""),1,IF(NOT(AND(E49=E48,F49=F48,G49=G48)),A48+1,IF(OR(H49="",AND(H49<>"",H49<>H48,H48<>"")),A48,A48+1))) -> 1 | B49: =IF(D49<>"",TEXT(D49,"YYYYMMDD")&CHAR(64+A49),"") | C49: =IF(OR(B49="",B49<>B48),1,C48+1) -> 1 | F49: =INDEX(Establishment!B$2:B$1005,MATCH($E49,Establishment!$A$2:$A$1005,0)) -> #N/A | G49: =INDEX(Establishment!C$2:C$1005,MATCH($E49,Establishment!$A$2:$A$1005,0)) -> #N/A | M49: =K49*L49 -> 0 | N49: =IF(B49=B48,N48+M49,M49) -> 0 | P49: =INDEX(Items!B$2:B$1032,MATCH($O49,Items!$A$2:$A$1032,0)) -> #N/A | Q49: =INDEX(Items!C$2:C$1032,MATCH($O49,Items!$A$2:$A$1032,0)) -> #N/A | R49: =INDEX(Items!D$2:D$1032,MATCH($O49,Items!$A$2:$A$1032,0)) -> #N/A
A50: =IF(OR(D50<>D49,D50=""),1,IF(NOT(AND(E50=E49,F50=F49,G50=G49)),A49+1,IF(OR(H50="",AND(H50<>"",H50<>H49,H49<>"")),A49,A49+1))) -> 1 | B50: =IF(D50<>"",TEXT(D50,"YYYYMMDD")&CHAR(64+A50),"") | C50: =IF(OR(B50="",B50<>B49),1,C49+1) -> 1 | F50: =INDEX(Establishment!B$2:B$1005,MATCH($E50,Establishment!$A$2:$A$1005,0)) -> #N/A | G50: =INDEX(Establishment!C$2:C$1005,MATCH($E50,Establishment!$A$2:$A$1005,0)) -> #N/A | M50: =K50*L50 -> 0 | N50: =IF(B50=B49,N49+M50,M50) -> 0 | P50: =INDEX(Items!B$2:B$1032,MATCH($O50,Items!$A$2:$A$1032,0)) -> #N/A | Q50: =INDEX(Items!C$2:C$1032,MATCH($O50,Items!$A$2:$A$1032,0)) -> #N/A | R50: =INDEX(Items!D$2:D$1032,MATCH($O50,Items!$A$2:$A$1032,0)) -> #N/A
A51: =IF(OR(D51<>D50,D51=""),1,IF(NOT(AND(E51=E50,F51=F50,G51=G50)),A50+1,IF(OR(H51="",AND(H51<>"",H51<>H50,H50<>"")),A50,A50+1))) -> 1 | B51: =IF(D51<>"",TEXT(D51,"YYYYMMDD")&CHAR(64+A51),"") | C51: =IF(OR(B51="",B51<>B50),1,C50+1) -> 1 | F51: =INDEX(Establishment!B$2:B$1005,MATCH($E51,Establishment!$A$2:$A$1005,0)) -> #N/A | G51: =INDEX(Establishment!C$2:C$1005,MATCH($E51,Establishment!$A$2:$A$1005,0)) -> #N/A | M51: =K51*L51 -> 0 | N51: =IF(B51=B50,N50+M51,M51) -> 0 | P51: =INDEX(Items!B$2:B$1032,MATCH($O51,Items!$A$2:$A$1032,0)) -> #N/A | Q51: =INDEX(Items!C$2:C$1032,MATCH($O51,Items!$A$2:$A$1032,0)) -> #N/A | R51: =INDEX(Items!D$2:D$1032,MATCH($O51,Items!$A$2:$A$1032,0)) -> #N/A
A52: =IF(OR(D52<>D51,D52=""),1,IF(NOT(AND(E52=E51,F52=F51,G52=G51)),A51+1,IF(OR(H52="",AND(H52<>"",H52<>H51,H51<>"")),A51,A51+1))) -> 1 | B52: =IF(D52<>"",TEXT(D52,"YYYYMMDD")&CHAR(64+A52),"") | C52: =IF(OR(B52="",B52<>B51),1,C51+1) -> 1 | F52: =INDEX(Establishment!B$2:B$1005,MATCH($E52,Establishment!$A$2:$A$1005,0)) -> #N/A | G52: =INDEX(Establishment!C$2:C$1005,MATCH($E52,Establishment!$A$2:$A$1005,0)) -> #N/A | M52: =K52*L52 -> 0 | N52: =IF(B52=B51,N51+M52,M52) -> 0 | P52: =INDEX(Items!B$2:B$1032,MATCH($O52,Items!$A$2:$A$1032,0)) -> #N/A | Q52: =INDEX(Items!C$2:C$1032,MATCH($O52,Items!$A$2:$A$1032,0)) -> #N/A | R52: =INDEX(Items!D$2:D$1032,MATCH($O52,Items!$A$2:$A$1032,0)) -> #N/A
A53: =IF(OR(D53<>D52,D53=""),1,IF(NOT(AND(E53=E52,F53=F52,G53=G52)),A52+1,IF(OR(H53="",AND(H53<>"",H53<>H52,H52<>"")),A52,A52+1))) -> 1 | B53: =IF(D53<>"",TEXT(D53,"YYYYMMDD")&CHAR(64+A53),"") | C53: =IF(OR(B53="",B53<>B52),1,C52+1) -> 1 | F53: =INDEX(Establishment!B$2:B$1005,MATCH($E53,Establishment!$A$2:$A$1005,0)) -> #N/A | G53: =INDEX(Establishment!C$2:C$1005,MATCH($E53,Establishment!$A$2:$A$1005,0)) -> #N/A | M53: =K53*L53 -> 0 | N53: =IF(B53=B52,N52+M53,M53) -> 0 | P53: =INDEX(Items!B$2:B$1032,MATCH($O53,Items!$A$2:$A$1032,0)) -> #N/A | Q53: =INDEX(Items!C$2:C$1032,MATCH($O53,Items!$A$2:$A$1032,0)) -> #N/A | R53: =INDEX(Items!D$2:D$1032,MATCH($O53,Items!$A$2:$A$1032,0)) -> #N/A
A54: =IF(OR(D54<>D53,D54=""),1,IF(NOT(AND(E54=E53,F54=F53,G54=G53)),A53+1,IF(OR(H54="",AND(H54<>"",H54<>H53,H53<>"")),A53,A53+1))) -> 1 | B54: =IF(D54<>"",TEXT(D54,"YYYYMMDD")&CHAR(64+A54),"") | C54: =IF(OR(B54="",B54<>B53),1,C53+1) -> 1 | F54: =INDEX(Establishment!B$2:B$1005,MATCH($E54,Establishment!$A$2:$A$1005,0)) -> #N/A | G54: =INDEX(Establishment!C$2:C$1005,MATCH($E54,Establishment!$A$2:$A$1005,0)) -> #N/A | M54: =K54*L54 -> 0 | N54: =IF(B54=B53,N53+M54,M54) -> 0 | P54: =INDEX(Items!B$2:B$1032,MATCH($O54,Items!$A$2:$A$1032,0)) -> #N/A | Q54: =INDEX(Items!C$2:C$1032,MATCH($O54,Items!$A$2:$A$1032,0)) -> #N/A | R54: =INDEX(Items!D$2:D$1032,MATCH($O54,Items!$A$2:$A$1032,0)) -> #N/A
A55: =IF(OR(D55<>D54,D55=""),1,IF(NOT(AND(E55=E54,F55=F54,G55=G54)),A54+1,IF(OR(H55="",AND(H55<>"",H55<>H54,H54<>"")),A54,A54+1))) -> 1 | B55: =IF(D55<>"",TEXT(D55,"YYYYMMDD")&CHAR(64+A55),"") | C55: =IF(OR(B55="",B55<>B54),1,C54+1) -> 1 | F55: =INDEX(Establishment!B$2:B$1005,MATCH($E55,Establishment!$A$2:$A$1005,0)) -> #N/A | G55: =INDEX(Establishment!C$2:C$1005,MATCH($E55,Establishment!$A$2:$A$1005,0)) -> #N/A | M55: =K55*L55 -> 0 | N55: =IF(B55=B54,N54+M55,M55) -> 0 | P55: =INDEX(Items!B$2:B$1032,MATCH($O55,Items!$A$2:$A$1032,0)) -> #N/A | Q55: =INDEX(Items!C$2:C$1032,MATCH($O55,Items!$A$2:$A$1032,0)) -> #N/A | R55: =INDEX(Items!D$2:D$1032,MATCH($O55,Items!$A$2:$A$1032,0)) -> #N/A
A56: =IF(OR(D56<>D55,D56=""),1,IF(NOT(AND(E56=E55,F56=F55,G56=G55)),A55+1,IF(OR(H56="",AND(H56<>"",H56<>H55,H55<>"")),A55,A55+1))) -> 1 | B56: =IF(D56<>"",TEXT(D56,"YYYYMMDD")&CHAR(64+A56),"") | C56: =IF(OR(B56="",B56<>B55),1,C55+1) -> 1 | F56: =INDEX(Establishment!B$2:B$1005,MATCH($E56,Establishment!$A$2:$A$1005,0)) -> #N/A | G56: =INDEX(Establishment!C$2:C$1005,MATCH($E56,Establishment!$A$2:$A$1005,0)) -> #N/A | M56: =K56*L56 -> 0 | N56: =IF(B56=B55,N55+M56,M56) -> 0 | P56: =INDEX(Items!B$2:B$1032,MATCH($O56,Items!$A$2:$A$1032,0)) -> #N/A | Q56: =INDEX(Items!C$2:C$1032,MATCH($O56,Items!$A$2:$A$1032,0)) -> #N/A | R56: =INDEX(Items!D$2:D$1032,MATCH($O56,Items!$A$2:$A$1032,0)) -> #N/A
A57: =IF(OR(D57<>D56,D57=""),1,IF(NOT(AND(E57=E56,F57=F56,G57=G56)),A56+1,IF(OR(H57="",AND(H57<>"",H57<>H56,H56<>"")),A56,A56+1))) -> 1 | B57: =IF(D57<>"",TEXT(D57,"YYYYMMDD")&CHAR(64+A57),"") | C57: =IF(OR(B57="",B57<>B56),1,C56+1) -> 1 | F57: =INDEX(Establishment!B$2:B$1005,MATCH($E57,Establishment!$A$2:$A$1005,0)) -> #N/A | G57: =INDEX(Establishment!C$2:C$1005,MATCH($E57,Establishment!$A$2:$A$1005,0)) -> #N/A | M57: =K57*L57 -> 0 | N57: =IF(B57=B56,N56+M57,M57) -> 0 | P57: =INDEX(Items!B$2:B$1032,MATCH($O57,Items!$A$2:$A$1032,0)) -> #N/A | Q57: =INDEX(Items!C$2:C$1032,MATCH($O57,Items!$A$2:$A$1032,0)) -> #N/A | R57: =INDEX(Items!D$2:D$1032,MATCH($O57,Items!$A$2:$A$1032,0)) -> #N/A
... A66: =IF(OR(D66<>D65,D66=""),1,IF(NOT(AND(E66=E65,F66=F65,G66=G65)),A65+1,IF(OR(H66="",AND(H66<>"",H66<>H65,H65<>"")),A65,A65+1))) -> 1 | B66: =IF(D66<>"",TEXT(D66,"YYYYMMDD")&CHAR(64+A66),"") | C66: =IF(OR(B66="",B66<>B65),1,C65+1) -> 1 | F66: =INDEX(Establishment!B$2:B$1005,MATCH($E66,Establishment!$A$2:$A$1005,0)) -> #N/A | G66: =INDEX(Establishment!C$2:C$1005,MATCH($E66,Establishment!$A$2:$A$1005,0)) -> #N/A | M66: =K66*L66 -> 0 | N66: =IF(B66=B65,N65+M66,M66) -> 0 | P66: =INDEX(Items!B$2:B$1032,MATCH($O66,Items!$A$2:$A$1032,0)) -> #N/A | Q66: =INDEX(Items!C$2:C$1032,MATCH($O66,Items!$A$2:$A$1032,0)) -> #N/A | R66: =INDEX(Items!D$2:D$1032,MATCH($O66,Items!$A$2:$A$1032,0)) -> #N/A
A67: =IF(OR(D67<>D66,D67=""),1,IF(NOT(AND(E67=E66,F67=F66,G67=G66)),A66+1,IF(OR(H67="",AND(H67<>"",H67<>H66,H66<>"")),A66,A66+1))) -> 1 | B67: =IF(D67<>"",TEXT(D67,"YYYYMMDD")&CHAR(64+A67),"") | C67: =IF(OR(B67="",B67<>B66),1,C66+1) -> 1 | F67: Street Vendor | G67: B. Rodriguez | M67: =K67*L67 -> 0 | N67: =IF(B67=B66,N66+M67,M67) -> 0 | P67: =INDEX(Items!B$2:B$1032,MATCH($O67,Items!$A$2:$A$1032,0)) -> #N/A | Q67: =INDEX(Items!C$2:C$1032,MATCH($O67,Items!$A$2:$A$1032,0)) -> #N/A | R67: =INDEX(Items!D$2:D$1032,MATCH($O67,Items!$A$2:$A$1032,0)) -> #N/A
A68: =IF(OR(D68<>D67,D68=""),1,IF(NOT(AND(E68=E67,F68=F67,G68=G67)),A67+1,IF(OR(H68="",AND(H68<>"",H68<>H67,H67<>"")),A67,A67+1))) -> 1 | B68: =IF(D68<>"",TEXT(D68,"YYYYMMDD")&CHAR(64+A68),"") | C68: =IF(OR(B68="",B68<>B67),1,C67+1) -> 1 | F68: Street Vendor | G68: B. Rodriguez | M68: =K68*L68 -> 0 | N68: =IF(B68=B67,N67+M68,M68) -> 0 | P68: =INDEX(Items!B$2:B$1032,MATCH($O68,Items!$A$2:$A$1032,0)) -> #N/A | Q68: =INDEX(Items!C$2:C$1032,MATCH($O68,Items!$A$2:$A$1032,0)) -> #N/A | R68: =INDEX(Items!D$2:D$1032,MATCH($O68,Items!$A$2:$A$1032,0)) -> #N/A
A69: =IF(OR(D69<>D68,D69=""),1,IF(NOT(AND(E69=E68,F69=F68,G69=G68)),A68+1,IF(OR(H69="",AND(H69<>"",H69<>H68,H68<>"")),A68,A68+1))) -> 1 | B69: =IF(D69<>"",TEXT(D69,"YYYYMMDD")&CHAR(64+A69),"") | C69: =IF(OR(B69="",B69<>B68),1,C68+1) -> 1 | F69: Street Vendor | G69: B. Rodriguez | M69: =K69*L69 -> 0 | N69: =IF(B69=B68,N68+M69,M69) -> 0 | P69: =INDEX(Items!B$2:B$1032,MATCH($O69,Items!$A$2:$A$1032,0)) -> #N/A | Q69: =INDEX(Items!C$2:C$1032,MATCH($O69,Items!$A$2:$A$1032,0)) -> #N/A | R69: =INDEX(Items!D$2:D$1032,MATCH($O69,Items!$A$2:$A$1032,0)) -> #N/A
A70: =IF(OR(D70<>D69,D70=""),1,IF(NOT(AND(E70=E69,F70=F69,G70=G69)),A69+1,IF(OR(H70="",AND(H70<>"",H70<>H69,H69<>"")),A69,A69+1))) -> 1 | B70: =IF(D70<>"",TEXT(D70,"YYYYMMDD")&CHAR(64+A70),"") | C70: =IF(OR(B70="",B70<>B69),1,C69+1) -> 1 | F70: Street Vendor | G70: B. Rodriguez | M70: =K70*L70 -> 0 | N70: =IF(B70=B69,N69+M70,M70) -> 0 | P70: =INDEX(Items!B$2:B$1032,MATCH($O70,Items!$A$2:$A$1032,0)) -> #N/A | Q70: =INDEX(Items!C$2:C$1032,MATCH($O70,Items!$A$2:$A$1032,0)) -> #N/A | R70: =INDEX(Items!D$2:D$1032,MATCH($O70,Items!$A$2:$A$1032,0)) -> #N/A
A71: =IF(OR(D71<>D70,D71=""),1,IF(NOT(AND(E71=E70,F71=F70,G71=G70)),A70+1,IF(OR(H71="",AND(H71<>"",H71<>H70,H70<>"")),A70,A70+1))) -> 1 | B71: =IF(D71<>"",TEXT(D71,"YYYYMMDD")&CHAR(64+A71),"") | C71: =IF(OR(B71="",B71<>B70),1,C70+1) -> 1 | F71: Street Vendor | G71: B. Rodriguez | M71: =K71*L71 -> 0 | N71: =IF(B71=B70,N70+M71,M71) -> 0 | P71: =INDEX(Items!B$2:B$1032,MATCH($O71,Items!$A$2:$A$1032,0)) -> #N/A | Q71: =INDEX(Items!C$2:C$1032,MATCH($O71,Items!$A$2:$A$1032,0)) -> #N/A | R71: =INDEX(Items!D$2:D$1032,MATCH($O71,Items!$A$2:$A$1032,0)) -> #N/A
A72: =IF(OR(D72<>D71,D72=""),1,IF(NOT(AND(E72=E71,F72=F71,G72=G71)),A71+1,IF(OR(H72="",AND(H72<>"",H72<>H71,H71<>"")),A71,A71+1))) -> 1 | B72: =IF(D72<>"",TEXT(D72,"YYYYMMDD")&CHAR(64+A72),"") | C72: =IF(OR(B72="",B72<>B71),1,C71+1) -> 1 | F72: Massage | G72: Don Gil Garcia st. | M72: =K72*L72 -> 0 | N72: =IF(B72=B71,N71+M72,M72) -> 0 | P72: =INDEX(Items!B$2:B$1032,MATCH($O72,Items!$A$2:$A$1032,0)) -> #N/A | Q72: =INDEX(Items!C$2:C$1032,MATCH($O72,Items!$A$2:$A$1032,0)) -> #N/A | R72: =INDEX(Items!D$2:D$1032,MATCH($O72,Items!$A$2:$A$1032,0)) -> #N/A
A73: =IF(OR(D73<>D72,D73=""),1,IF(NOT(AND(E73=E72,F73=F72,G73=G72)),A72+1,IF(OR(H73="",AND(H73<>"",H73<>H72,H72<>"")),A72,A72+1))) -> 1 | B73: =IF(D73<>"",TEXT(D73,"YYYYMMDD")&CHAR(64+A73),"") | C73: =IF(OR(B73="",B73<>B72),1,C72+1) -> 1 | F73: Massage | G73: Don Gil Garcia st. | M73: =K73*L73 -> 0 | N73: =IF(B73=B72,N72+M73,M73) -> 0 | P73: =INDEX(Items!B$2:B$1032,MATCH($O73,Items!$A$2:$A$1032,0)) -> #N/A | Q73: =INDEX(Items!C$2:C$1032,MATCH($O73,Items!$A$2:$A$1032,0)) -> #N/A | R73: =INDEX(Items!D$2:D$1032,MATCH($O73,Items!$A$2:$A$1032,0)) -> #N/A
A74: =IF(OR(D74<>D73,D74=""),1,IF(NOT(AND(E74=E73,F74=F73,G74=G73)),A73+1,IF(OR(H74="",AND(H74<>"",H74<>H73,H73<>"")),A73,A73+1))) -> 1 | B74: =IF(D74<>"",TEXT(D74,"YYYYMMDD")&CHAR(64+A74),"") | C74: =IF(OR(B74="",B74<>B73),1,C73+1) -> 1 | F74: Street Vendor | G74: Don Gil Garcia st. | M74: =K74*L74 -> 0 | N74: =IF(B74=B73,N73+M74,M74) -> 0 | P74: =INDEX(Items!B$2:B$1032,MATCH($O74,Items!$A$2:$A$1032,0)) -> #N/A | Q74: =INDEX(Items!C$2:C$1032,MATCH($O74,Items!$A$2:$A$1032,0)) -> #N/A | R74: =INDEX(Items!D$2:D$1032,MATCH($O74,Items!$A$2:$A$1032,0)) -> #N/A
A75: =IF(OR(D75<>D74,D75=""),1,IF(NOT(AND(E75=E74,F75=F74,G75=G74)),A74+1,IF(OR(H75="",AND(H75<>"",H75<>H74,H74<>"")),A74,A74+1))) -> 1 | B75: =IF(D75<>"",TEXT(D75,"YYYYMMDD")&CHAR(64+A75),"") | C75: =IF(OR(B75="",B75<>B74),1,C74+1) -> 1 | F75: Street Vendor | G75: Don Gil Garcia st. | M75: =K75*L75 -> 0 | N75: =IF(B75=B74,N74+M75,M75) -> 0 | P75: =INDEX(Items!B$2:B$1032,MATCH($O75,Items!$A$2:$A$1032,0)) -> #N/A | Q75: =INDEX(Items!C$2:C$1032,MATCH($O75,Items!$A$2:$A$1032,0)) -> #N/A | R75: =INDEX(Items!D$2:D$1032,MATCH($O75,Items!$A$2:$A$1032,0)) -> #N/A
A76: =IF(OR(D76<>D75,D76=""),1,IF(NOT(AND(E76=E75,F76=F75,G76=G75)),A75+1,IF(OR(H76="",AND(H76<>"",H76<>H75,H75<>"")),A75,A75+1))) -> 1 | B76: =IF(D76<>"",TEXT(D76,"YYYYMMDD")&CHAR(64+A76),"") | C76: =IF(OR(B76="",B76<>B75),1,C75+1) -> 1 | F76: Street Vendor | G76: Don Gil Garcia st. | M76: =K76*L76 -> 0 | N76: =IF(B76=B75,N75+M76,M76) -> 0 | P76: =INDEX(Items!B$2:B$1032,MATCH($O76,Items!$A$2:$A$1032,0)) -> #N/A | Q76: =INDEX(Items!C$2:C$1032,MATCH($O76,Items!$A$2:$A$1032,0)) -> #N/A | R76: =INDEX(Items!D$2:D$1032,MATCH($O76,Items!$A$2:$A$1032,0)) -> #N/A
A77: =IF(OR(D77<>D76,D77=""),1,IF(NOT(AND(E77=E76,F77=F76,G77=G76)),A76+1,IF(OR(H77="",AND(H77<>"",H77<>H76,H76<>"")),A76,A76+1))) -> 1 | B77: =IF(D77<>"",TEXT(D77,"YYYYMMDD")&CHAR(64+A77),"") | C77: =IF(OR(B77="",B77<>B76),1,C76+1) -> 1 | F77: Street Vendor | G77: Don Gil Garcia st. | M77: =K77*L77 -> 0 | N77: =IF(B77=B76,N76+M77,M77) -> 0 | P77: =INDEX(Items!B$2:B$1032,MATCH($O77,Items!$A$2:$A$1032,0)) -> #N/A | Q77: =INDEX(Items!C$2:C$1032,MATCH($O77,Items!$A$2:$A$1032,0)) -> #N/A | R77: =INDEX(Items!D$2:D$1032,MATCH($O77,Items!$A$2:$A$1032,0)) -> #N/A
A78: =IF(OR(D78<>D77,D78=""),1,IF(NOT(AND(E78=E77,F78=F77,G78=G77)),A77+1,IF(OR(H78="",AND(H78<>"",H78<>H77,H77<>"")),A77,A77+1))) -> 1 | B78: =IF(D78<>"",TEXT(D78,"YYYYMMDD")&CHAR(64+A78),"") | C78: =IF(OR(B78="",B78<>B77),1,C77+1) -> 1 | F78: Street Vendor | G78: Don Gil Garcia st. | M78: =K78*L78 -> 0 | N78: =IF(B78=B77,N77+M78,M78) -> 0 | P78: =INDEX(Items!B$2:B$1032,MATCH($O78,Items!$A$2:$A$1032,0)) -> #N/A | Q78: =INDEX(Items!C$2:C$1032,MATCH($O78,Items!$A$2:$A$1032,0)) -> #N/A | R78: =INDEX(Items!D$2:D$1032,MATCH($O78,Items!$A$2:$A$1032,0)) -> #N/A
... A82: =IF(OR(D82<>D81,D82=""),1,IF(NOT(AND(E82=E81,F82=F81,G82=G81)),A81+1,IF(OR(H82="",AND(H82<>"",H82<>H81,H81<>"")),A81,A81+1))) -> 1 | B82: =IF(D82<>"",TEXT(D82,"YYYYMMDD")&CHAR(64+A82),"") | C82: =IF(OR(B82="",B82<>B81),1,C81+1) -> 1 | F82: Street Vendor | G82: B. Rodriguez | M82: =K82*L82 -> 0 | N82: =IF(B82=B81,N81+M82,M82) -> 0 | P82: =INDEX(Items!B$2:B$1032,MATCH($O82,Items!$A$2:$A$1032,0)) -> #N/A | Q82: =INDEX(Items!C$2:C$1032,MATCH($O82,Items!$A$2:$A$1032,0)) -> #N/A | R82: =INDEX(Items!D$2:D$1032,MATCH($O82,Items!$A$2:$A$1032,0)) -> #N/A
A83: =IF(OR(D83<>D82,D83=""),1,IF(NOT(AND(E83=E82,F83=F82,G83=G82)),A82+1,IF(OR(H83="",AND(H83<>"",H83<>H82,H82<>"")),A82,A82+1))) -> 1 | B83: =IF(D83<>"",TEXT(D83,"YYYYMMDD")&CHAR(64+A83),"") | C83: =IF(OR(B83="",B83<>B82),1,C82+1) -> 1 | F83: =INDEX(Establishment!B$2:B$1005,MATCH($E83,Establishment!$A$2:$A$1005,0)) -> #N/A | G83: =INDEX(Establishment!C$2:C$1005,MATCH($E83,Establishment!$A$2:$A$1005,0)) -> #N/A | M83: =K83*L83 -> 0 | N83: =IF(B83=B82,N82+M83,M83) -> 0 | P83: =INDEX(Items!B$2:B$1032,MATCH($O83,Items!$A$2:$A$1032,0)) -> #N/A | Q83: =INDEX(Items!C$2:C$1032,MATCH($O83,Items!$A$2:$A$1032,0)) -> #N/A | R83: =INDEX(Items!D$2:D$1032,MATCH($O83,Items!$A$2:$A$1032,0)) -> #N/A
A84: =IF(OR(D84<>D83,D84=""),1,IF(NOT(AND(E84=E83,F84=F83,G84=G83)),A83+1,IF(OR(H84="",AND(H84<>"",H84<>H83,H83<>"")),A83,A83+1))) -> 1 | B84: =IF(D84<>"",TEXT(D84,"YYYYMMDD")&CHAR(64+A84),"") | C84: =IF(OR(B84="",B84<>B83),1,C83+1) -> 1 | F84: =INDEX(Establishment!B$2:B$1005,MATCH($E84,Establishment!$A$2:$A$1005,0)) -> #N/A | G84: =INDEX(Establishment!C$2:C$1005,MATCH($E84,Establishment!$A$2:$A$1005,0)) -> #N/A | M84: =K84*L84 -> 0 | N84: =IF(B84=B83,N83+M84,M84) -> 0 | P84: =INDEX(Items!B$2:B$1032,MATCH($O84,Items!$A$2:$A$1032,0)) -> #N/A | Q84: =INDEX(Items!C$2:C$1032,MATCH($O84,Items!$A$2:$A$1032,0)) -> #N/A | R84: =INDEX(Items!D$2:D$1032,MATCH($O84,Items!$A$2:$A$1032,0)) -> #N/A
A85: =IF(OR(D85<>D84,D85=""),1,IF(NOT(AND(E85=E84,F85=F84,G85=G84)),A84+1,IF(OR(H85="",AND(H85<>"",H85<>H84,H84<>"")),A84,A84+1))) -> 1 | B85: =IF(D85<>"",TEXT(D85,"YYYYMMDD")&CHAR(64+A85),"") | C85: =IF(OR(B85="",B85<>B84),1,C84+1) -> 1 | F85: =INDEX(Establishment!B$2:B$1005,MATCH($E85,Establishment!$A$2:$A$1005,0)) -> #N/A | G85: =INDEX(Establishment!C$2:C$1005,MATCH($E85,Establishment!$A$2:$A$1005,0)) -> #N/A | M85: =K85*L85 -> 0 | N85: =IF(B85=B84,N84+M85,M85) -> 0 | P85: =INDEX(Items!B$2:B$1032,MATCH($O85,Items!$A$2:$A$1032,0)) -> #N/A | Q85: =INDEX(Items!C$2:C$1032,MATCH($O85,Items!$A$2:$A$1032,0)) -> #N/A | R85: =INDEX(Items!D$2:D$1032,MATCH($O85,Items!$A$2:$A$1032,0)) -> #N/A
A86: =IF(OR(D86<>D85,D86=""),1,IF(NOT(AND(E86=E85,F86=F85,G86=G85)),A85+1,IF(OR(H86="",AND(H86<>"",H86<>H85,H85<>"")),A85,A85+1))) -> 1 | B86: =IF(D86<>"",TEXT(D86,"YYYYMMDD")&CHAR(64+A86),"") | C86: =IF(OR(B86="",B86<>B85),1,C85+1) -> 1 | F86: =INDEX(Establishment!B$2:B$1005,MATCH($E86,Establishment!$A$2:$A$1005,0)) -> #N/A | G86: =INDEX(Establishment!C$2:C$1005,MATCH($E86,Establishment!$A$2:$A$1005,0)) -> #N/A | M86: =K86*L86 -> 0 | N86: =IF(B86=B85,N85+M86,M86) -> 0 | P86: =INDEX(Items!B$2:B$1032,MATCH($O86,Items!$A$2:$A$1032,0)) -> #N/A | Q86: =INDEX(Items!C$2:C$1032,MATCH($O86,Items!$A$2:$A$1032,0)) -> #N/A | R86: =INDEX(Items!D$2:D$1032,MATCH($O86,Items!$A$2:$A$1032,0)) -> #N/A
A87: =IF(OR(D87<>D86,D87=""),1,IF(NOT(AND(E87=E86,F87=F86,G87=G86)),A86+1,IF(OR(H87="",AND(H87<>"",H87<>H86,H86<>"")),A86,A86+1))) -> 1 | B87: =IF(D87<>"",TEXT(D87,"YYYYMMDD")&CHAR(64+A87),"") | C87: =IF(OR(B87="",B87<>B86),1,C86+1) -> 1 | F87: =INDEX(Establishment!B$2:B$1005,MATCH($E87,Establishment!$A$2:$A$1005,0)) -> #N/A | G87: =INDEX(Establishment!C$2:C$1005,MATCH($E87,Establishment!$A$2:$A$1005,0)) -> #N/A | M87: =K87*L87 -> 0 | N87: =IF(B87=B86,N86+M87,M87) -> 0 | P87: =INDEX(Items!B$2:B$1032,MATCH($O87,Items!$A$2:$A$1032,0)) -> #N/A | Q87: =INDEX(Items!C$2:C$1032,MATCH($O87,Items!$A$2:$A$1032,0)) -> #N/A | R87: =INDEX(Items!D$2:D$1032,MATCH($O87,Items!$A$2:$A$1032,0)) -> #N/A
A88: =IF(OR(D88<>D87,D88=""),1,IF(NOT(AND(E88=E87,F88=F87,G88=G87)),A87+1,IF(OR(H88="",AND(H88<>"",H88<>H87,H87<>"")),A87,A87+1))) -> 1 | B88: =IF(D88<>"",TEXT(D88,"YYYYMMDD")&CHAR(64+A88),"") | C88: =IF(OR(B88="",B88<>B87),1,C87+1) -> 1 | F88: =INDEX(Establishment!B$2:B$1005,MATCH($E88,Establishment!$A$2:$A$1005,0)) -> #N/A | G88: =INDEX(Establishment!C$2:C$1005,MATCH($E88,Establishment!$A$2:$A$1005,0)) -> #N/A | M88: =K88*L88 -> 0 | N88: =IF(B88=B87,N87+M88,M88) -> 0 | P88: =INDEX(Items!B$2:B$1032,MATCH($O88,Items!$A$2:$A$1032,0)) -> #N/A | Q88: =INDEX(Items!C$2:C$1032,MATCH($O88,Items!$A$2:$A$1032,0)) -> #N/A | R88: =INDEX(Items!D$2:D$1032,MATCH($O88,Items!$A$2:$A$1032,0)) -> #N/A
A89: =IF(OR(D89<>D88,D89=""),1,IF(NOT(AND(E89=E88,F89=F88,G89=G88)),A88+1,IF(OR(H89="",AND(H89<>"",H89<>H88,H88<>"")),A88,A88+1))) -> 1 | B89: =IF(D89<>"",TEXT(D89,"YYYYMMDD")&CHAR(64+A89),"") | C89: =IF(OR(B89="",B89<>B88),1,C88+1) -> 1 | F89: =INDEX(Establishment!B$2:B$1005,MATCH($E89,Establishment!$A$2:$A$1005,0)) -> #N/A | G89: =INDEX(Establishment!C$2:C$1005,MATCH($E89,Establishment!$A$2:$A$1005,0)) -> #N/A | M89: =K89*L89 -> 0 | N89: =IF(B89=B88,N88+M89,M89) -> 0 | P89: =INDEX(Items!B$2:B$1032,MATCH($O89,Items!$A$2:$A$1032,0)) -> #N/A | Q89: =INDEX(Items!C$2:C$1032,MATCH($O89,Items!$A$2:$A$1032,0)) -> #N/A | R89: =INDEX(Items!D$2:D$1032,MATCH($O89,Items!$A$2:$A$1032,0)) -> #N/A
A90: =IF(OR(D90<>D89,D90=""),1,IF(NOT(AND(E90=E89,F90=F89,G90=G89)),A89+1,IF(OR(H90="",AND(H90<>"",H90<>H89,H89<>"")),A89,A89+1))) -> 1 | B90: =IF(D90<>"",TEXT(D90,"YYYYMMDD")&CHAR(64+A90),"") | C90: =IF(OR(B90="",B90<>B89),1,C89+1) -> 1 | F90: =INDEX(Establishment!B$2:B$1005,MATCH($E90,Establishment!$A$2:$A$1005,0)) -> #N/A | G90: =INDEX(Establishment!C$2:C$1005,MATCH($E90,Establishment!$A$2:$A$1005,0)) -> #N/A | M90: =K90*L90 -> 0 | N90: =IF(B90=B89,N89+M90,M90) -> 0 | P90: =INDEX(Items!B$2:B$1032,MATCH($O90,Items!$A$2:$A$1032,0)) -> #N/A | Q90: =INDEX(Items!C$2:C$1032,MATCH($O90,Items!$A$2:$A$1032,0)) -> #N/A | R90: =INDEX(Items!D$2:D$1032,MATCH($O90,Items!$A$2:$A$1032,0)) -> #N/A
A91: =IF(OR(D91<>D90,D91=""),1,IF(NOT(AND(E91=E90,F91=F90,G91=G90)),A90+1,IF(OR(H91="",AND(H91<>"",H91<>H90,H90<>"")),A90,A90+1))) -> 1 | B91: =IF(D91<>"",TEXT(D91,"YYYYMMDD")&CHAR(64+A91),"") | C91: =IF(OR(B91="",B91<>B90),1,C90+1) -> 1 | F91: =INDEX(Establishment!B$2:B$1005,MATCH($E91,Establishment!$A$2:$A$1005,0)) -> #N/A | G91: =INDEX(Establishment!C$2:C$1005,MATCH($E91,Establishment!$A$2:$A$1005,0)) -> #N/A | M91: =K91*L91 -> 0 | N91: =IF(B91=B90,N90+M91,M91) -> 0 | P91: =INDEX(Items!B$2:B$1032,MATCH($O91,Items!$A$2:$A$1032,0)) -> #N/A | Q91: =INDEX(Items!C$2:C$1032,MATCH($O91,Items!$A$2:$A$1032,0)) -> #N/A | R91: =INDEX(Items!D$2:D$1032,MATCH($O91,Items!$A$2:$A$1032,0)) -> #N/A
A92: =IF(OR(D92<>D91,D92=""),1,IF(NOT(AND(E92=E91,F92=F91,G92=G91)),A91+1,IF(OR(H92="",AND(H92<>"",H92<>H91,H91<>"")),A91,A91+1))) -> 1 | B92: =IF(D92<>"",TEXT(D92,"YYYYMMDD")&CHAR(64+A92),"") | C92: =IF(OR(B92="",B92<>B91),1,C91+1) -> 1 | F92: =INDEX(Establishment!B$2:B$1005,MATCH($E92,Establishment!$A$2:$A$1005,0)) -> #N/A | G92: =INDEX(Establishment!C$2:C$1005,MATCH($E92,Establishment!$A$2:$A$1005,0)) -> #N/A | M92: =K92*L92 -> 0 | N92: =IF(B92=B91,N91+M92,M92) -> 0 | P92: =INDEX(Items!B$2:B$1032,MATCH($O92,Items!$A$2:$A$1032,0)) -> #N/A | Q92: =INDEX(Items!C$2:C$1032,MATCH($O92,Items!$A$2:$A$1032,0)) -> #N/A | R92: =INDEX(Items!D$2:D$1032,MATCH($O92,Items!$A$2:$A$1032,0)) -> #N/A
A93: =IF(OR(D93<>D92,D93=""),1,IF(NOT(AND(E93=E92,F93=F92,G93=G92)),A92+1,IF(OR(H93="",AND(H93<>"",H93<>H92,H92<>"")),A92,A92+1))) -> 1 | B93: =IF(D93<>"",TEXT(D93,"YYYYMMDD")&CHAR(64+A93),"") | C93: =IF(OR(B93="",B93<>B92),1,C92+1) -> 1 | F93: =INDEX(Establishment!B$2:B$1005,MATCH($E93,Establishment!$A$2:$A$1005,0)) | G93: =INDEX(Establishment!C$2:C$1005,MATCH($E93,Establishment!$A$2:$A$1005,0)) | M93: =K93*L93 -> 0 | N93: =IF(B93=B92,N92+M93,M93) -> 0 | P93: =INDEX(Items!B$2:B$1032,MATCH($O93,Items!$A$2:$A$1032,0)) -> #N/A | Q93: =INDEX(Items!C$2:C$1032,MATCH($O93,Items!$A$2:$A$1032,0)) -> #N/A | R93: =INDEX(Items!D$2:D$1032,MATCH($O93,Items!$A$2:$A$1032,0)) -> #N/A
A94: =IF(OR(D94<>D93,D94=""),1,IF(NOT(AND(E94=E93,F94=F93,G94=G93)),A93+1,IF(OR(H94="",AND(H94<>"",H94<>H93,H93<>"")),A93,A93+1))) -> 1 | B94: =IF(D94<>"",TEXT(D94,"YYYYMMDD")&CHAR(64+A94),"") | C94: =IF(OR(B94="",B94<>B93),1,C93+1) -> 1 | F94: =INDEX(Establishment!B$2:B$1005,MATCH($E94,Establishment!$A$2:$A$1005,0)) | G94: =INDEX(Establishment!C$2:C$1005,MATCH($E94,Establishment!$A$2:$A$1005,0)) | M94: =K94*L94 -> 0 | N94: =IF(B94=B93,N93+M94,M94) -> 0 | P94: =INDEX(Items!B$2:B$1032,MATCH($O94,Items!$A$2:$A$1032,0)) -> #N/A | Q94: =INDEX(Items!C$2:C$1032,MATCH($O94,Items!$A$2:$A$1032,0)) -> #N/A | R94: =INDEX(Items!D$2:D$1032,MATCH($O94,Items!$A$2:$A$1032,0)) -> #N/A
... A98: =IF(OR(D98<>D97,D98=""),1,IF(NOT(AND(E98=E97,F98=F97,G98=G97)),A97+1,IF(OR(H98="",AND(H98<>"",H98<>H97,H97<>"")),A97,A97+1))) -> 1 | B98: =IF(D98<>"",TEXT(D98,"YYYYMMDD")&CHAR(64+A98),"") | C98: =IF(OR(B98="",B98<>B97),1,C97+1) -> 1 | F98: =INDEX(Establishment!B$2:B$1005,MATCH($E98,Establishment!$A$2:$A$1005,0)) | G98: =INDEX(Establishment!C$2:C$1005,MATCH($E98,Establishment!$A$2:$A$1005,0)) | M98: =K98*L98 -> 0 | N98: =IF(B98=B97,N97+M98,M98) -> 0 | P98: =INDEX(Items!B$2:B$1032,MATCH($O98,Items!$A$2:$A$1032,0)) -> #N/A | Q98: =INDEX(Items!C$2:C$1032,MATCH($O98,Items!$A$2:$A$1032,0)) -> #N/A | R98: =INDEX(Items!D$2:D$1032,MATCH($O98,Items!$A$2:$A$1032,0)) -> #N/A
A99: =IF(OR(D99<>D98,D99=""),1,IF(NOT(AND(E99=E98,F99=F98,G99=G98)),A98+1,IF(OR(H99="",AND(H99<>"",H99<>H98,H98<>"")),A98,A98+1))) -> 1 | B99: =IF(D99<>"",TEXT(D99,"YYYYMMDD")&CHAR(64+A99),"") -> 20230621A | C99: =IF(OR(B99="",B99<>B98),1,C98+1) -> 1 | D99: 45098 | E99: Carenderia 14th Floor-ACC Tower Cebu Business Park | F99: =INDEX(Establishment!B$2:B$1005,MATCH($E99,Establishment!$A$2:$A$1005,0)) -> Carenderia 14th Floor | G99: =INDEX(Establishment!C$2:C$1005,MATCH($E99,Establishment!$A$2:$A$1005,0)) -> ACC Tower Cebu Business Park | M99: =K99*L99 -> 0 | N99: =IF(B99=B98,N98+M99,M99) -> 0 | P99: =INDEX(Items!B$2:B$1032,MATCH($O99,Items!$A$2:$A$1032,0)) -> #N/A | Q99: =INDEX(Items!C$2:C$1032,MATCH($O99,Items!$A$2:$A$1032,0)) -> #N/A | R99: =INDEX(Items!D$2:D$1032,MATCH($O99,Items!$A$2:$A$1032,0)) -> #N/A
A100: =IF(OR(D100<>D99,D100=""),1,IF(NOT(AND(E100=E99,F100=F99,G100=G99)),A99+1,IF(OR(H100="",AND(H100<>"",H100<>H99,H99<>"")),A99,A99+1))) -> 1 | B100: =IF(D100<>"",TEXT(D100,"YYYYMMDD")&CHAR(64+A100),"") | C100: =IF(OR(B100="",B100<>B99),1,C99+1) -> 1 | F100: =INDEX(Establishment!B$2:B$1005,MATCH($E100,Establishment!$A$2:$A$1005,0)) -> #N/A | G100: =INDEX(Establishment!C$2:C$1005,MATCH($E100,Establishment!$A$2:$A$1005,0)) -> #N/A | M100: =K100*L100 -> 0 | N100: =IF(B100=B99,N99+M100,M100) -> 0 | P100: =INDEX(Items!B$2:B$1032,MATCH($O100,Items!$A$2:$A$1032,0)) -> #N/A | Q100: =INDEX(Items!C$2:C$1032,MATCH($O100,Items!$A$2:$A$1032,0)) -> #N/A | R100: =INDEX(Items!D$2:D$1032,MATCH($O100,Items!$A$2:$A$1032,0)) -> #N/A
A101: =IF(OR(D101<>D100,D101=""),1,IF(NOT(AND(E101=E100,F101=F100,G101=G100)),A100+1,IF(OR(H101="",AND(H101<>"",H101<>H100,H100<>"")),A100,A100+1))) -> 1 | B101: =IF(D101<>"",TEXT(D101,"YYYYMMDD")&CHAR(64+A101),"") | C101: =IF(OR(B101="",B101<>B100),1,C100+1) -> 1 | F101: =INDEX(Establishment!B$2:B$1005,MATCH($E101,Establishment!$A$2:$A$1005,0)) | G101: =INDEX(Establishment!C$2:C$1005,MATCH($E101,Establishment!$A$2:$A$1005,0)) | M101: =K101*L101 -> 0 | N101: =IF(B101=B100,N100+M101,M101) -> 0 | P101: =INDEX(Items!B$2:B$1032,MATCH($O101,Items!$A$2:$A$1032,0)) -> #N/A | Q101: =INDEX(Items!C$2:C$1032,MATCH($O101,Items!$A$2:$A$1032,0)) -> #N/A | R101: =INDEX(Items!D$2:D$1032,MATCH($O101,Items!$A$2:$A$1032,0)) -> #N/A
A102: =IF(OR(D102<>D101,D102=""),1,IF(NOT(AND(E102=E101,F102=F101,G102=G101)),A101+1,IF(OR(H102="",AND(H102<>"",H102<>H101,H101<>"")),A101,A101+1))) -> 1 | B102: =IF(D102<>"",TEXT(D102,"YYYYMMDD")&CHAR(64+A102),"") | C102: =IF(OR(B102="",B102<>B101),1,C101+1) -> 1 | F102: =INDEX(Establishment!B$2:B$1005,MATCH($E102,Establishment!$A$2:$A$1005,0)) | G102: =INDEX(Establishment!C$2:C$1005,MATCH($E102,Establishment!$A$2:$A$1005,0)) | M102: =K102*L102 -> 0 | N102: =IF(B102=B101,N101+M102,M102) -> 0 | P102: =INDEX(Items!B$2:B$1032,MATCH($O102,Items!$A$2:$A$1032,0)) -> #N/A | Q102: =INDEX(Items!C$2:C$1032,MATCH($O102,Items!$A$2:$A$1032,0)) -> #N/A | R102: =INDEX(Items!D$2:D$1032,MATCH($O102,Items!$A$2:$A$1032,0)) -> #N/A
A103: =IF(OR(D103<>D102,D103=""),1,IF(NOT(AND(E103=E102,F103=F102,G103=G102)),A102+1,IF(OR(H103="",AND(H103<>"",H103<>H102,H102<>"")),A102,A102+1))) -> 1 | B103: =IF(D103<>"",TEXT(D103,"YYYYMMDD")&CHAR(64+A103),"") | C103: =IF(OR(B103="",B103<>B102),1,C102+1) -> 1 | F103: =INDEX(Establishment!B$2:B$1005,MATCH($E103,Establishment!$A$2:$A$1005,0)) | G103: =INDEX(Establishment!C$2:C$1005,MATCH($E103,Establishment!$A$2:$A$1005,0)) | M103: =K103*L103 -> 0 | N103: =IF(B103=B102,N102+M103,M103) -> 0 | P103: =INDEX(Items!B$2:B$1032,MATCH($O103,Items!$A$2:$A$1032,0)) -> #N/A | Q103: =INDEX(Items!C$2:C$1032,MATCH($O103,Items!$A$2:$A$1032,0)) -> #N/A | R103: =INDEX(Items!D$2:D$1032,MATCH($O103,Items!$A$2:$A$1032,0)) -> #N/A
A104: =IF(OR(D104<>D103,D104=""),1,IF(NOT(AND(E104=E103,F104=F103,G104=G103)),A103+1,IF(OR(H104="",AND(H104<>"",H104<>H103,H103<>"")),A103,A103+1))) -> 1 | B104: =IF(D104<>"",TEXT(D104,"YYYYMMDD")&CHAR(64+A104),"") | C104: =IF(OR(B104="",B104<>B103),1,C103+1) -> 1 | F104: =INDEX(Establishment!B$2:B$1005,MATCH($E104,Establishment!$A$2:$A$1005,0)) | G104: =INDEX(Establishment!C$2:C$1005,MATCH($E104,Establishment!$A$2:$A$1005,0)) | M104: =K104*L104 -> 0 | N104: =IF(B104=B103,N103+M104,M104) -> 0 | P104: =INDEX(Items!B$2:B$1032,MATCH($O104,Items!$A$2:$A$1032,0)) -> #N/A | Q104: =INDEX(Items!C$2:C$1032,MATCH($O104,Items!$A$2:$A$1032,0)) -> #N/A | R104: =INDEX(Items!D$2:D$1032,MATCH($O104,Items!$A$2:$A$1032,0)) -> #N/A
A105: =IF(OR(D105<>D104,D105=""),1,IF(NOT(AND(E105=E104,F105=F104,G105=G104)),A104+1,IF(OR(H105="",AND(H105<>"",H105<>H104,H104<>"")),A104,A104+1))) -> 1 | B105: =IF(D105<>"",TEXT(D105,"YYYYMMDD")&CHAR(64+A105),"") | C105: =IF(OR(B105="",B105<>B104),1,C104+1) -> 1 | F105: =INDEX(Establishment!B$2:B$1005,MATCH($E105,Establishment!$A$2:$A$1005,0)) | G105: =INDEX(Establishment!C$2:C$1005,MATCH($E105,Establishment!$A$2:$A$1005,0)) | M105: =K105*L105 -> 0 | N105: =IF(B105=B104,N104+M105,M105) -> 0 | P105: =INDEX(Items!B$2:B$1032,MATCH($O105,Items!$A$2:$A$1032,0)) -> #N/A | Q105: =INDEX(Items!C$2:C$1032,MATCH($O105,Items!$A$2:$A$1032,0)) -> #N/A | R105: =INDEX(Items!D$2:D$1032,MATCH($O105,Items!$A$2:$A$1032,0)) -> #N/A
A106: =IF(OR(D106<>D105,D106=""),1,IF(NOT(AND(E106=E105,F106=F105,G106=G105)),A105+1,IF(OR(H106="",AND(H106<>"",H106<>H105,H105<>"")),A105,A105+1))) -> 1 | B106: =IF(D106<>"",TEXT(D106,"YYYYMMDD")&CHAR(64+A106),"") | C106: =IF(OR(B106="",B106<>B105),1,C105+1) -> 1 | F106: =INDEX(Establishment!B$2:B$1005,MATCH($E106,Establishment!$A$2:$A$1005,0)) | G106: =INDEX(Establishment!C$2:C$1005,MATCH($E106,Establishment!$A$2:$A$1005,0)) | M106: =K106*L106 -> 0 | N106: =IF(B106=B105,N105+M106,M106) -> 0 | P106: =INDEX(Items!B$2:B$1032,MATCH($O106,Items!$A$2:$A$1032,0)) -> #N/A | Q106: =INDEX(Items!C$2:C$1032,MATCH($O106,Items!$A$2:$A$1032,0)) -> #N/A | R106: =INDEX(Items!D$2:D$1032,MATCH($O106,Items!$A$2:$A$1032,0)) -> #N/A
A107: =IF(OR(D107<>D106,D107=""),1,IF(NOT(AND(E107=E106,F107=F106,G107=G106)),A106+1,IF(OR(H107="",AND(H107<>"",H107<>H106,H106<>"")),A106,A106+1))) -> 1 | B107: =IF(D107<>"",TEXT(D107,"YYYYMMDD")&CHAR(64+A107),"") | C107: =IF(OR(B107="",B107<>B106),1,C106+1) -> 1 | F107: =INDEX(Establishment!B$2:B$1005,MATCH($E107,Establishment!$A$2:$A$1005,0)) | G107: =INDEX(Establishment!C$2:C$1005,MATCH($E107,Establishment!$A$2:$A$1005,0)) | M107: =K107*L107 -> 0 | N107: =IF(B107=B106,N106+M107,M107) -> 0 | P107: =INDEX(Items!B$2:B$1032,MATCH($O107,Items!$A$2:$A$1032,0)) -> #N/A | Q107: =INDEX(Items!C$2:C$1032,MATCH($O107,Items!$A$2:$A$1032,0)) -> #N/A | R107: =INDEX(Items!D$2:D$1032,MATCH($O107,Items!$A$2:$A$1032,0)) -> #N/A
A108: =IF(OR(D108<>D107,D108=""),1,IF(NOT(AND(E108=E107,F108=F107,G108=G107)),A107+1,IF(OR(H108="",AND(H108<>"",H108<>H107,H107<>"")),A107,A107+1))) -> 1 | B108: =IF(D108<>"",TEXT(D108,"YYYYMMDD")&CHAR(64+A108),"") | C108: =IF(OR(B108="",B108<>B107),1,C107+1) -> 1 | F108: =INDEX(Establishment!B$2:B$1005,MATCH($E108,Establishment!$A$2:$A$1005,0)) | G108: =INDEX(Establishment!C$2:C$1005,MATCH($E108,Establishment!$A$2:$A$1005,0)) | M108: =K108*L108 -> 0 | N108: =IF(B108=B107,N107+M108,M108) -> 0 | P108: =INDEX(Items!B$2:B$1032,MATCH($O108,Items!$A$2:$A$1032,0)) -> #N/A | Q108: =INDEX(Items!C$2:C$1032,MATCH($O108,Items!$A$2:$A$1032,0)) -> #N/A | R108: =INDEX(Items!D$2:D$1032,MATCH($O108,Items!$A$2:$A$1032,0)) -> #N/A
A109: =IF(OR(D109<>D108,D109=""),1,IF(NOT(AND(E109=E108,F109=F108,G109=G108)),A108+1,IF(OR(H109="",AND(H109<>"",H109<>H108,H108<>"")),A108,A108+1))) -> 1 | B109: =IF(D109<>"",TEXT(D109,"YYYYMMDD")&CHAR(64+A109),"") | C109: =IF(OR(B109="",B109<>B108),1,C108+1) -> 1 | F109: =INDEX(Establishment!B$2:B$1005,MATCH($E109,Establishment!$A$2:$A$1005,0)) | G109: =INDEX(Establishment!C$2:C$1005,MATCH($E109,Establishment!$A$2:$A$1005,0)) | M109: =K109*L109 -> 0 | N109: =IF(B109=B108,N108+M109,M109) -> 0 | P109: =INDEX(Items!B$2:B$1032,MATCH($O109,Items!$A$2:$A$1032,0)) -> #N/A | Q109: =INDEX(Items!C$2:C$1032,MATCH($O109,Items!$A$2:$A$1032,0)) -> #N/A | R109: =INDEX(Items!D$2:D$1032,MATCH($O109,Items!$A$2:$A$1032,0)) -> #N/A
A110: =IF(OR(D110<>D109,D110=""),1,IF(NOT(AND(E110=E109,F110=F109,G110=G109)),A109+1,IF(OR(H110="",AND(H110<>"",H110<>H109,H109<>"")),A109,A109+1))) -> 1 | B110: =IF(D110<>"",TEXT(D110,"YYYYMMDD")&CHAR(64+A110),"") | C110: =IF(OR(B110="",B110<>B109),1,C109+1) -> 1 | F110: =INDEX(Establishment!B$2:B$1005,MATCH($E110,Establishment!$A$2:$A$1005,0)) | G110: =INDEX(Establishment!C$2:C$1005,MATCH($E110,Establishment!$A$2:$A$1005,0)) | M110: =K110*L110 -> 0 | N110: =IF(B110=B109,N109+M110,M110) -> 0 | P110: =INDEX(Items!B$2:B$1032,MATCH($O110,Items!$A$2:$A$1032,0)) -> #N/A | Q110: =INDEX(Items!C$2:C$1032,MATCH($O110,Items!$A$2:$A$1032,0)) -> #N/A | R110: =INDEX(Items!D$2:D$1032,MATCH($O110,Items!$A$2:$A$1032,0)) -> #N/A
A111: =IF(OR(D111<>D110,D111=""),1,IF(NOT(AND(E111=E110,F111=F110,G111=G110)),A110+1,IF(OR(H111="",AND(H111<>"",H111<>H110,H110<>"")),A110,A110+1))) -> 1 | B111: =IF(D111<>"",TEXT(D111,"YYYYMMDD")&CHAR(64+A111),"") | C111: =IF(OR(B111="",B111<>B110),1,C110+1) -> 1 | F111: =INDEX(Establishment!B$2:B$1005,MATCH($E111,Establishment!$A$2:$A$1005,0)) | G111: =INDEX(Establishment!C$2:C$1005,MATCH($E111,Establishment!$A$2:$A$1005,0)) | M111: =K111*L111 -> 0 | N111: =IF(B111=B110,N110+M111,M111) -> 0 | P111: =INDEX(Items!B$2:B$1032,MATCH($O111,Items!$A$2:$A$1032,0)) -> #N/A | Q111: =INDEX(Items!C$2:C$1032,MATCH($O111,Items!$A$2:$A$1032,0)) -> #N/A | R111: =INDEX(Items!D$2:D$1032,MATCH($O111,Items!$A$2:$A$1032,0)) -> #N/A
... A499: =IF(OR(D499<>D498,D499=""),1,IF(NOT(AND(E499=E498,F499=F498,G499=G498)),A498+1,IF(OR(H499="",AND(H499<>"",H499<>H498,H498<>"")),A498,A498+1))) -> 1 | B499: =IF(D499<>"",TEXT(D499,"YYYYMMDD")&CHAR(64+A499),"") | C499: =IF(OR(B499="",B499<>B498),1,C498+1) -> 1 | F499: =INDEX(Establishment!B$2:B$1005,MATCH($E499,Establishment!$A$2:$A$1005,0)) | G499: =INDEX(Establishment!C$2:C$1005,MATCH($E499,Establishment!$A$2:$A$1005,0)) | M499: =K499*L499 -> 0 | N499: =IF(B499=B498,N498+M499,M499) -> 0 | P499: =INDEX(Items!B$2:B$1032,MATCH($O499,Items!$A$2:$A$1032,0)) -> #N/A | Q499: =INDEX(Items!C$2:C$1032,MATCH($O499,Items!$A$2:$A$1032,0)) -> #N/A | R499: =INDEX(Items!D$2:D$1032,MATCH($O499,Items!$A$2:$A$1032,0)) -> #N/A

Sheet 2023-02
A1: Count | B1: Transaction Number | C1: Detail # | D1: Date | E1: Establishment Id | F1: Establishment | G1: Branch | H1: Payment Type | I1: Amount | J1: Account | K1: Quantity | L1: Unit Price | M1: Amount | N1: Total | O1: Item ID | P1: Brand | Q1: Type | R1: Details | S1: Notes
A2: =IF(OR(D2<>D1,D2=""),1,IF(NOT(AND(E2=E1,F2=F1,G2=G1)),A1+1,IF(OR(H2="",AND(H2<>"",H2<>H1,H1<>"")),A1,A1+1))) -> 1 | B2: =IF(D2<>"",TEXT(D2,"YYYYMMDD")&CHAR(64+A2),"") | C2: =IF(OR(B2="",B2<>B10),1,C10+1) -> 1 | F2: =INDEX(Establishment!B$2:B$1005,MATCH($E2,Establishment!$A$2:$A$1005,0)) -> #N/A | G2: =INDEX(Establishment!C$2:C$1005,MATCH($E2,Establishment!$A$2:$A$1005,0)) -> #N/A | M2: =K2*L2 -> 0 | N2: =IF(B2=B1,N1+M2,M2) -> 0 | P2: =INDEX(Items!B$2:B$1032,MATCH($O2,Items!$A$2:$A$1032,0)) -> #N/A | Q2: =INDEX(Items!C$2:C$1032,MATCH($O2,Items!$A$2:$A$1032,0)) -> #N/A | R2: =INDEX(Items!D$2:D$1032,MATCH($O2,Items!$A$2:$A$1032,0)) -> #N/A
A3: =IF(OR(D3<>D2,D3=""),1,IF(NOT(AND(E3=E2,F3=F2,G3=G2)),A2+1,IF(OR(H3="",AND(H3<>"",H3<>H2,H2<>"")),A2,A2+1))) -> 1 | B3: =IF(D3<>"",TEXT(D3,"YYYYMMDD")&CHAR(64+A3),"") | C3: =IF(OR(B3="",B3<>B11),1,C11+1) -> 1 | F3: =INDEX(Establishment!B$2:B$1005,MATCH($E3,Establishment!$A$2:$A$1005,0)) -> #N/A | G3: =INDEX(Establishment!C$2:C$1005,MATCH($E3,Establishment!$A$2:$A$1005,0)) -> #N/A | M3: =K3*L3 -> 0 | N3: =IF(B3=B2,N2+M3,M3) -> 0 | P3: =INDEX(Items!B$2:B$1032,MATCH($O3,Items!$A$2:$A$1032,0)) -> #N/A | Q3: =INDEX(Items!C$2:C$1032,MATCH($O3,Items!$A$2:$A$1032,0)) -> #N/A | R3: =INDEX(Items!D$2:D$1032,MATCH($O3,Items!$A$2:$A$1032,0)) -> #N/A
A4: =IF(OR(D4<>D3,D4=""),1,IF(NOT(AND(E4=E3,F4=F3,G4=G3)),A3+1,IF(OR(H4="",AND(H4<>"",H4<>H3,H3<>"")),A3,A3+1))) -> 1 | B4: =IF(D4<>"",TEXT(D4,"YYYYMMDD")&CHAR(64+A4),"") | C4: =IF(OR(B4="",B4<>B12),1,C12+1) -> 1 | F4: =INDEX(Establishment!B$2:B$1005,MATCH($E4,Establishment!$A$2:$A$1005,0)) -> #N/A | G4: =INDEX(Establishment!C$2:C$1005,MATCH($E4,Establishment!$A$2:$A$1005,0)) -> #N/A | M4: =K4*L4 -> 0 | N4: =IF(B4=B3,N3+M4,M4) -> 0 | P4: =INDEX(Items!B$2:B$1032,MATCH($O4,Items!$A$2:$A$1032,0)) -> #N/A | Q4: =INDEX(Items!C$2:C$1032,MATCH($O4,Items!$A$2:$A$1032,0)) -> #N/A | R4: =INDEX(Items!D$2:D$1032,MATCH($O4,Items!$A$2:$A$1032,0)) -> #N/A
A5: =IF(OR(D5<>D4,D5=""),1,IF(NOT(AND(E5=E4,F5=F4,G5=G4)),A4+1,IF(OR(H5="",AND(H5<>"",H5<>H4,H4<>"")),A4,A4+1))) -> 1 | B5: =IF(D5<>"",TEXT(D5,"YYYYMMDD")&CHAR(64+A5),"") | C5: =IF(OR(B5="",B5<>B13),1,C13+1) -> 1 | F5: =INDEX(Establishment!B$2:B$1005,MATCH($E5,Establishment!$A$2:$A$1005,0)) -> #N/A | G5: =INDEX(Establishment!C$2:C$1005,MATCH($E5,Establishment!$A$2:$A$1005,0)) -> #N/A | M5: =K5*L5 -> 0 | N5: =IF(B5=B4,N4+M5,M5) -> 0 | P5: =INDEX(Items!B$2:B$1032,MATCH($O5,Items!$A$2:$A$1032,0)) -> #N/A | Q5: =INDEX(Items!C$2:C$1032,MATCH($O5,Items!$A$2:$A$1032,0)) -> #N/A | R5: =INDEX(Items!D$2:D$1032,MATCH($O5,Items!$A$2:$A$1032,0)) -> #N/A
A6: =IF(OR(D6<>D5,D6=""),1,IF(NOT(AND(E6=E5,F6=F5,G6=G5)),A5+1,IF(OR(H6="",AND(H6<>"",H6<>H5,H5<>"")),A5,A5+1))) -> 1 | B6: =IF(D6<>"",TEXT(D6,"YYYYMMDD")&CHAR(64+A6),"") | C6: =IF(OR(B6="",B6<>B14),1,C14+1) -> 1 | F6: =INDEX(Establishment!B$2:B$1005,MATCH($E6,Establishment!$A$2:$A$1005,0)) -> #N/A | G6: =INDEX(Establishment!C$2:C$1005,MATCH($E6,Establishment!$A$2:$A$1005,0)) -> #N/A | M6: =K6*L6 -> 0 | N6: =IF(B6=B5,N5+M6,M6) -> 0 | P6: =INDEX(Items!B$2:B$1032,MATCH($O6,Items!$A$2:$A$1032,0)) -> #N/A | Q6: =INDEX(Items!C$2:C$1032,MATCH($O6,Items!$A$2:$A$1032,0)) -> #N/A | R6: =INDEX(Items!D$2:D$1032,MATCH($O6,Items!$A$2:$A$1032,0)) -> #N/A
A7: =IF(OR(D7<>D6,D7=""),1,IF(NOT(AND(E7=E6,F7=F6,G7=G6)),A6+1,IF(OR(H7="",AND(H7<>"",H7<>H6,H6<>"")),A6,A6+1))) -> 1 | B7: =IF(D7<>"",TEXT(D7,"YYYYMMDD")&CHAR(64+A7),"") | C7: =IF(OR(B7="",B7<>B15),1,C15+1) -> 1 | F7: =INDEX(Establishment!B$2:B$1005,MATCH($E7,Establishment!$A$2:$A$1005,0)) -> #N/A | G7: =INDEX(Establishment!C$2:C$1005,MATCH($E7,Establishment!$A$2:$A$1005,0)) -> #N/A | M7: =K7*L7 -> 0 | N7: =IF(B7=B6,N6+M7,M7) -> 0 | P7: =INDEX(Items!B$2:B$1032,MATCH($O7,Items!$A$2:$A$1032,0)) -> #N/A | Q7: =INDEX(Items!C$2:C$1032,MATCH($O7,Items!$A$2:$A$1032,0)) -> #N/A | R7: =INDEX(Items!D$2:D$1032,MATCH($O7,Items!$A$2:$A$1032,0)) -> #N/A
A8: =IF(OR(D8<>D7,D8=""),1,IF(NOT(AND(E8=E7,F8=F7,G8=G7)),A7+1,IF(OR(H8="",AND(H8<>"",H8<>H7,H7<>"")),A7,A7+1))) -> 1 | B8: =IF(D8<>"",TEXT(D8,"YYYYMMDD")&CHAR(64+A8),"") | C8: =IF(OR(B8="",B8<>B7),1,C7+1) -> 1 | F8: =INDEX(Establishment!B$2:B$1005,MATCH($E8,Establishment!$A$2:$A$1005,0)) -> #N/A | G8: =INDEX(Establishment!C$2:C$1005,MATCH($E8,Establishment!$A$2:$A$1005,0)) -> #N/A | M8: =K8*L8 -> 0 | N8: =IF(B8=B7,N7+M8,M8) -> 0 | P8: =INDEX(Items!B$2:B$1032,MATCH($O8,Items!$A$2:$A$1032,0)) -> #N/A | Q8: =INDEX(Items!C$2:C$1032,MATCH($O8,Items!$A$2:$A$1032,0)) -> #N/A | R8: =INDEX(Items!D$2:D$1032,MATCH($O8,Items!$A$2:$A$1032,0)) -> #N/A
A9: =IF(OR(D9<>D8,D9=""),1,IF(NOT(AND(E9=E8,F9=F8,G9=G8)),A8+1,IF(OR(H9="",AND(H9<>"",H9<>H8,H8<>"")),A8,A8+1))) -> 1 | B9: =IF(D9<>"",TEXT(D9,"YYYYMMDD")&CHAR(64+A9),"") | C9: =IF(OR(B9="",B9<>B8),1,C8+1) -> 1 | F9: =INDEX(Establishment!B$2:B$1005,MATCH($E9,Establishment!$A$2:$A$1005,0)) -> #N/A | G9: =INDEX(Establishment!C$2:C$1005,MATCH($E9,Establishment!$A$2:$A$1005,0)) -> #N/A | M9: =K9*L9 -> 0 | N9: =IF(B9=B8,N8+M9,M9) -> 0 | P9: =INDEX(Items!B$2:B$1032,MATCH($O9,Items!$A$2:$A$1032,0)) -> #N/A | Q9: =INDEX(Items!C$2:C$1032,MATCH($O9,Items!$A$2:$A$1032,0)) -> #N/A | R9: =INDEX(Items!D$2:D$1032,MATCH($O9,Items!$A$2:$A$1032,0)) -> #N/A
A10: =IF(OR(D10<>D9,D10=""),1,IF(NOT(AND(E10=E9,F10=F9,G10=G9)),A9+1,IF(OR(H10="",AND(H10<>"",H10<>H9,H9<>"")),A9,A9+1))) -> 1 | B10: =IF(D10<>"",TEXT(D10,"YYYYMMDD")&CHAR(64+A10),"") | C10: =IF(OR(B10="",B10<>B9),1,C9+1) -> 1 | F10: =INDEX(Establishment!B$2:B$1005,MATCH($E10,Establishment!$A$2:$A$1005,0)) -> #N/A | G10: =INDEX(Establishment!C$2:C$1005,MATCH($E10,Establishment!$A$2:$A$1005,0)) -> #N/A | M10: =K10*L10 -> 0 | N10: =IF(B10=B9,N9+M10,M10) -> 0 | P10: =INDEX(Items!B$2:B$1032,MATCH($O10,Items!$A$2:$A$1032,0)) -> #N/A | Q10: =INDEX(Items!C$2:C$1032,MATCH($O10,Items!$A$2:$A$1032,0)) -> #N/A | R10: =INDEX(Items!D$2:D$1032,MATCH($O10,Items!$A$2:$A$1032,0)) -> #N/A
A11: =IF(OR(D11<>D10,D11=""),1,IF(NOT(AND(E11=E10,F11=F10,G11=G10)),A10+1,IF(OR(H11="",AND(H11<>"",H11<>H10,H10<>"")),A10,A10+1))) -> 1 | B11: =IF(D11<>"",TEXT(D11,"YYYYMMDD")&CHAR(64+A11),"") | C11: =IF(OR(B11="",B11<>B10),1,C10+1) -> 1 | F11: =INDEX(Establishment!B$2:B$1005,MATCH($E11,Establishment!$A$2:$A$1005,0)) -> #N/A | G11: =INDEX(Establishment!C$2:C$1005,MATCH($E11,Establishment!$A$2:$A$1005,0)) -> #N/A | M11: =K11*L11 -> 0 | N11: =IF(B11=B10,N10+M11,M11) -> 0 | P11: =INDEX(Items!B$2:B$1032,MATCH($O11,Items!$A$2:$A$1032,0)) -> #N/A | Q11: =INDEX(Items!C$2:C$1032,MATCH($O11,Items!$A$2:$A$1032,0)) -> #N/A | R11: =INDEX(Items!D$2:D$1032,MATCH($O11,Items!$A$2:$A$1032,0)) -> #N/A
A12: =IF(OR(D12<>D11,D12=""),1,IF(NOT(AND(E12=E11,F12=F11,G12=G11)),A11+1,IF(OR(H12="",AND(H12<>"",H12<>H11,H11<>"")),A11,A11+1))) -> 1 | B12: =IF(D12<>"",TEXT(D12,"YYYYMMDD")&CHAR(64+A12),"") | C12: =IF(OR(B12="",B12<>B11),1,C11+1) -> 1 | F12: =INDEX(Establishment!B$2:B$1005,MATCH($E12,Establishment!$A$2:$A$1005,0)) -> #N/A | G12: =INDEX(Establishment!C$2:C$1005,MATCH($E12,Establishment!$A$2:$A$1005,0)) -> #N/A | M12: =K12*L12 -> 0 | N12: =IF(B12=B11,N11+M12,M12) -> 0 | P12: =INDEX(Items!B$2:B$1032,MATCH($O12,Items!$A$2:$A$1032,0)) -> #N/A | Q12: =INDEX(Items!C$2:C$1032,MATCH($O12,Items!$A$2:$A$1032,0)) -> #N/A | R12: =INDEX(Items!D$2:D$1032,MATCH($O12,Items!$A$2:$A$1032,0)) -> #N/A
A13: =IF(OR(D13<>D12,D13=""),1,IF(NOT(AND(E13=E12,F13=F12,G13=G12)),A12+1,IF(OR(H13="",AND(H13<>"",H13<>H12,H12<>"")),A12,A12+1))) -> 1 | B13: =IF(D13<>"",TEXT(D13,"YYYYMMDD")&CHAR(64+A13),"") | C13: =IF(OR(B13="",B13<>B12),1,C12+1) -> 1 | F13: =INDEX(Establishment!B$2:B$1005,MATCH($E13,Establishment!$A$2:$A$1005,0)) -> #N/A | G13: =INDEX(Establishment!C$2:C$1005,MATCH($E13,Establishment!$A$2:$A$1005,0)) -> #N/A | M13: =K13*L13 -> 0 | N13: =IF(B13=B12,N12+M13,M13) -> 0 | P13: =INDEX(Items!B$2:B$1032,MATCH($O13,Items!$A$2:$A$1032,0)) -> #N/A | Q13: =INDEX(Items!C$2:C$1032,MATCH($O13,Items!$A$2:$A$1032,0)) -> #N/A | R13: =INDEX(Items!D$2:D$1032,MATCH($O13,Items!$A$2:$A$1032,0)) -> #N/A
A14: =IF(OR(D14<>D13,D14=""),1,IF(NOT(AND(E14=E13,F14=F13,G14=G13)),A13+1,IF(OR(H14="",AND(H14<>"",H14<>H13,H13<>"")),A13,A13+1))) -> 1 | B14: =IF(D14<>"",TEXT(D14,"YYYYMMDD")&CHAR(64+A14),"") | C14: =IF(OR(B14="",B14<>B13),1,C13+1) -> 1 | F14: =INDEX(Establishment!B$2:B$1005,MATCH($E14,Establishment!$A$2:$A$1005,0)) -> #N/A | G14: =INDEX(Establishment!C$2:C$1005,MATCH($E14,Establishment!$A$2:$A$1005,0)) -> #N/A | M14: =K14*L14 -> 0 | N14: =IF(B14=B13,N13+M14,M14) -> 0 | P14: =INDEX(Items!B$2:B$1032,MATCH($O14,Items!$A$2:$A$1032,0)) -> #N/A | Q14: =INDEX(Items!C$2:C$1032,MATCH($O14,Items!$A$2:$A$1032,0)) -> #N/A | R14: =INDEX(Items!D$2:D$1032,MATCH($O14,Items!$A$2:$A$1032,0)) -> #N/A
A15: =IF(OR(D15<>D14,D15=""),1,IF(NOT(AND(E15=E14,F15=F14,G15=G14)),A14+1,IF(OR(H15="",AND(H15<>"",H15<>H14,H14<>"")),A14,A14+1))) -> 1 | B15: =IF(D15<>"",TEXT(D15,"YYYYMMDD")&CHAR(64+A15),"") | C15: =IF(OR(B15="",B15<>B14),1,C14+1) -> 1 | F15: =INDEX(Establishment!B$2:B$1005,MATCH($E15,Establishment!$A$2:$A$1005,0)) -> #N/A | G15: =INDEX(Establishment!C$2:C$1005,MATCH($E15,Establishment!$A$2:$A$1005,0)) -> #N/A | M15: =K15*L15 -> 0 | N15: =IF(B15=B14,N14+M15,M15) -> 0 | P15: =INDEX(Items!B$2:B$1032,MATCH($O15,Items!$A$2:$A$1032,0)) -> #N/A | Q15: =INDEX(Items!C$2:C$1032,MATCH($O15,Items!$A$2:$A$1032,0)) -> #N/A | R15: =INDEX(Items!D$2:D$1032,MATCH($O15,Items!$A$2:$A$1032,0)) -> #N/A
A16: =IF(OR(D16<>D15,D16=""),1,IF(NOT(AND(E16=E15,F16=F15,G16=G15)),A15+1,IF(OR(H16="",AND(H16<>"",H16<>H15,H15<>"")),A15,A15+1))) -> 1 | B16: =IF(D16<>"",TEXT(D16,"YYYYMMDD")&CHAR(64+A16),"") | C16: =IF(OR(B16="",B16<>B15),1,C15+1) -> 1 | F16: =INDEX(Establishment!B$2:B$1005,MATCH($E16,Establishment!$A$2:$A$1005,0)) -> #N/A | G16: =INDEX(Establishment!C$2:C$1005,MATCH($E16,Establishment!$A$2:$A$1005,0)) -> #N/A | M16: =K16*L16 -> 0 | N16: =IF(B16=B15,N15+M16,M16) -> 0 | P16: =INDEX(Items!B$2:B$1032,MATCH($O16,Items!$A$2:$A$1032,0)) -> #N/A | Q16: =INDEX(Items!C$2:C$1032,MATCH($O16,Items!$A$2:$A$1032,0)) -> #N/A | R16: =INDEX(Items!D$2:D$1032,MATCH($O16,Items!$A$2:$A$1032,0)) -> #N/A
A17: =IF(OR(D17<>D16,D17=""),1,IF(NOT(AND(E17=E16,F17=F16,G17=G16)),A16+1,IF(OR(H17="",AND(H17<>"",H17<>H16,H16<>"")),A16,A16+1))) -> 1 | B17: =IF(D17<>"",TEXT(D17,"YYYYMMDD")&CHAR(64+A17),"") | C17: =IF(OR(B17="",B17<>B16),1,C16+1) -> 1 | F17: =INDEX(Establishment!B$2:B$1005,MATCH($E17,Establishment!$A$2:$A$1005,0)) -> #N/A | G17: =INDEX(Establishment!C$2:C$1005,MATCH($E17,Establishment!$A$2:$A$1005,0)) -> #N/A | M17: =K17*L17 -> 0 | N17: =IF(B17=B16,N16+M17,M17) -> 0 | P17: =INDEX(Items!B$2:B$1032,MATCH($O17,Items!$A$2:$A$1032,0)) -> #N/A | Q17: =INDEX(Items!C$2:C$1032,MATCH($O17,Items!$A$2:$A$1032,0)) -> #N/A | R17: =INDEX(Items!D$2:D$1032,MATCH($O17,Items!$A$2:$A$1032,0)) -> #N/A
A18: =IF(OR(D18<>D17,D18=""),1,IF(NOT(AND(E18=E17,F18=F17,G18=G17)),A17+1,IF(OR(H18="",AND(H18<>"",H18<>H17,H17<>"")),A17,A17+1))) -> 1 | B18: =IF(D18<>"",TEXT(D18,"YYYYMMDD")&CHAR(64+A18),"") | C18: =IF(OR(B18="",B18<>B17),1,C17+1) -> 1 | F18: =INDEX(Establishment!B$2:B$1005,MATCH($E18,Establishment!$A$2:$A$1005,0)) -> #N/A | G18: =INDEX(Establishment!C$2:C$1005,MATCH($E18,Establishment!$A$2:$A$1005,0)) -> #N/A | M18: =K18*L18 -> 0 | N18: =IF(B18=B17,N17+M18,M18) -> 0 | P18: =INDEX(Items!B$2:B$1032,MATCH($O18,Items!$A$2:$A$1032,0)) -> #N/A | Q18: =INDEX(Items!C$2:C$1032,MATCH($O18,Items!$A$2:$A$1032,0)) -> #N/A | R18: =INDEX(Items!D$2:D$1032,MATCH($O18,Items!$A$2:$A$1032,0)) -> #N/A
A19: =IF(OR(D19<>D18,D19=""),1,IF(NOT(AND(E19=E18,F19=F18,G19=G18)),A18+1,IF(OR(H19="",AND(H19<>"",H19<>H18,H18<>"")),A18,A18+1))) -> 1 | B19: =IF(D19<>"",TEXT(D19,"YYYYMMDD")&CHAR(64+A19),"") | C19: =IF(OR(B19="",B19<>B18),1,C18+1) -> 1 | F19: =INDEX(Establishment!B$2:B$1005,MATCH($E19,Establishment!$A$2:$A$1005,0)) -> #N/A | G19: =INDEX(Establishment!C$2:C$1005,MATCH($E19,Establishment!$A$2:$A$1005,0)) -> #N/A | M19: =K19*L19 -> 0 | N19: =IF(B19=B18,N18+M19,M19) -> 0 | P19: =INDEX(Items!B$2:B$1032,MATCH($O19,Items!$A$2:$A$1032,0)) -> #N/A | Q19: =INDEX(Items!C$2:C$1032,MATCH($O19,Items!$A$2:$A$1032,0)) -> #N/A | R19: =INDEX(Items!D$2:D$1032,MATCH($O19,Items!$A$2:$A$1032,0)) -> #N/A
... A25: =IF(OR(D25<>D24,D25=""),1,IF(NOT(AND(E25=E24,F25=F24,G25=G24)),A24+1,IF(OR(H25="",AND(H25<>"",H25<>H24,H24<>"")),A24,A24+1))) -> 1 | B25: =IF(D25<>"",TEXT(D25,"YYYYMMDD")&CHAR(64+A25),"") | C25: =IF(OR(B25="",B25<>B24),1,C24+1) -> 1 | F25: =INDEX(Establishment!B$2:B$1005,MATCH($E25,Establishment!$A$2:$A$1005,0)) -> #N/A | G25: =INDEX(Establishment!C$2:C$1005,MATCH($E25,Establishment!$A$2:$A$1005,0)) -> #N/A | M25: =K25*L25 -> 0 | N25: =IF(B25=B24,N24+M25,M25) -> 0 | P25: =INDEX(Items!B$2:B$1032,MATCH($O25,Items!$A$2:$A$1032,0)) -> #N/A | Q25: =INDEX(Items!C$2:C$1032,MATCH($O25,Items!$A$2:$A$1032,0)) -> #N/A | R25: =INDEX(Items!D$2:D$1032,MATCH($O25,Items!$A$2:$A$1032,0)) -> #N/A
A26: =IF(OR(D26<>D25,D26=""),1,IF(NOT(AND(E26=E25,F26=F25,G26=G25)),A25+1,IF(OR(H26="",AND(H26<>"",H26<>H25,H25<>"")),A25,A25+1))) -> 1 | B26: =IF(D26<>"",TEXT(D26,"YYYYMMDD")&CHAR(64+A26),"") | C26: =IF(OR(B26="",B26<>B25),1,C25+1) -> 1 | F26: Street Vendor | G26: Fried Chicken Seller | M26: =K26*L26 -> 0 | N26: =IF(B26=B25,N25+M26,M26) -> 0 | P26: =INDEX(Items!B$2:B$1032,MATCH($O26,Items!$A$2:$A$1032,0)) -> #N/A | Q26: =INDEX(Items!C$2:C$1032,MATCH($O26,Items!$A$2:$A$1032,0)) -> #N/A | R26: =INDEX(Items!D$2:D$1032,MATCH($O26,Items!$A$2:$A$1032,0)) -> #N/A
A27: =IF(OR(D27<>D26,D27=""),1,IF(NOT(AND(E27=E26,F27=F26,G27=G26)),A26+1,IF(OR(H27="",AND(H27<>"",H27<>H26,H26<>"")),A26,A26+1))) -> 1 | B27: =IF(D27<>"",TEXT(D27,"YYYYMMDD")&CHAR(64+A27),"") | C27: =IF(OR(B27="",B27<>B26),1,C26+1) -> 1 | F27: Street Vendor | G27: Fried Chicken Seller | M27: =K27*L27 -> 0 | N27: =IF(B27=B26,N26+M27,M27) -> 0 | P27: =INDEX(Items!B$2:B$1032,MATCH($O27,Items!$A$2:$A$1032,0)) -> #N/A | Q27: =INDEX(Items!C$2:C$1032,MATCH($O27,Items!$A$2:$A$1032,0)) -> #N/A | R27: =INDEX(Items!D$2:D$1032,MATCH($O27,Items!$A$2:$A$1032,0)) -> #N/A
A28: =IF(OR(D28<>D27,D28=""),1,IF(NOT(AND(E28=E27,F28=F27,G28=G27)),A27+1,IF(OR(H28="",AND(H28<>"",H28<>H27,H27<>"")),A27,A27+1))) -> 1 | B28: =IF(D28<>"",TEXT(D28,"YYYYMMDD")&CHAR(64+A28),"") | C28: =IF(OR(B28="",B28<>B27),1,C27+1) -> 1 | F28: Street Vendor | G28: Fried Chicken Seller | M28: =K28*L28 -> 0 | N28: =IF(B28=B27,N27+M28,M28) -> 0 | P28: =INDEX(Items!B$2:B$1032,MATCH($O28,Items!$A$2:$A$1032,0)) -> #N/A | Q28: =INDEX(Items!C$2:C$1032,MATCH($O28,Items!$A$2:$A$1032,0)) -> #N/A | R28: =INDEX(Items!D$2:D$1032,MATCH($O28,Items!$A$2:$A$1032,0)) -> #N/A
A29: =IF(OR(D29<>D28,D29=""),1,IF(NOT(AND(E29=E28,F29=F28,G29=G28)),A28+1,IF(OR(H29="",AND(H29<>"",H29<>H28,H28<>"")),A28,A28+1))) -> 1 | B29: =IF(D29<>"",TEXT(D29,"YYYYMMDD")&CHAR(64+A29),"") | C29: =IF(OR(B29="",B29<>B28),1,C28+1) -> 1 | F29: =INDEX(Establishment!B$2:B$1005,MATCH($E29,Establishment!$A$2:$A$1005,0)) -> #N/A | G29: =INDEX(Establishment!C$2:C$1005,MATCH($E29,Establishment!$A$2:$A$1005,0)) -> #N/A | M29: =K29*L29 -> 0 | N29: =IF(B29=B28,N28+M29,M29) -> 0 | P29: =INDEX(Items!B$2:B$1032,MATCH($O29,Items!$A$2:$A$1032,0)) -> #N/A | Q29: =INDEX(Items!C$2:C$1032,MATCH($O29,Items!$A$2:$A$1032,0)) -> #N/A | R29: =INDEX(Items!D$2:D$1032,MATCH($O29,Items!$A$2:$A$1032,0)) -> #N/A
A30: =IF(OR(D30<>D29,D30=""),1,IF(NOT(AND(E30=E29,F30=F29,G30=G29)),A29+1,IF(OR(H30="",AND(H30<>"",H30<>H29,H29<>"")),A29,A29+1))) -> 1 | B30: =IF(D30<>"",TEXT(D30,"YYYYMMDD")&CHAR(64+A30),"") | C30: =IF(OR(B30="",B30<>B29),1,C29+1) -> 1 | F30: =INDEX(Establishment!B$2:B$1005,MATCH($E30,Establishment!$A$2:$A$1005,0)) -> #N/A | G30: =INDEX(Establishment!C$2:C$1005,MATCH($E30,Establishment!$A$2:$A$1005,0)) -> #N/A | M30: =K30*L30 -> 0 | N30: =IF(B30=B29,N29+M30,M30) -> 0 | P30: =INDEX(Items!B$2:B$1032,MATCH($O30,Items!$A$2:$A$1032,0)) -> #N/A | Q30: =INDEX(Items!C$2:C$1032,MATCH($O30,Items!$A$2:$A$1032,0)) -> #N/A | R30: =INDEX(Items!D$2:D$1032,MATCH($O30,Items!$A$2:$A$1032,0)) -> #N/A
A31: =IF(OR(D31<>D30,D31=""),1,IF(NOT(AND(E31=E30,F31=F30,G31=G30)),A30+1,IF(OR(H31="",AND(H31<>"",H31<>H30,H30<>"")),A30,A30+1))) -> 1 | B31: =IF(D31<>"",TEXT(D31,"YYYYMMDD")&CHAR(64+A31),"") | C31: =IF(OR(B31="",B31<>B30),1,C30+1) -> 1 | F31: =INDEX(Establishment!B$2:B$1005,MATCH($E31,Establishment!$A$2:$A$1005,0)) -> #N/A | G31: =INDEX(Establishment!C$2:C$1005,MATCH($E31,Establishment!$A$2:$A$1005,0)) -> #N/A | M31: =K31*L31 -> 0 | N31: =IF(B31=B30,N30+M31,M31) -> 0 | P31: =INDEX(Items!B$2:B$1032,MATCH($O31,Items!$A$2:$A$1032,0)) -> #N/A | Q31: =INDEX(Items!C$2:C$1032,MATCH($O31,Items!$A$2:$A$1032,0)) -> #N/A | R31: =INDEX(Items!D$2:D$1032,MATCH($O31,Items!$A$2:$A$1032,0)) -> #N/A
A32: =IF(OR(D32<>D31,D32=""),1,IF(NOT(AND(E32=E31,F32=F31,G32=G31)),A31+1,IF(OR(H32="",AND(H32<>"",H32<>H31,H31<>"")),A31,A31+1))) -> 1 | B32: =IF(D32<>"",TEXT(D32,"YYYYMMDD")&CHAR(64+A32),"") | C32: =IF(OR(B32="",B32<>B31),1,C31+1) -> 1 | F32: Street Vendor | G32: B. Rodriguez | M32: =K32*L32 -> 0 | N32: =IF(B32=B31,N31+M32,M32) -> 0 | P32: =INDEX(Items!B$2:B$1032,MATCH($O32,Items!$A$2:$A$1032,0)) -> #N/A | Q32: =INDEX(Items!C$2:C$1032,MATCH($O32,Items!$A$2:$A$1032,0)) -> #N/A | R32: =INDEX(Items!D$2:D$1032,MATCH($O32,Items!$A$2:$A$1032,0)) -> #N/A
A33: =IF(OR(D33<>D32,D33=""),1,IF(NOT(AND(E33=E32,F33=F32,G33=G32)),A32+1,IF(OR(H33="",AND(H33<>"",H33<>H32,H32<>"")),A32,A32+1))) -> 1 | B33: =IF(D33<>"",TEXT(D33,"YYYYMMDD")&CHAR(64+A33),"") | C33: =IF(OR(B33="",B33<>B32),1,C32+1) -> 1 | F33: Street Vendor | G33: B. Rodriguez | M33: =K33*L33 -> 0 | N33: =IF(B33=B32,N32+M33,M33) -> 0 | P33: =INDEX(Items!B$2:B$1032,MATCH($O33,Items!$A$2:$A$1032,0)) -> #N/A | Q33: =INDEX(Items!C$2:C$1032,MATCH($O33,Items!$A$2:$A$1032,0)) -> #N/A | R33: =INDEX(Items!D$2:D$1032,MATCH($O33,Items!$A$2:$A$1032,0)) -> #N/A
A34: =IF(OR(D34<>D33,D34=""),1,IF(NOT(AND(E34=E33,F34=F33,G34=G33)),A33+1,IF(OR(H34="",AND(H34<>"",H34<>H33,H33<>"")),A33,A33+1))) -> 1 | B34: =IF(D34<>"",TEXT(D34,"YYYYMMDD")&CHAR(64+A34),"") | C34: =IF(OR(B34="",B34<>B33),1,C33+1) -> 1 | F34: Street Vendor | G34: B. Rodriguez | M34: =K34*L34 -> 0 | N34: =IF(B34=B33,N33+M34,M34) -> 0 | P34: =INDEX(Items!B$2:B$1032,MATCH($O34,Items!$A$2:$A$1032,0)) -> #N/A | Q34: =INDEX(Items!C$2:C$1032,MATCH($O34,Items!$A$2:$A$1032,0)) -> #N/A | R34: =INDEX(Items!D$2:D$1032,MATCH($O34,Items!$A$2:$A$1032,0)) -> #N/A
A35: =IF(OR(D35<>D34,D35=""),1,IF(NOT(AND(E35=E34,F35=F34,G35=G34)),A34+1,IF(OR(H35="",AND(H35<>"",H35<>H34,H34<>"")),A34,A34+1))) -> 1 | B35: =IF(D35<>"",TEXT(D35,"YYYYMMDD")&CHAR(64+A35),"") | C35: =IF(OR(B35="",B35<>B34),1,C34+1) -> 1 | F35: Street Vendor | G35: B. Rodriguez | M35: =K35*L35 -> 0 | N35: =IF(B35=B34,N34+M35,M35) -> 0 | P35: =INDEX(Items!B$2:B$1032,MATCH($O35,Items!$A$2:$A$1032,0)) -> #N/A | Q35: =INDEX(Items!C$2:C$1032,MATCH($O35,Items!$A$2:$A$1032,0)) -> #N/A | R35: =INDEX(Items!D$2:D$1032,MATCH($O35,Items!$A$2:$A$1032,0)) -> #N/A
A36: =IF(OR(D36<>D35,D36=""),1,IF(NOT(AND(E36=E35,F36=F35,G36=G35)),A35+1,IF(OR(H36="",AND(H36<>"",H36<>H35,H35<>"")),A35,A35+1))) -> 1 | B36: =IF(D36<>"",TEXT(D36,"YYYYMMDD")&CHAR(64+A36),"") | C36: =IF(OR(B36="",B36<>B35),1,C35+1) -> 1 | F36: Carenderia | G36: B. Rodriguez | M36: =K36*L36 -> 0 | N36: =IF(B36=B35,N35+M36,M36) -> 0 | P36: =INDEX(Items!B$2:B$1032,MATCH($O36,Items!$A$2:$A$1032,0)) -> #N/A | Q36: =INDEX(Items!C$2:C$1032,MATCH($O36,Items!$A$2:$A$1032,0)) -> #N/A | R36: =INDEX(Items!D$2:D$1032,MATCH($O36,Items!$A$2:$A$1032,0)) -> #N/A
A37: =IF(OR(D37<>D36,D37=""),1,IF(NOT(AND(E37=E36,F37=F36,G37=G36)),A36+1,IF(OR(H37="",AND(H37<>"",H37<>H36,H36<>"")),A36,A36+1))) -> 1 | B37: =IF(D37<>"",TEXT(D37,"YYYYMMDD")&CHAR(64+A37),"") | C37: =IF(OR(B37="",B37<>B36),1,C36+1) -> 1 | F37: Carenderia | G37: B. Rodriguez | M37: =K37*L37 -> 0 | N37: =IF(B37=B36,N36+M37,M37) -> 0 | P37: =INDEX(Items!B$2:B$1032,MATCH($O37,Items!$A$2:$A$1032,0)) -> #N/A | Q37: =INDEX(Items!C$2:C$1032,MATCH($O37,Items!$A$2:$A$1032,0)) -> #N/A | R37: =INDEX(Items!D$2:D$1032,MATCH($O37,Items!$A$2:$A$1032,0)) -> #N/A
A38: =IF(OR(D38<>D37,D38=""),1,IF(NOT(AND(E38=E37,F38=F37,G38=G37)),A37+1,IF(OR(H38="",AND(H38<>"",H38<>H37,H37<>"")),A37,A37+1))) -> 1 | B38: =IF(D38<>"",TEXT(D38,"YYYYMMDD")&CHAR(64+A38),"") | C38: =IF(OR(B38="",B38<>B37),1,C37+1) -> 1 | F38: Carenderia | G38: B. Rodriguez | M38: =K38*L38 -> 0 | N38: =IF(B38=B37,N37+M38,M38) -> 0 | P38: =INDEX(Items!B$2:B$1032,MATCH($O38,Items!$A$2:$A$1032,0)) -> #N/A | Q38: =INDEX(Items!C$2:C$1032,MATCH($O38,Items!$A$2:$A$1032,0)) -> #N/A | R38: =INDEX(Items!D$2:D$1032,MATCH($O38,Items!$A$2:$A$1032,0)) -> #N/A
A39: =IF(OR(D39<>D38,D39=""),1,IF(NOT(AND(E39=E38,F39=F38,G39=G38)),A38+1,IF(OR(H39="",AND(H39<>"",H39<>H38,H38<>"")),A38,A38+1))) -> 1 | B39: =IF(D39<>"",TEXT(D39,"YYYYMMDD")&CHAR(64+A39),"") | C39: =IF(OR(B39="",B39<>B38),1,C38+1) -> 1 | F39: Carenderia | G39: B. Rodriguez | M39: =K39*L39 -> 0 | N39: =IF(B39=B38,N38+M39,M39) -> 0 | P39: =INDEX(Items!B$2:B$1032,MATCH($O39,Items!$A$2:$A$1032,0)) -> #N/A | Q39: =INDEX(Items!C$2:C$1032,MATCH($O39,Items!$A$2:$A$1032,0)) -> #N/A | R39: =INDEX(Items!D$2:D$1032,MATCH($O39,Items!$A$2:$A$1032,0)) -> #N/A
A40: =IF(OR(D40<>D39,D40=""),1,IF(NOT(AND(E40=E39,F40=F39,G40=G39)),A39+1,IF(OR(H40="",AND(H40<>"",H40<>H39,H39<>"")),A39,A39+1))) -> 1 | B40: =IF(D40<>"",TEXT(D40,"YYYYMMDD")&CHAR(64+A40),"") | C40: =IF(OR(B40="",B40<>B39),1,C39+1) -> 1 | F40: Carenderia | G40: B. Rodriguez | M40: =K40*L40 -> 0 | N40: =IF(B40=B39,N39+M40,M40) -> 0 | P40: =INDEX(Items!B$2:B$1032,MATCH($O40,Items!$A$2:$A$1032,0)) -> #N/A | Q40: =INDEX(Items!C$2:C$1032,MATCH($O40,Items!$A$2:$A$1032,0)) -> #N/A | R40: =INDEX(Items!D$2:D$1032,MATCH($O40,Items!$A$2:$A$1032,0)) -> #N/A
A41: =IF(OR(D41<>D40,D41=""),1,IF(NOT(AND(E41=E40,F41=F40,G41=G40)),A40+1,IF(OR(H41="",AND(H41<>"",H41<>H40,H40<>"")),A40,A40+1))) -> 1 | B41: =IF(D41<>"",TEXT(D41,"YYYYMMDD")&CHAR(64+A41),"") | C41: =IF(OR(B41="",B41<>B40),1,C40+1) -> 1 | F41: Carenderia | G41: B. Rodriguez | M41: =K41*L41 -> 0 | N41: =IF(B41=B40,N40+M41,M41) -> 0 | P41: =INDEX(Items!B$2:B$1032,MATCH($O41,Items!$A$2:$A$1032,0)) -> #N/A | Q41: =INDEX(Items!C$2:C$1032,MATCH($O41,Items!$A$2:$A$1032,0)) -> #N/A | R41: =INDEX(Items!D$2:D$1032,MATCH($O41,Items!$A$2:$A$1032,0)) -> #N/A
A42: =IF(OR(D42<>D41,D42=""),1,IF(NOT(AND(E42=E41,F42=F41,G42=G41)),A41+1,IF(OR(H42="",AND(H42<>"",H42<>H41,H41<>"")),A41,A41+1))) -> 1 | B42: =IF(D42<>"",TEXT(D42,"YYYYMMDD")&CHAR(64+A42),"") | C42: =IF(OR(B42="",B42<>B41),1,C41+1) -> 1 | F42: Carenderia | G42: B. Rodriguez | M42: =K42*L42 -> 0 | N42: =IF(B42=B41,N41+M42,M42) -> 0 | P42: =INDEX(Items!B$2:B$1032,MATCH($O42,Items!$A$2:$A$1032,0)) -> #N/A | Q42: =INDEX(Items!C$2:C$1032,MATCH($O42,Items!$A$2:$A$1032,0)) -> #N/A | R42: =INDEX(Items!D$2:D$1032,MATCH($O42,Items!$A$2:$A$1032,0)) -> #N/A
A43: =IF(OR(D43<>D42,D43=""),1,IF(NOT(AND(E43=E42,F43=F42,G43=G42)),A42+1,IF(OR(H43="",AND(H43<>"",H43<>H42,H42<>"")),A42,A42+1))) -> 1 | B43: =IF(D43<>"",TEXT(D43,"YYYYMMDD")&CHAR(64+A43),"") | C43: =IF(OR(B43="",B43<>B42),1,C42+1) -> 1 | F43: Carenderia | G43: B. Rodriguez | M43: =K43*L43 -> 0 | N43: =IF(B43=B42,N42+M43,M43) -> 0 | P43: =INDEX(Items!B$2:B$1032,MATCH($O43,Items!$A$2:$A$1032,0)) -> #N/A | Q43: =INDEX(Items!C$2:C$1032,MATCH($O43,Items!$A$2:$A$1032,0)) -> #N/A | R43: =INDEX(Items!D$2:D$1032,MATCH($O43,Items!$A$2:$A$1032,0)) -> #N/A
... A45: =IF(OR(D45<>D44,D45=""),1,IF(NOT(AND(E45=E44,F45=F44,G45=G44)),A44+1,IF(OR(H45="",AND(H45<>"",H45<>H44,H44<>"")),A44,A44+1))) -> 1 | B45: =IF(D45<>"",TEXT(D45,"YYYYMMDD")&CHAR(64+A45),"") | C45: =IF(OR(B45="",B45<>B44),1,C44+1) -> 1 | F45: Street Vendor | G45: Don Gil Garcia st. | M45: =K45*L45 -> 0 | N45: =IF(B45=B44,N44+M45,M45) -> 0 | P45: =INDEX(Items!B$2:B$1032,MATCH($O45,Items!$A$2:$A$1032,0)) -> #N/A | Q45: =INDEX(Items!C$2:C$1032,MATCH($O45,Items!$A$2:$A$1032,0)) -> #N/A | R45: =INDEX(Items!D$2:D$1032,MATCH($O45,Items!$A$2:$A$1032,0)) -> #N/A
A46: =IF(OR(D46<>D45,D46=""),1,IF(NOT(AND(E46=E45,F46=F45,G46=G45)),A45+1,IF(OR(H46="",AND(H46<>"",H46<>H45,H45<>"")),A45,A45+1))) -> 1 | B46: =IF(D46<>"",TEXT(D46,"YYYYMMDD")&CHAR(64+A46),"") | C46: =IF(OR(B46="",B46<>B45),1,C45+1) -> 1 | F46: =INDEX(Establishment!B$2:B$1005,MATCH($E46,Establishment!$A$2:$A$1005,0)) -> #N/A | G46: =INDEX(Establishment!C$2:C$1005,MATCH($E46,Establishment!$A$2:$A$1005,0)) -> #N/A | M46: =K46*L46 -> 0 | N46: =IF(B46=B45,N45+M46,M46) -> 0 | P46: =INDEX(Items!B$2:B$1032,MATCH($O46,Items!$A$2:$A$1032,0)) -> #N/A | Q46: =INDEX(Items!C$2:C$1032,MATCH($O46,Items!$A$2:$A$1032,0)) -> #N/A | R46: =INDEX(Items!D$2:D$1032,MATCH($O46,Items!$A$2:$A$1032,0)) -> #N/A
A47: =IF(OR(D47<>D46,D47=""),1,IF(NOT(AND(E47=E46,F47=F46,G47=G46)),A46+1,IF(OR(H47="",AND(H47<>"",H47<>H46,H46<>"")),A46,A46+1))) -> 1 | B47: =IF(D47<>"",TEXT(D47,"YYYYMMDD")&CHAR(64+A47),"") | C47: =IF(OR(B47="",B47<>B46),1,C46+1) -> 1 | F47: =INDEX(Establishment!B$2:B$1005,MATCH($E47,Establishment!$A$2:$A$1005,0)) -> #N/A | G47: =INDEX(Establishment!C$2:C$1005,MATCH($E47,Establishment!$A$2:$A$1005,0)) -> #N/A | M47: =K47*L47 -> 0 | N47: =IF(B47=B46,N46+M47,M47) -> 0 | P47: =INDEX(Items!B$2:B$1032,MATCH($O47,Items!$A$2:$A$1032,0)) -> #N/A | Q47: =INDEX(Items!C$2:C$1032,MATCH($O47,Items!$A$2:$A$1032,0)) -> #N/A | R47: =INDEX(Items!D$2:D$1032,MATCH($O47,Items!$A$2:$A$1032,0)) -> #N/A
A48: =IF(OR(D48<>D47,D48=""),1,IF(NOT(AND(E48=E47,F48=F47,G48=G47)),A47+1,IF(OR(H48="",AND(H48<>"",H48<>H47,H47<>"")),A47,A47+1))) -> 1 | B48: =IF(D48<>"",TEXT(D48,"YYYYMMDD")&CHAR(64+A48),"") | C48: =IF(OR(B48="",B48<>B47),1,C47+1) -> 1 | F48: =INDEX(Establishment!B$2:B$1005,MATCH($E48,Establishment!$A$2:$A$1005,0)) -> #N/A | G48: =INDEX(Establishment!C$2:C$1005,MATCH($E48,Establishment!$A$2:$A$1005,0)) -> #N/A | M48: =K48*L48 -> 0 | N48: =IF(B48=B47,N47+M48,M48) -> 0 | P48: =INDEX(Items!B$2:B$1032,MATCH($O48,Items!$A$2:$A$1032,0)) -> #N/A | Q48: =INDEX(Items!C$2:C$1032,MATCH($O48,Items!$A$2:$A$1032,0)) -> #N/A | R48: =INDEX(Items!D$2:D$1032,MATCH($O48,Items!$A$2:$A$1032,0)) -> #N/A
A49: =IF(OR(D49<>D48,D49=""),1,IF(NOT(AND(E49=E48,F49=F48,G49=G48)),A48+1,IF(OR(H49="",AND(H49<>"",H49<>H48,H48<>"")),A48,A48+1))) -> 1 | B49: =IF(D49<>"",TEXT(D49,"YYYYMMDD")&CHAR(64+A49),"") | C49: =IF(OR(B49="",B49<>B48),1,C48+1) -> 1 | F49: =INDEX(Establishment!B$2:B$1005,MATCH($E49,Establishment!$A$2:$A$1005,0)) -> #N/A | G49: =INDEX(Establishment!C$2:C$1005,MATCH($E49,Establishment!$A$2:$A$1005,0)) -> #N/A | M49: =K49*L49 -> 0 | N49: =IF(B49=B48,N48+M49,M49) -> 0 | P49: =INDEX(Items!B$2:B$1032,MATCH($O49,Items!$A$2:$A$1032,0)) -> #N/A | Q49: =INDEX(Items!C$2:C$1032,MATCH($O49,Items!$A$2:$A$1032,0)) -> #N/A | R49: =INDEX(Items!D$2:D$1032,MATCH($O49,Items!$A$2:$A$1032,0)) -> #N/A
A50: =IF(OR(D50<>D49,D50=""),1,IF(NOT(AND(E50=E49,F50=F49,G50=G49)),A49+1,IF(OR(H50="",AND(H50<>"",H50<>H49,H49<>"")),A49,A49+1))) -> 1 | B50: =IF(D50<>"",TEXT(D50,"YYYYMMDD")&CHAR(64+A50),"") | C50: =IF(OR(B50="",B50<>B49),1,C49+1) -> 1 | F50: =INDEX(Establishment!B$2:B$1005,MATCH($E50,Establishment!$A$2:$A$1005,0)) -> #N/A | G50: =INDEX(Establishment!C$2:C$1005,MATCH($E50,Establishment!$A$2:$A$1005,0)) -> #N/A | M50: =K50*L50 -> 0 | N50: =IF(B50=B49,N49+M50,M50) -> 0 | P50: =INDEX(Items!B$2:B$1032,MATCH($O50,Items!$A$2:$A$1032,0)) -> #N/A | Q50: =INDEX(Items!C$2:C$1032,MATCH($O50,Items!$A$2:$A$1032,0)) -> #N/A | R50: =INDEX(Items!D$2:D$1032,MATCH($O50,Items!$A$2:$A$1032,0)) -> #N/A
A51: =IF(OR(D51<>D50,D51=""),1,IF(NOT(AND(E51=E50,F51=F50,G51=G50)),A50+1,IF(OR(H51="",AND(H51<>"",H51<>H50,H50<>"")),A50,A50+1))) -> 1 | B51: =IF(D51<>"",TEXT(D51,"YYYYMMDD")&CHAR(64+A51),"") | C51: =IF(OR(B51="",B51<>B50),1,C50+1) -> 1 | F51: =INDEX(Establishment!B$2:B$1005,MATCH($E51,Establishment!$A$2:$A$1005,0)) -> #N/A | G51: =INDEX(Establishment!C$2:C$1005,MATCH($E51,Establishment!$A$2:$A$1005,0)) -> #N/A | M51: =K51*L51 -> 0 | N51: =IF(B51=B50,N50+M51,M51) -> 0 | P51: =INDEX(Items!B$2:B$1032,MATCH($O51,Items!$A$2:$A$1032,0)) -> #N/A | Q51: =INDEX(Items!C$2:C$1032,MATCH($O51,Items!$A$2:$A$1032,0)) -> #N/A | R51: =INDEX(Items!D$2:D$1032,MATCH($O51,Items!$A$2:$A$1032,0)) -> #N/A
A52: =IF(OR(D52<>D51,D52=""),1,IF(NOT(AND(E52=E51,F52=F51,G52=G51)),A51+1,IF(OR(H52="",AND(H52<>"",H52<>H51,H51<>"")),A51,A51+1))) -> 1 | B52: =IF(D52<>"",TEXT(D52,"YYYYMMDD")&CHAR(64+A52),"") | C52: =IF(OR(B52="",B52<>B51),1,C51+1) -> 1 | F52: =INDEX(Establishment!B$2:B$1005,MATCH($E52,Establishment!$A$2:$A$1005,0)) -> #N/A | G52: =INDEX(Establishment!C$2:C$1005,MATCH($E52,Establishment!$A$2:$A$1005,0)) -> #N/A | M52: =K52*L52 -> 0 | N52: =IF(B52=B51,N51+M52,M52) -> 0 | P52: =INDEX(Items!B$2:B$1032,MATCH($O52,Items!$A$2:$A$1032,0)) -> #N/A | Q52: =INDEX(Items!C$2:C$1032,MATCH($O52,Items!$A$2:$A$1032,0)) -> #N/A | R52: =INDEX(Items!D$2:D$1032,MATCH($O52,Items!$A$2:$A$1032,0)) -> #N/A
A53: =IF(OR(D53<>D52,D53=""),1,IF(NOT(AND(E53=E52,F53=F52,G53=G52)),A52+1,IF(OR(H53="",AND(H53<>"",H53<>H52,H52<>"")),A52,A52+1))) -> 1 | B53: =IF(D53<>"",TEXT(D53,"YYYYMMDD")&CHAR(64+A53),"") | C53: =IF(OR(B53="",B53<>B52),1,C52+1) -> 1 | F53: =INDEX(Establishment!B$2:B$1005,MATCH($E53,Establishment!$A$2:$A$1005,0)) -> #N/A | G53: =INDEX(Establishment!C$2:C$1005,MATCH($E53,Establishment!$A$2:$A$1005,0)) -> #N/A | M53: =K53*L53 -> 0 | N53: =IF(B53=B52,N52+M53,M53) -> 0 | P53: =INDEX(Items!B$2:B$1032,MATCH($O53,Items!$A$2:$A$1032,0)) -> #N/A | Q53: =INDEX(Items!C$2:C$1032,MATCH($O53,Items!$A$2:$A$1032,0)) -> #N/A | R53: =INDEX(Items!D$2:D$1032,MATCH($O53,Items!$A$2:$A$1032,0)) -> #N/A
A54: =IF(OR(D54<>D53,D54=""),1,IF(NOT(AND(E54=E53,F54=F53,G54=G53)),A53+1,IF(OR(H54="",AND(H54<>"",H54<>H53,H53<>"")),A53,A53+1))) -> 1 | B54: =IF(D54<>"",TEXT(D54,"YYYYMMDD")&CHAR(64+A54),"") | C54: =IF(OR(B54="",B54<>B53),1,C53+1) -> 1 | F54: =INDEX(Establishment!B$2:B$1005,MATCH($E54,Establishment!$A$2:$A$1005,0)) -> #N/A | G54: =INDEX(Establishment!C$2:C$1005,MATCH($E54,Establishment!$A$2:$A$1005,0)) -> #N/A | M54: =K54*L54 -> 0 | N54: =IF(B54=B53,N53+M54,M54) -> 0 | P54: =INDEX(Items!B$2:B$1032,MATCH($O54,Items!$A$2:$A$1032,0)) -> #N/A | Q54: =INDEX(Items!C$2:C$1032,MATCH($O54,Items!$A$2:$A$1032,0)) -> #N/A | R54: =INDEX(Items!D$2:D$1032,MATCH($O54,Items!$A$2:$A$1032,0)) -> #N/A
A55: =IF(OR(D55<>D54,D55=""),1,IF(NOT(AND(E55=E54,F55=F54,G55=G54)),A54+1,IF(OR(H55="",AND(H55<>"",H55<>H54,H54<>"")),A54,A54+1))) -> 1 | B55: =IF(D55<>"",TEXT(D55,"YYYYMMDD")&CHAR(64+A55),"") | C55: =IF(OR(B55="",B55<>B54),1,C54+1) -> 1 | F55: =INDEX(Establishment!B$2:B$1005,MATCH($E55,Establishment!$A$2:$A$1005,0)) -> #N/A | G55: =INDEX(Establishment!C$2:C$1005,MATCH($E55,Establishment!$A$2:$A$1005,0)) -> #N/A | M55: =K55*L55 -> 0 | N55: =IF(B55=B54,N54+M55,M55) -> 0 | P55: =INDEX(Items!B$2:B$1032,MATCH($O55,Items!$A$2:$A$1032,0)) -> #N/A | Q55: =INDEX(Items!C$2:C$1032,MATCH($O55,Items!$A$2:$A$1032,0)) -> #N/A | R55: =INDEX(Items!D$2:D$1032,MATCH($O55,Items!$A$2:$A$1032,0)) -> #N/A
A56: =IF(OR(D56<>D55,D56=""),1,IF(NOT(AND(E56=E55,F56=F55,G56=G55)),A55+1,IF(OR(H56="",AND(H56<>"",H56<>H55,H55<>"")),A55,A55+1))) -> 1 | B56: =IF(D56<>"",TEXT(D56,"YYYYMMDD")&CHAR(64+A56),"") | C56: =IF(OR(B56="",B56<>B55),1,C55+1) -> 1 | F56: =INDEX(Establishment!B$2:B$1005,MATCH($E56,Establishment!$A$2:$A$1005,0)) -> #N/A | G56: =INDEX(Establishment!C$2:C$1005,MATCH($E56,Establishment!$A$2:$A$1005,0)) -> #N/A | M56: =K56*L56 -> 0 | N56: =IF(B56=B55,N55+M56,M56) -> 0 | P56: =INDEX(Items!B$2:B$1032,MATCH($O56,Items!$A$2:$A$1032,0)) -> #N/A | Q56: =INDEX(Items!C$2:C$1032,MATCH($O56,Items!$A$2:$A$1032,0)) -> #N/A | R56: =INDEX(Items!D$2:D$1032,MATCH($O56,Items!$A$2:$A$1032,0)) -> #N/A
A57: =IF(OR(D57<>D56,D57=""),1,IF(NOT(AND(E57=E56,F57=F56,G57=G56)),A56+1,IF(OR(H57="",AND(H57<>"",H57<>H56,H56<>"")),A56,A56+1))) -> 1 | B57: =IF(D57<>"",TEXT(D57,"YYYYMMDD")&CHAR(64+A57),"") | C57: =IF(OR(B57="",B57<>B56),1,C56+1) -> 1 | F57: =INDEX(Establishment!B$2:B$1005,MATCH($E57,Establishment!$A$2:$A$1005,0)) -> #N/A | G57: =INDEX(Establishment!C$2:C$1005,MATCH($E57,Establishment!$A$2:$A$1005,0)) -> #N/A | M57: =K57*L57 -> 0 | N57: =IF(B57=B56,N56+M57,M57) -> 0 | P57: =INDEX(Items!B$2:B$1032,MATCH($O57,Items!$A$2:$A$1032,0)) -> #N/A | Q57: =INDEX(Items!C$2:C$1032,MATCH($O57,Items!$A$2:$A$1032,0)) -> #N/A | R57: =INDEX(Items!D$2:D$1032,MATCH($O57,Items!$A$2:$A$1032,0)) -> #N/A
... A66: =IF(OR(D66<>D65,D66=""),1,IF(NOT(AND(E66=E65,F66=F65,G66=G65)),A65+1,IF(OR(H66="",AND(H66<>"",H66<>H65,H65<>"")),A65,A65+1))) -> 1 | B66: =IF(D66<>"",TEXT(D66,"YYYYMMDD")&CHAR(64+A66),"") | C66: =IF(OR(B66="",B66<>B65),1,C65+1) -> 1 | F66: =INDEX(Establishment!B$2:B$1005,MATCH($E66,Establishment!$A$2:$A$1005,0)) -> #N/A | G66: =INDEX(Establishment!C$2:C$1005,MATCH($E66,Establishment!$A$2:$A$1005,0)) -> #N/A | M66: =K66*L66 -> 0 | N66: =IF(B66=B65,N65+M66,M66) -> 0 | P66: =INDEX(Items!B$2:B$1032,MATCH($O66,Items!$A$2:$A$1032,0)) -> #N/A | Q66: =INDEX(Items!C$2:C$1032,MATCH($O66,Items!$A$2:$A$1032,0)) -> #N/A | R66: =INDEX(Items!D$2:D$1032,MATCH($O66,Items!$A$2:$A$1032,0)) -> #N/A
A67: =IF(OR(D67<>D66,D67=""),1,IF(NOT(AND(E67=E66,F67=F66,G67=G66)),A66+1,IF(OR(H67="",AND(H67<>"",H67<>H66,H66<>"")),A66,A66+1))) -> 1 | B67: =IF(D67<>"",TEXT(D67,"YYYYMMDD")&CHAR(64+A67),"") | C67: =IF(OR(B67="",B67<>B66),1,C66+1) -> 1 | F67: Street Vendor | G67: B. Rodriguez | M67: =K67*L67 -> 0 | N67: =IF(B67=B66,N66+M67,M67) -> 0 | P67: =INDEX(Items!B$2:B$1032,MATCH($O67,Items!$A$2:$A$1032,0)) -> #N/A | Q67: =INDEX(Items!C$2:C$1032,MATCH($O67,Items!$A$2:$A$1032,0)) -> #N/A | R67: =INDEX(Items!D$2:D$1032,MATCH($O67,Items!$A$2:$A$1032,0)) -> #N/A
A68: =IF(OR(D68<>D67,D68=""),1,IF(NOT(AND(E68=E67,F68=F67,G68=G67)),A67+1,IF(OR(H68="",AND(H68<>"",H68<>H67,H67<>"")),A67,A67+1))) -> 1 | B68: =IF(D68<>"",TEXT(D68,"YYYYMMDD")&CHAR(64+A68),"") | C68: =IF(OR(B68="",B68<>B67),1,C67+1) -> 1 | F68: Street Vendor | G68: B. Rodriguez | M68: =K68*L68 -> 0 | N68: =IF(B68=B67,N67+M68,M68) -> 0 | P68: =INDEX(Items!B$2:B$1032,MATCH($O68,Items!$A$2:$A$1032,0)) -> #N/A | Q68: =INDEX(Items!C$2:C$1032,MATCH($O68,Items!$A$2:$A$1032,0)) -> #N/A | R68: =INDEX(Items!D$2:D$1032,MATCH($O68,Items!$A$2:$A$1032,0)) -> #N/A
A69: =IF(OR(D69<>D68,D69=""),1,IF(NOT(AND(E69=E68,F69=F68,G69=G68)),A68+1,IF(OR(H69="",AND(H69<>"",H69<>H68,H68<>"")),A68,A68+1))) -> 1 | B69: =IF(D69<>"",TEXT(D69,"YYYYMMDD")&CHAR(64+A69),"") | C69: =IF(OR(B69="",B69<>B68),1,C68+1) -> 1 | F69: Street Vendor | G69: B. Rodriguez | M69: =K69*L69 -> 0 | N69: =IF(B69=B68,N68+M69,M69) -> 0 | P69: =INDEX(Items!B$2:B$1032,MATCH($O69,Items!$A$2:$A$1032,0)) -> #N/A | Q69: =INDEX(Items!C$2:C$1032,MATCH($O69,Items!$A$2:$A$1032,0)) -> #N/A | R69: =INDEX(Items!D$2:D$1032,MATCH($O69,Items!$A$2:$A$1032,0)) -> #N/A
A70: =IF(OR(D70<>D69,D70=""),1,IF(NOT(AND(E70=E69,F70=F69,G70=G69)),A69+1,IF(OR(H70="",AND(H70<>"",H70<>H69,H69<>"")),A69,A69+1))) -> 1 | B70: =IF(D70<>"",TEXT(D70,"YYYYMMDD")&CHAR(64+A70),"") | C70: =IF(OR(B70="",B70<>B69),1,C69+1) -> 1 | F70: Street Vendor | G70: B. Rodriguez | M70: =K70*L70 -> 0 | N70: =IF(B70=B69,N69+M70,M70) -> 0 | P70: =INDEX(Items!B$2:B$1032,MATCH($O70,Items!$A$2:$A$1032,0)) -> #N/A | Q70: =INDEX(Items!C$2:C$1032,MATCH($O70,Items!$A$2:$A$1032,0)) -> #N/A | R70: =INDEX(Items!D$2:D$1032,MATCH($O70,Items!$A$2:$A$1032,0)) -> #N/A
A71: =IF(OR(D71<>D70,D71=""),1,IF(NOT(AND(E71=E70,F71=F70,G71=G70)),A70+1,IF(OR(H71="",AND(H71<>"",H71<>H70,H70<>"")),A70,A70+1))) -> 1 | B71: =IF(D71<>"",TEXT(D71,"YYYYMMDD")&CHAR(64+A71),"") | C71: =IF(OR(B71="",B71<>B70),1,C70+1) -> 1 | F71: Street Vendor | G71: B. Rodriguez | M71: =K71*L71 -> 0 | N71: =IF(B71=B70,N70+M71,M71) -> 0 | P71: =INDEX(Items!B$2:B$1032,MATCH($O71,Items!$A$2:$A$1032,0)) -> #N/A | Q71: =INDEX(Items!C$2:C$1032,MATCH($O71,Items!$A$2:$A$1032,0)) -> #N/A | R71: =INDEX(Items!D$2:D$1032,MATCH($O71,Items!$A$2:$A$1032,0)) -> #N/A
A72: =IF(OR(D72<>D71,D72=""),1,IF(NOT(AND(E72=E71,F72=F71,G72=G71)),A71+1,IF(OR(H72="",AND(H72<>"",H72<>H71,H71<>"")),A71,A71+1))) -> 1 | B72: =IF(D72<>"",TEXT(D72,"YYYYMMDD")&CHAR(64+A72),"") | C72: =IF(OR(B72="",B72<>B71),1,C71+1) -> 1 | F72: Massage | G72: Don Gil Garcia st. | M72: =K72*L72 -> 0 | N72: =IF(B72=B71,N71+M72,M72) -> 0 | P72: =INDEX(Items!B$2:B$1032,MATCH($O72,Items!$A$2:$A$1032,0)) -> #N/A | Q72: =INDEX(Items!C$2:C$1032,MATCH($O72,Items!$A$2:$A$1032,0)) -> #N/A | R72: =INDEX(Items!D$2:D$1032,MATCH($O72,Items!$A$2:$A$1032,0)) -> #N/A
A73: =IF(OR(D73<>D72,D73=""),1,IF(NOT(AND(E73=E72,F73=F72,G73=G72)),A72+1,IF(OR(H73="",AND(H73<>"",H73<>H72,H72<>"")),A72,A72+1))) -> 1 | B73: =IF(D73<>"",TEXT(D73,"YYYYMMDD")&CHAR(64+A73),"") | C73: =IF(OR(B73="",B73<>B72),1,C72+1) -> 1 | F73: Massage | G73: Don Gil Garcia st. | M73: =K73*L73 -> 0 | N73: =IF(B73=B72,N72+M73,M73) -> 0 | P73: =INDEX(Items!B$2:B$1032,MATCH($O73,Items!$A$2:$A$1032,0)) -> #N/A | Q73: =INDEX(Items!C$2:C$1032,MATCH($O73,Items!$A$2:$A$1032,0)) -> #N/A | R73: =INDEX(Items!D$2:D$1032,MATCH($O73,Items!$A$2:$A$1032,0)) -> #N/A
A74: =IF(OR(D74<>D73,D74=""),1,IF(NOT(AND(E74=E73,F74=F73,G74=G73)),A73+1,IF(OR(H74="",AND(H74<>"",H74<>H73,H73<>"")),A73,A73+1))) -> 1 | B74: =IF(D74<>"",TEXT(D74,"YYYYMMDD")&CHAR(64+A74),"") | C74: =IF(OR(B74="",B74<>B73),1,C73+1) -> 1 | F74: Street Vendor | G74: Don Gil Garcia st. | M74: =K74*L74 -> 0 | N74: =IF(B74=B73,N73+M74,M74) -> 0 | P74: =INDEX(Items!B$2:B$1032,MATCH($O74,Items!$A$2:$A$1032,0)) -> #N/A | Q74: =INDEX(Items!C$2:C$1032,MATCH($O74,Items!$A$2:$A$1032,0)) -> #N/A | R74: =INDEX(Items!D$2:D$1032,MATCH($O74,Items!$A$2:$A$1032,0)) -> #N/A
A75: =IF(OR(D75<>D74,D75=""),1,IF(NOT(AND(E75=E74,F75=F74,G75=G74)),A74+1,IF(OR(H75="",AND(H75<>"",H75<>H74,H74<>"")),A74,A74+1))) -> 1 | B75: =IF(D75<>"",TEXT(D75,"YYYYMMDD")&CHAR(64+A75),"") | C75: =IF(OR(B75="",B75<>B74),1,C74+1) -> 1 | F75: Street Vendor | G75: Don Gil Garcia st. | M75: =K75*L75 -> 0 | N75: =IF(B75=B74,N74+M75,M75) -> 0 | P75: =INDEX(Items!B$2:B$1032,MATCH($O75,Items!$A$2:$A$1032,0)) -> #N/A | Q75: =INDEX(Items!C$2:C$1032,MATCH($O75,Items!$A$2:$A$1032,0)) -> #N/A | R75: =INDEX(Items!D$2:D$1032,MATCH($O75,Items!$A$2:$A$1032,0)) -> #N/A
A76: =IF(OR(D76<>D75,D76=""),1,IF(NOT(AND(E76=E75,F76=F75,G76=G75)),A75+1,IF(OR(H76="",AND(H76<>"",H76<>H75,H75<>"")),A75,A75+1))) -> 1 | B76: =IF(D76<>"",TEXT(D76,"YYYYMMDD")&CHAR(64+A76),"") | C76: =IF(OR(B76="",B76<>B75),1,C75+1) -> 1 | F76: Street Vendor | G76: Don Gil Garcia st. | M76: =K76*L76 -> 0 | N76: =IF(B76=B75,N75+M76,M76) -> 0 | P76: =INDEX(Items!B$2:B$1032,MATCH($O76,Items!$A$2:$A$1032,0)) -> #N/A | Q76: =INDEX(Items!C$2:C$1032,MATCH($O76,Items!$A$2:$A$1032,0)) -> #N/A | R76: =INDEX(Items!D$2:D$1032,MATCH($O76,Items!$A$2:$A$1032,0)) -> #N/A
A77: =IF(OR(D77<>D76,D77=""),1,IF(NOT(AND(E77=E76,F77=F76,G77=G76)),A76+1,IF(OR(H77="",AND(H77<>"",H77<>H76,H76<>"")),A76,A76+1))) -> 1 | B77: =IF(D77<>"",TEXT(D77,"YYYYMMDD")&CHAR(64+A77),"") | C77: =IF(OR(B77="",B77<>B76),1,C76+1) -> 1 | F77: Street Vendor | G77: Don Gil Garcia st. | M77: =K77*L77 -> 0 | N77: =IF(B77=B76,N76+M77,M77) -> 0 | P77: =INDEX(Items!B$2:B$1032,MATCH($O77,Items!$A$2:$A$1032,0)) -> #N/A | Q77: =INDEX(Items!C$2:C$1032,MATCH($O77,Items!$A$2:$A$1032,0)) -> #N/A | R77: =INDEX(Items!D$2:D$1032,MATCH($O77,Items!$A$2:$A$1032,0)) -> #N/A
A78: =IF(OR(D78<>D77,D78=""),1,IF(NOT(AND(E78=E77,F78=F77,G78=G77)),A77+1,IF(OR(H78="",AND(H78<>"",H78<>H77,H77<>"")),A77,A77+1))) -> 1 | B78: =IF(D78<>"",TEXT(D78,"YYYYMMDD")&CHAR(64+A78),"") | C78: =IF(OR(B78="",B78<>B77),1,C77+1) -> 1 | F78: Street Vendor | G78: Don Gil Garcia st. | M78: =K78*L78 -> 0 | N78: =IF(B78=B77,N77+M78,M78) -> 0 | P78: =INDEX(Items!B$2:B$1032,MATCH($O78,Items!$A$2:$A$1032,0)) -> #N/A | Q78: =INDEX(Items!C$2:C$1032,MATCH($O78,Items!$A$2:$A$1032,0)) -> #N/A | R78: =INDEX(Items!D$2:D$1032,MATCH($O78,Items!$A$2:$A$1032,0)) -> #N/A
... A82: =IF(OR(D82<>D81,D82=""),1,IF(NOT(AND(E82=E81,F82=F81,G82=G81)),A81+1,IF(OR(H82="",AND(H82<>"",H82<>H81,H81<>"")),A81,A81+1))) -> 1 | B82: =IF(D82<>"",TEXT(D82,"YYYYMMDD")&CHAR(64+A82),"") | C82: =IF(OR(B82="",B82<>B81),1,C81+1) -> 1 | F82: Street Vendor | G82: B. Rodriguez | M82: =K82*L82 -> 0 | N82: =IF(B82=B81,N81+M82,M82) -> 0 | P82: =INDEX(Items!B$2:B$1032,MATCH($O82,Items!$A$2:$A$1032,0)) -> #N/A | Q82: =INDEX(Items!C$2:C$1032,MATCH($O82,Items!$A$2:$A$1032,0)) -> #N/A | R82: =INDEX(Items!D$2:D$1032,MATCH($O82,Items!$A$2:$A$1032,0)) -> #N/A
A83: =IF(OR(D83<>D82,D83=""),1,IF(NOT(AND(E83=E82,F83=F82,G83=G82)),A82+1,IF(OR(H83="",AND(H83<>"",H83<>H82,H82<>"")),A82,A82+1))) -> 1 | B83: =IF(D83<>"",TEXT(D83,"YYYYMMDD")&CHAR(64+A83),"") | C83: =IF(OR(B83="",B83<>B82),1,C82+1) -> 1 | F83: =INDEX(Establishment!B$2:B$1005,MATCH($E83,Establishment!$A$2:$A$1005,0)) -> #N/A | G83: =INDEX(Establishment!C$2:C$1005,MATCH($E83,Establishment!$A$2:$A$1005,0)) -> #N/A | M83: =K83*L83 -> 0 | N83: =IF(B83=B82,N82+M83,M83) -> 0 | P83: =INDEX(Items!B$2:B$1032,MATCH($O83,Items!$A$2:$A$1032,0)) -> #N/A | Q83: =INDEX(Items!C$2:C$1032,MATCH($O83,Items!$A$2:$A$1032,0)) -> #N/A | R83: =INDEX(Items!D$2:D$1032,MATCH($O83,Items!$A$2:$A$1032,0)) -> #N/A
A84: =IF(OR(D84<>D83,D84=""),1,IF(NOT(AND(E84=E83,F84=F83,G84=G83)),A83+1,IF(OR(H84="",AND(H84<>"",H84<>H83,H83<>"")),A83,A83+1))) -> 1 | B84: =IF(D84<>"",TEXT(D84,"YYYYMMDD")&CHAR(64+A84),"") | C84: =IF(OR(B84="",B84<>B83),1,C83+1) -> 1 | F84: =INDEX(Establishment!B$2:B$1005,MATCH($E84,Establishment!$A$2:$A$1005,0)) -> #N/A | G84: =INDEX(Establishment!C$2:C$1005,MATCH($E84,Establishment!$A$2:$A$1005,0)) -> #N/A | M84: =K84*L84 -> 0 | N84: =IF(B84=B83,N83+M84,M84) -> 0 | P84: =INDEX(Items!B$2:B$1032,MATCH($O84,Items!$A$2:$A$1032,0)) -> #N/A | Q84: =INDEX(Items!C$2:C$1032,MATCH($O84,Items!$A$2:$A$1032,0)) -> #N/A | R84: =INDEX(Items!D$2:D$1032,MATCH($O84,Items!$A$2:$A$1032,0)) -> #N/A
A85: =IF(OR(D85<>D84,D85=""),1,IF(NOT(AND(E85=E84,F85=F84,G85=G84)),A84+1,IF(OR(H85="",AND(H85<>"",H85<>H84,H84<>"")),A84,A84+1))) -> 1 | B85: =IF(D85<>"",TEXT(D85,"YYYYMMDD")&CHAR(64+A85),"") | C85: =IF(OR(B85="",B85<>B84),1,C84+1) -> 1 | F85: =INDEX(Establishment!B$2:B$1005,MATCH($E85,Establishment!$A$2:$A$1005,0)) -> #N/A | G85: =INDEX(Establishment!C$2:C$1005,MATCH($E85,Establishment!$A$2:$A$1005,0)) -> #N/A | M85: =K85*L85 -> 0 | N85: =IF(B85=B84,N84+M85,M85) -> 0 | P85: =INDEX(Items!B$2:B$1032,MATCH($O85,Items!$A$2:$A$1032,0)) -> #N/A | Q85: =INDEX(Items!C$2:C$1032,MATCH($O85,Items!$A$2:$A$1032,0)) -> #N/A | R85: =INDEX(Items!D$2:D$1032,MATCH($O85,Items!$A$2:$A$1032,0)) -> #N/A
A86: =IF(OR(D86<>D85,D86=""),1,IF(NOT(AND(E86=E85,F86=F85,G86=G85)),A85+1,IF(OR(H86="",AND(H86<>"",H86<>H85,H85<>"")),A85,A85+1))) -> 1 | B86: =IF(D86<>"",TEXT(D86,"YYYYMMDD")&CHAR(64+A86),"") | C86: =IF(OR(B86="",B86<>B85),1,C85+1) -> 1 | F86: =INDEX(Establishment!B$2:B$1005,MATCH($E86,Establishment!$A$2:$A$1005,0)) -> #N/A | G86: =INDEX(Establishment!C$2:C$1005,MATCH($E86,Establishment!$A$2:$A$1005,0)) -> #N/A | M86: =K86*L86 -> 0 | N86: =IF(B86=B85,N85+M86,M86) -> 0 | P86: =INDEX(Items!B$2:B$1032,MATCH($O86,Items!$A$2:$A$1032,0)) -> #N/A | Q86: =INDEX(Items!C$2:C$1032,MATCH($O86,Items!$A$2:$A$1032,0)) -> #N/A | R86: =INDEX(Items!D$2:D$1032,MATCH($O86,Items!$A$2:$A$1032,0)) -> #N/A
A87: =IF(OR(D87<>D86,D87=""),1,IF(NOT(AND(E87=E86,F87=F86,G87=G86)),A86+1,IF(OR(H87="",AND(H87<>"",H87<>H86,H86<>"")),A86,A86+1))) -> 1 | B87: =IF(D87<>"",TEXT(D87,"YYYYMMDD")&CHAR(64+A87),"") | C87: =IF(OR(B87="",B87<>B86),1,C86+1) -> 1 | F87: =INDEX(Establishment!B$2:B$1005,MATCH($E87,Establishment!$A$2:$A$1005,0)) -> #N/A | G87: =INDEX(Establishment!C$2:C$1005,MATCH($E87,Establishment!$A$2:$A$1005,0)) -> #N/A | M87: =K87*L87 -> 0 | N87: =IF(B87=B86,N86+M87,M87) -> 0 | P87: =INDEX(Items!B$2:B$1032,MATCH($O87,Items!$A$2:$A$1032,0)) -> #N/A | Q87: =INDEX(Items!C$2:C$1032,MATCH($O87,Items!$A$2:$A$1032,0)) -> #N/A | R87: =INDEX(Items!D$2:D$1032,MATCH($O87,Items!$A$2:$A$1032,0)) -> #N/A
A88: =IF(OR(D88<>D87,D88=""),1,IF(NOT(AND(E88=E87,F88=F87,G88=G87)),A87+1,IF(OR(H88="",AND(H88<>"",H88<>H87,H87<>"")),A87,A87+1))) -> 1 | B88: =IF(D88<>"",TEXT(D88,"YYYYMMDD")&CHAR(64+A88),"") | C88: =IF(OR(B88="",B88<>B87),1,C87+1) -> 1 | F88: =INDEX(Establishment!B$2:B$1005,MATCH($E88,Establishment!$A$2:$A$1005,0)) -> #N/A | G88: =INDEX(Establishment!C$2:C$1005,MATCH($E88,Establishment!$A$2:$A$1005,0)) -> #N/A | M88: =K88*L88 -> 0 | N88: =IF(B88=B87,N87+M88,M88) -> 0 | P88: =INDEX(Items!B$2:B$1032,MATCH($O88,Items!$A$2:$A$1032,0)) -> #N/A | Q88: =INDEX(Items!C$2:C$1032,MATCH($O88,Items!$A$2:$A$1032,0)) -> #N/A | R88: =INDEX(Items!D$2:D$1032,MATCH($O88,Items!$A$2:$A$1032,0)) -> #N/A
A89: =IF(OR(D89<>D88,D89=""),1,IF(NOT(AND(E89=E88,F89=F88,G89=G88)),A88+1,IF(OR(H89="",AND(H89<>"",H89<>H88,H88<>"")),A88,A88+1))) -> 1 | B89: =IF(D89<>"",TEXT(D89,"YYYYMMDD")&CHAR(64+A89),"") | C89: =IF(OR(B89="",B89<>B88),1,C88+1) -> 1 | F89: =INDEX(Establishment!B$2:B$1005,MATCH($E89,Establishment!$A$2:$A$1005,0)) -> #N/A | G89: =INDEX(Establishment!C$2:C$1005,MATCH($E89,Establishment!$A$2:$A$1005,0)) -> #N/A | M89: =K89*L89 -> 0 | N89: =IF(B89=B88,N88+M89,M89) -> 0 | P89: =INDEX(Items!B$2:B$1032,MATCH($O89,Items!$A$2:$A$1032,0)) -> #N/A | Q89: =INDEX(Items!C$2:C$1032,MATCH($O89,Items!$A$2:$A$1032,0)) -> #N/A | R89: =INDEX(Items!D$2:D$1032,MATCH($O89,Items!$A$2:$A$1032,0)) -> #N/A
A90: =IF(OR(D90<>D89,D90=""),1,IF(NOT(AND(E90=E89,F90=F89,G90=G89)),A89+1,IF(OR(H90="",AND(H90<>"",H90<>H89,H89<>"")),A89,A89+1))) -> 1 | B90: =IF(D90<>"",TEXT(D90,"YYYYMMDD")&CHAR(64+A90),"") | C90: =IF(OR(B90="",B90<>B89),1,C89+1) -> 1 | F90: =INDEX(Establishment!B$2:B$1005,MATCH($E90,Establishment!$A$2:$A$1005,0)) -> #N/A | G90: =INDEX(Establishment!C$2:C$1005,MATCH($E90,Establishment!$A$2:$A$1005,0)) -> #N/A | M90: =K90*L90 -> 0 | N90: =IF(B90=B89,N89+M90,M90) -> 0 | P90: =INDEX(Items!B$2:B$1032,MATCH($O90,Items!$A$2:$A$1032,0)) -> #N/A | Q90: =INDEX(Items!C$2:C$1032,MATCH($O90,Items!$A$2:$A$1032,0)) -> #N/A | R90: =INDEX(Items!D$2:D$1032,MATCH($O90,Items!$A$2:$A$1032,0)) -> #N/A
A91: =IF(OR(D91<>D90,D91=""),1,IF(NOT(AND(E91=E90,F91=F90,G91=G90)),A90+1,IF(OR(H91="",AND(H91<>"",H91<>H90,H90<>"")),A90,A90+1))) -> 1 | B91: =IF(D91<>"",TEXT(D91,"YYYYMMDD")&CHAR(64+A91),"") | C91: =IF(OR(B91="",B91<>B90),1,C90+1) -> 1 | F91: =INDEX(Establishment!B$2:B$1005,MATCH($E91,Establishment!$A$2:$A$1005,0)) -> #N/A | G91: =INDEX(Establishment!C$2:C$1005,MATCH($E91,Establishment!$A$2:$A$1005,0)) -> #N/A | M91: =K91*L91 -> 0 | N91: =IF(B91=B90,N90+M91,M91) -> 0 | P91: =INDEX(Items!B$2:B$1032,MATCH($O91,Items!$A$2:$A$1032,0)) -> #N/A | Q91: =INDEX(Items!C$2:C$1032,MATCH($O91,Items!$A$2:$A$1032,0)) -> #N/A | R91: =INDEX(Items!D$2:D$1032,MATCH($O91,Items!$A$2:$A$1032,0)) -> #N/A
A92: =IF(OR(D92<>D91,D92=""),1,IF(NOT(AND(E92=E91,F92=F91,G92=G91)),A91+1,IF(OR(H92="",AND(H92<>"",H92<>H91,H91<>"")),A91,A91+1))) -> 1 | B92: =IF(D92<>"",TEXT(D92,"YYYYMMDD")&CHAR(64+A92),"") | C92: =IF(OR(B92="",B92<>B91),1,C91+1) -> 1 | F92: =INDEX(Establishment!B$2:B$1005,MATCH($E92,Establishment!$A$2:$A$1005,0)) -> #N/A | G92: =INDEX(Establishment!C$2:C$1005,MATCH($E92,Establishment!$A$2:$A$1005,0)) -> #N/A | M92: =K92*L92 -> 0 | N92: =IF(B92=B91,N91+M92,M92) -> 0 | P92: =INDEX(Items!B$2:B$1032,MATCH($O92,Items!$A$2:$A$1032,0)) -> #N/A | Q92: =INDEX(Items!C$2:C$1032,MATCH($O92,Items!$A$2:$A$1032,0)) -> #N/A | R92: =INDEX(Items!D$2:D$1032,MATCH($O92,Items!$A$2:$A$1032,0)) -> #N/A
A93: =IF(OR(D93<>D92,D93=""),1,IF(NOT(AND(E93=E92,F93=F92,G93=G92)),A92+1,IF(OR(H93="",AND(H93<>"",H93<>H92,H92<>"")),A92,A92+1))) -> 1 | B93: =IF(D93<>"",TEXT(D93,"YYYYMMDD")&CHAR(64+A93),"") | C93: =IF(OR(B93="",B93<>B92),1,C92+1) -> 1 | F93: =INDEX(Establishment!B$2:B$1005,MATCH($E93,Establishment!$A$2:$A$1005,0)) | G93: =INDEX(Establishment!C$2:C$1005,MATCH($E93,Establishment!$A$2:$A$1005,0)) | M93: =K93*L93 -> 0 | N93: =IF(B93=B92,N92+M93,M93) -> 0 | P93: =INDEX(Items!B$2:B$1032,MATCH($O93,Items!$A$2:$A$1032,0)) -> #N/A | Q93: =INDEX(Items!C$2:C$1032,MATCH($O93,Items!$A$2:$A$1032,0)) -> #N/A | R93: =INDEX(Items!D$2:D$1032,MATCH($O93,Items!$A$2:$A$1032,0)) -> #N/A
A94: =IF(OR(D94<>D93,D94=""),1,IF(NOT(AND(E94=E93,F94=F93,G94=G93)),A93+1,IF(OR(H94="",AND(H94<>"",H94<>H93,H93<>"")),A93,A93+1))) -> 1 | B94: =IF(D94<>"",TEXT(D94,"YYYYMMDD")&CHAR(64+A94),"") | C94: =IF(OR(B94="",B94<>B93),1,C93+1) -> 1 | F94: =INDEX(Establishment!B$2:B$1005,MATCH($E94,Establishment!$A$2:$A$1005,0)) | G94: =INDEX(Establishment!C$2:C$1005,MATCH($E94,Establishment!$A$2:$A$1005,0)) | M94: =K94*L94 -> 0 | N94: =IF(B94=B93,N93+M94,M94) -> 0 | P94: =INDEX(Items!B$2:B$1032,MATCH($O94,Items!$A$2:$A$1032,0)) -> #N/A | Q94: =INDEX(Items!C$2:C$1032,MATCH($O94,Items!$A$2:$A$1032,0)) -> #N/A | R94: =INDEX(Items!D$2:D$1032,MATCH($O94,Items!$A$2:$A$1032,0)) -> #N/A
... A98: =IF(OR(D98<>D97,D98=""),1,IF(NOT(AND(E98=E97,F98=F97,G98=G97)),A97+1,IF(OR(H98="",AND(H98<>"",H98<>H97,H97<>"")),A97,A97+1))) -> 1 | B98: =IF(D98<>"",TEXT(D98,"YYYYMMDD")&CHAR(64+A98),"") | C98: =IF(OR(B98="",B98<>B97),1,C97+1) -> 1 | F98: =INDEX(Establishment!B$2:B$1005,MATCH($E98,Establishment!$A$2:$A$1005,0)) | G98: =INDEX(Establishment!C$2:C$1005,MATCH($E98,Establishment!$A$2:$A$1005,0)) | M98: =K98*L98 -> 0 | N98: =IF(B98=B97,N97+M98,M98) -> 0 | P98: =INDEX(Items!B$2:B$1032,MATCH($O98,Items!$A$2:$A$1032,0)) -> #N/A | Q98: =INDEX(Items!C$2:C$1032,MATCH($O98,Items!$A$2:$A$1032,0)) -> #N/A | R98: =INDEX(Items!D$2:D$1032,MATCH($O98,Items!$A$2:$A$1032,0)) -> #N/A
A99: =IF(OR(D99<>D98,D99=""),1,IF(NOT(AND(E99=E98,F99=F98,G99=G98)),A98+1,IF(OR(H99="",AND(H99<>"",H99<>H98,H98<>"")),A98,A98+1))) -> 1 | B99: =IF(D99<>"",TEXT(D99,"YYYYMMDD")&CHAR(64+A99),"") -> 20230621A | C99: =IF(OR(B99="",B99<>B98),1,C98+1) -> 1 | D99: 45098 | E99: Carenderia 14th Floor-ACC Tower Cebu Business Park | F99: =INDEX(Establishment!B$2:B$1005,MATCH($E99,Establishment!$A$2:$A$1005,0)) -> Carenderia 14th Floor | G99: =INDEX(Establishment!C$2:C$1005,MATCH($E99,Establishment!$A$2:$A$1005,0)) -> ACC Tower Cebu Business Park | M99: =K99*L99 -> 0 | N99: =IF(B99=B98,N98+M99,M99) -> 0 | P99: =INDEX(Items!B$2:B$1032,MATCH($O99,Items!$A$2:$A$1032,0)) -> #N/A | Q99: =INDEX(Items!C$2:C$1032,MATCH($O99,Items!$A$2:$A$1032,0)) -> #N/A | R99: =INDEX(Items!D$2:D$1032,MATCH($O99,Items!$A$2:$A$1032,0)) -> #N/A
A100: =IF(OR(D100<>D99,D100=""),1,IF(NOT(AND(E100=E99,F100=F99,G100=G99)),A99+1,IF(OR(H100="",AND(H100<>"",H100<>H99,H99<>"")),A99,A99+1))) -> 1 | B100: =IF(D100<>"",TEXT(D100,"YYYYMMDD")&CHAR(64+A100),"") | C100: =IF(OR(B100="",B100<>B99),1,C99+1) -> 1 | F100: =INDEX(Establishment!B$2:B$1005,MATCH($E100,Establishment!$A$2:$A$1005,0)) -> #N/A | G100: =INDEX(Establishment!C$2:C$1005,MATCH($E100,Establishment!$A$2:$A$1005,0)) -> #N/A | M100: =K100*L100 -> 0 | N100: =IF(B100=B99,N99+M100,M100) -> 0 | P100: =INDEX(Items!B$2:B$1032,MATCH($O100,Items!$A$2:$A$1032,0)) -> #N/A | Q100: =INDEX(Items!C$2:C$1032,MATCH($O100,Items!$A$2:$A$1032,0)) -> #N/A | R100: =INDEX(Items!D$2:D$1032,MATCH($O100,Items!$A$2:$A$1032,0)) -> #N/A
A101: =IF(OR(D101<>D100,D101=""),1,IF(NOT(AND(E101=E100,F101=F100,G101=G100)),A100+1,IF(OR(H101="",AND(H101<>"",H101<>H100,H100<>"")),A100,A100+1))) -> 1 | B101: =IF(D101<>"",TEXT(D101,"YYYYMMDD")&CHAR(64+A101),"") | C101: =IF(OR(B101="",B101<>B100),1,C100+1) -> 1 | F101: =INDEX(Establishment!B$2:B$1005,MATCH($E101,Establishment!$A$2:$A$1005,0)) | G101: =INDEX(Establishment!C$2:C$1005,MATCH($E101,Establishment!$A$2:$A$1005,0)) | M101: =K101*L101 -> 0 | N101: =IF(B101=B100,N100+M101,M101) -> 0 | P101: =INDEX(Items!B$2:B$1032,MATCH($O101,Items!$A$2:$A$1032,0)) -> #N/A | Q101: =INDEX(Items!C$2:C$1032,MATCH($O101,Items!$A$2:$A$1032,0)) -> #N/A | R101: =INDEX(Items!D$2:D$1032,MATCH($O101,Items!$A$2:$A$1032,0)) -> #N/A
A102: =IF(OR(D102<>D101,D102=""),1,IF(NOT(AND(E102=E101,F102=F101,G102=G101)),A101+1,IF(OR(H102="",AND(H102<>"",H102<>H101,H101<>"")),A101,A101+1))) -> 1 | B102: =IF(D102<>"",TEXT(D102,"YYYYMMDD")&CHAR(64+A102),"") | C102: =IF(OR(B102="",B102<>B101),1,C101+1) -> 1 | F102: =INDEX(Establishment!B$2:B$1005,MATCH($E102,Establishment!$A$2:$A$1005,0)) | G102: =INDEX(Establishment!C$2:C$1005,MATCH($E102,Establishment!$A$2:$A$1005,0)) | M102: =K102*L102 -> 0 | N102: =IF(B102=B101,N101+M102,M102) -> 0 | P102: =INDEX(Items!B$2:B$1032,MATCH($O102,Items!$A$2:$A$1032,0)) -> #N/A | Q102: =INDEX(Items!C$2:C$1032,MATCH($O102,Items!$A$2:$A$1032,0)) -> #N/A | R102: =INDEX(Items!D$2:D$1032,MATCH($O102,Items!$A$2:$A$1032,0)) -> #N/A
A103: =IF(OR(D103<>D102,D103=""),1,IF(NOT(AND(E103=E102,F103=F102,G103=G102)),A102+1,IF(OR(H103="",AND(H103<>"",H103<>H102,H102<>"")),A102,A102+1))) -> 1 | B103: =IF(D103<>"",TEXT(D103,"YYYYMMDD")&CHAR(64+A103),"") | C103: =IF(OR(B103="",B103<>B102),1,C102+1) -> 1 | F103: =INDEX(Establishment!B$2:B$1005,MATCH($E103,Establishment!$A$2:$A$1005,0)) | G103: =INDEX(Establishment!C$2:C$1005,MATCH($E103,Establishment!$A$2:$A$1005,0)) | M103: =K103*L103 -> 0 | N103: =IF(B103=B102,N102+M103,M103) -> 0 | P103: =INDEX(Items!B$2:B$1032,MATCH($O103,Items!$A$2:$A$1032,0)) -> #N/A | Q103: =INDEX(Items!C$2:C$1032,MATCH($O103,Items!$A$2:$A$1032,0)) -> #N/A | R103: =INDEX(Items!D$2:D$1032,MATCH($O103,Items!$A$2:$A$1032,0)) -> #N/A
A104: =IF(OR(D104<>D103,D104=""),1,IF(NOT(AND(E104=E103,F104=F103,G104=G103)),A103+1,IF(OR(H104="",AND(H104<>"",H104<>H103,H103<>"")),A103,A103+1))) -> 1 | B104: =IF(D104<>"",TEXT(D104,"YYYYMMDD")&CHAR(64+A104),"") | C104: =IF(OR(B104="",B104<>B103),1,C103+1) -> 1 | F104: =INDEX(Establishment!B$2:B$1005,MATCH($E104,Establishment!$A$2:$A$1005,0)) | G104: =INDEX(Establishment!C$2:C$1005,MATCH($E104,Establishment!$A$2:$A$1005,0)) | M104: =K104*L104 -> 0 | N104: =IF(B104=B103,N103+M104,M104) -> 0 | P104: =INDEX(Items!B$2:B$1032,MATCH($O104,Items!$A$2:$A$1032,0)) -> #N/A | Q104: =INDEX(Items!C$2:C$1032,MATCH($O104,Items!$A$2:$A$1032,0)) -> #N/A | R104: =INDEX(Items!D$2:D$1032,MATCH($O104,Items!$A$2:$A$1032,0)) -> #N/A
A105: =IF(OR(D105<>D104,D105=""),1,IF(NOT(AND(E105=E104,F105=F104,G105=G104)),A104+1,IF(OR(H105="",AND(H105<>"",H105<>H104,H104<>"")),A104,A104+1))) -> 1 | B105: =IF(D105<>"",TEXT(D105,"YYYYMMDD")&CHAR(64+A105),"") | C105: =IF(OR(B105="",B105<>B104),1,C104+1) -> 1 | F105: =INDEX(Establishment!B$2:B$1005,MATCH($E105,Establishment!$A$2:$A$1005,0)) | G105: =INDEX(Establishment!C$2:C$1005,MATCH($E105,Establishment!$A$2:$A$1005,0)) | M105: =K105*L105 -> 0 | N105: =IF(B105=B104,N104+M105,M105) -> 0 | P105: =INDEX(Items!B$2:B$1032,MATCH($O105,Items!$A$2:$A$1032,0)) -> #N/A | Q105: =INDEX(Items!C$2:C$1032,MATCH($O105,Items!$A$2:$A$1032,0)) -> #N/A | R105: =INDEX(Items!D$2:D$1032,MATCH($O105,Items!$A$2:$A$1032,0)) -> #N/A
A106: =IF(OR(D106<>D105,D106=""),1,IF(NOT(AND(E106=E105,F106=F105,G106=G105)),A105+1,IF(OR(H106="",AND(H106<>"",H106<>H105,H105<>"")),A105,A105+1))) -> 1 | B106: =IF(D106<>"",TEXT(D106,"YYYYMMDD")&CHAR(64+A106),"") | C106: =IF(OR(B106="",B106<>B105),1,C105+1) -> 1 | F106: =INDEX(Establishment!B$2:B$1005,MATCH($E106,Establishment!$A$2:$A$1005,0)) | G106: =INDEX(Establishment!C$2:C$1005,MATCH($E106,Establishment!$A$2:$A$1005,0)) | M106: =K106*L106 -> 0 | N106: =IF(B106=B105,N105+M106,M106) -> 0 | P106: =INDEX(Items!B$2:B$1032,MATCH($O106,Items!$A$2:$A$1032,0)) -> #N/A | Q106: =INDEX(Items!C$2:C$1032,MATCH($O106,Items!$A$2:$A$1032,0)) -> #N/A | R106: =INDEX(Items!D$2:D$1032,MATCH($O106,Items!$A$2:$A$1032,0)) -> #N/A
A107: =IF(OR(D107<>D106,D107=""),1,IF(NOT(AND(E107=E106,F107=F106,G107=G106)),A106+1,IF(OR(H107="",AND(H107<>"",H107<>H106,H106<>"")),A106,A106+1))) -> 1 | B107: =IF(D107<>"",TEXT(D107,"YYYYMMDD")&CHAR(64+A107),"") | C107: =IF(OR(B107="",B107<>B106),1,C106+1) -> 1 | F107: =INDEX(Establishment!B$2:B$1005,MATCH($E107,Establishment!$A$2:$A$1005,0)) | G107: =INDEX(Establishment!C$2:C$1005,MATCH($E107,Establishment!$A$2:$A$1005,0)) | M107: =K107*L107 -> 0 | N107: =IF(B107=B106,N106+M107,M107) -> 0 | P107: =INDEX(Items!B$2:B$1032,MATCH($O107,Items!$A$2:$A$1032,0)) -> #N/A | Q107: =INDEX(Items!C$2:C$1032,MATCH($O107,Items!$A$2:$A$1032,0)) -> #N/A | R107: =INDEX(Items!D$2:D$1032,MATCH($O107,Items!$A$2:$A$1032,0)) -> #N/A
A108: =IF(OR(D108<>D107,D108=""),1,IF(NOT(AND(E108=E107,F108=F107,G108=G107)),A107+1,IF(OR(H108="",AND(H108<>"",H108<>H107,H107<>"")),A107,A107+1))) -> 1 | B108: =IF(D108<>"",TEXT(D108,"YYYYMMDD")&CHAR(64+A108),"") | C108: =IF(OR(B108="",B108<>B107),1,C107+1) -> 1 | F108: =INDEX(Establishment!B$2:B$1005,MATCH($E108,Establishment!$A$2:$A$1005,0)) | G108: =INDEX(Establishment!C$2:C$1005,MATCH($E108,Establishment!$A$2:$A$1005,0)) | M108: =K108*L108 -> 0 | N108: =IF(B108=B107,N107+M108,M108) -> 0 | P108: =INDEX(Items!B$2:B$1032,MATCH($O108,Items!$A$2:$A$1032,0)) -> #N/A | Q108: =INDEX(Items!C$2:C$1032,MATCH($O108,Items!$A$2:$A$1032,0)) -> #N/A | R108: =INDEX(Items!D$2:D$1032,MATCH($O108,Items!$A$2:$A$1032,0)) -> #N/A
A109: =IF(OR(D109<>D108,D109=""),1,IF(NOT(AND(E109=E108,F109=F108,G109=G108)),A108+1,IF(OR(H109="",AND(H109<>"",H109<>H108,H108<>"")),A108,A108+1))) -> 1 | B109: =IF(D109<>"",TEXT(D109,"YYYYMMDD")&CHAR(64+A109),"") | C109: =IF(OR(B109="",B109<>B108),1,C108+1) -> 1 | F109: =INDEX(Establishment!B$2:B$1005,MATCH($E109,Establishment!$A$2:$A$1005,0)) | G109: =INDEX(Establishment!C$2:C$1005,MATCH($E109,Establishment!$A$2:$A$1005,0)) | M109: =K109*L109 -> 0 | N109: =IF(B109=B108,N108+M109,M109) -> 0 | P109: =INDEX(Items!B$2:B$1032,MATCH($O109,Items!$A$2:$A$1032,0)) -> #N/A | Q109: =INDEX(Items!C$2:C$1032,MATCH($O109,Items!$A$2:$A$1032,0)) -> #N/A | R109: =INDEX(Items!D$2:D$1032,MATCH($O109,Items!$A$2:$A$1032,0)) -> #N/A
